[
  {
    "text": "This is a NIST 800-171 control in the Access Control family. It corresponds to Level 1, Level 2. The control ID is AC.L1-3.1.1 with title 'AUTHORIZED ACCESS CONTROL'. Security requirement: Limit system access to authorized users, processes acting on behalf of authorized users, and devices (including other systems).. Assessment objective (3.1.1[a]): authorized users are identified.. POA&M allowed: No. SPRS score: 5.\nThis is a NIST 800-171 control in the Access Control family. It corresponds to Level 1, Level 2. The control ID is AC.L1-3.1.1 with title 'AUTHORIZED ACCESS CONTROL'. Security requirement: Limit system access to authorized users, processes acting on behalf of authorized users, and devices (including other systems).. Assessment objective (3.1.1[b]): processes acting on behalf of authorized users are identified.. POA&M allowed: No. SPRS score: 5.\nThis is a NIST 800-171 control in the Access Control family. It corresponds to Level 1, Level 2. The control ID is AC.L1-3.1.1 with title 'AUTHORIZED ACCESS CONTROL'. Security requirement: Limit system access to authorized users, processes acting on behalf of authorized users, and devices (including other systems).. Assessment objective (3.1.1[c]): devices (including other systems) authorized to connect to the system are identified.. POA&M allowed: No. SPRS score: 5.\nThis is a NIST 800-171 control in the Access Control family. It corresponds to Level 1, Level 2. The control ID is AC.L1-3.1.1 with title 'AUTHORIZED ACCESS CONTROL'. Security requirement: Limit system access to authorized users, processes acting on behalf of authorized users, and devices (including other systems).. Assessment objective (3.1.1[d]): system access is limited to authorized users.. POA&M allowed: No. SPRS score: 5.\nThis is a NIST 800-171 control in the Access Control family. It corresponds to Level 1, Level 2. The control ID is AC.L1-3.1.1 with title 'AUTHORIZED ACCESS CONTROL'. Security requirement: Limit system access to authorized users, processes acting on behalf of authorized users, and devices (including other systems).. Assessment objective (3.1.1[e]): system access is limited to processes acting on behalf of authorized users.. POA&M allowed: No. SPRS score: 5.\nThis is a NIST 800-171 control in the Access Control family. It corresponds to Level 1, Level 2. The control ID is AC.L1-3.1.1 with title 'AUTHORIZED ACCESS CONTROL'. Security requirement: Limit system access to authorized users, processes acting on behalf of authorized users, and devices (including other systems).. Assessment objective (3.1.1[f]): system access is limited to authorized devices (including other systems).. POA&M allowed: No. SPRS score: 5.",
    "metadata": {
      "framework": "NIST 800-171",
      "family": "Access Control",
      "control_id": "3.1.1",
      "cmmc_id": "AC.L1-3.1.1",
      "title": "AUTHORIZED ACCESS CONTROL",
      "sprs": 5,
      "cmmc_levels": [
        "Level 1",
        "Level 2"
      ],
      "poam_allowed": "No",
      "ao_ids": [
        "3.1.1[a]",
        "3.1.1[b]",
        "3.1.1[c]",
        "3.1.1[d]",
        "3.1.1[e]",
        "3.1.1[f]"
      ],
      "assessment_methods": [
        {
          "type": "Examine",
          "description": "[SELECT FROM: Access control policy; procedures addressing account management; security plan; system design documentation; system configuration settings and associated documentation; list of active system accounts and the name of the individual associated with each account; list of conditions for group and role membership; notifications or records of recently transferred, separated, or terminated employees; list of recently disabled system accounts along with the name of the individual associated with each account; access authorization records; account management compliance reviews; system monitoring records; system audit logs and records; other relevant documents or records; list of devices and other systems authorized to connect to organizational systems]."
        },
        {
          "type": "Interview",
          "description": "[SELECT FROM: Personnel with account management responsibilities; system or network administrators; personnel with information security responsibilities]."
        },
        {
          "type": "Test",
          "description": "[SELECT FROM: Organizational processes for managing system accounts; mechanisms for implementing account management]."
        }
      ]
    },
    "last_ao_sentence": "system access is limited to authorized devices (including other systems)."
  },
  {
    "text": "This is a NIST 800-171 control in the Access Control family. It corresponds to Level 1, Level 2. The control ID is AC.L1-3.1.2 with title 'TRANSACTION & FUNCTION CONTROL'. Security requirement: Limit system access to the types of transactions and functions that authorized users are permitted to execute.. Assessment objective (3.1.2[a]): the types of transactions and functions that authorized users are permitted to execute are defined. POA&M allowed: No. SPRS score: 5.\nThis is a NIST 800-171 control in the Access Control family. It corresponds to Level 1, Level 2. The control ID is AC.L1-3.1.2 with title 'TRANSACTION & FUNCTION CONTROL'. Security requirement: Limit system access to the types of transactions and functions that authorized users are permitted to execute.. Assessment objective (3.1.2[b]): system access is limited to the defined types of transactions and functions for authorized users.. POA&M allowed: No. SPRS score: 5.",
    "metadata": {
      "framework": "NIST 800-171",
      "family": "Access Control",
      "control_id": "3.1.2",
      "cmmc_id": "AC.L1-3.1.2",
      "title": "TRANSACTION & FUNCTION CONTROL",
      "sprs": 5,
      "cmmc_levels": [
        "Level 1",
        "Level 2"
      ],
      "poam_allowed": "No",
      "ao_ids": [
        "3.1.2[a]",
        "3.1.2[b]"
      ],
      "assessment_methods": [
        {
          "type": "Examine",
          "description": "[SELECT FROM: Access control policy; procedures addressing access enforcement; security plan; system design documentation; list of approved authorizations (user privileges) including remote access authorizations; system configuration settings and associated documentation; system audit logs and records; other relevant documents or records]."
        },
        {
          "type": "Interview",
          "description": "[SELECT FROM: Personnel with access enforcement responsibilities; system or network administrators; personnel with information security responsibilities; system developers]."
        },
        {
          "type": "Test",
          "description": "[SELECT FROM: Mechanisms implementing access control policy]."
        }
      ]
    },
    "last_ao_sentence": "system access is limited to the defined types of transactions and functions for authorized users."
  },
  {
    "text": "This is a NIST 800-171 control in the Access Control family. It corresponds to Level 2. The control ID is AC.L2-3.1.3 with title 'CONTROL CUI FLOW'. Security requirement: Control the flow of CUI in accordance with approved authorizations.. Assessment objective (3.1.3[a]): information flow control policies are defined.. POA&M allowed: Yes. SPRS score: 1.\nThis is a NIST 800-171 control in the Access Control family. It corresponds to Level 2. The control ID is AC.L2-3.1.3 with title 'CONTROL CUI FLOW'. Security requirement: Control the flow of CUI in accordance with approved authorizations.. Assessment objective (3.1.3[b]): methods and enforcement mechanisms for controlling the flow of CUI are defined.. POA&M allowed: Yes. SPRS score: 1.\nThis is a NIST 800-171 control in the Access Control family. It corresponds to Level 2. The control ID is AC.L2-3.1.3 with title 'CONTROL CUI FLOW'. Security requirement: Control the flow of CUI in accordance with approved authorizations.. Assessment objective (3.1.3[c]): \tdesignated sources and destinations (e.g., networks, individuals, and devices) for CUI within systems and between interconnected systems are identified.. POA&M allowed: Yes. SPRS score: 1.\nThis is a NIST 800-171 control in the Access Control family. It corresponds to Level 2. The control ID is AC.L2-3.1.3 with title 'CONTROL CUI FLOW'. Security requirement: Control the flow of CUI in accordance with approved authorizations.. Assessment objective (3.1.3[d]): \tauthorizations for controlling the flow of CUI are defined.. POA&M allowed: Yes. SPRS score: 1.\nThis is a NIST 800-171 control in the Access Control family. It corresponds to Level 2. The control ID is AC.L2-3.1.3 with title 'CONTROL CUI FLOW'. Security requirement: Control the flow of CUI in accordance with approved authorizations.. Assessment objective (3.1.3[e]): approved authorizations for controlling the flow of CUI are enforced.. POA&M allowed: Yes. SPRS score: 1.",
    "metadata": {
      "framework": "NIST 800-171",
      "family": "Access Control",
      "control_id": "3.1.3",
      "cmmc_id": "AC.L2-3.1.3",
      "title": "CONTROL CUI FLOW",
      "sprs": 1,
      "cmmc_levels": [
        "Level 2"
      ],
      "poam_allowed": "Yes",
      "ao_ids": [
        "3.1.3[a]",
        "3.1.3[b]",
        "3.1.3[c]",
        "3.1.3[d]",
        "3.1.3[e]"
      ],
      "assessment_methods": [
        {
          "type": "Examine",
          "description": "[SELECT FROM: Access control policy; information flow control policies; procedures addressing information flow enforcement; security plan; system design documentation; system configuration settings and associated documentation; list of information flow authorizations; system baseline configuration; system audit logs and records; other relevant documents or records]."
        },
        {
          "type": "Interview",
          "description": "[SELECT FROM: System or network administrators; personnel with information security responsibilities; system developers]."
        },
        {
          "type": "Test",
          "description": "[SELECT FROM: Mechanisms implementing information flow enforcement policy]."
        }
      ]
    },
    "last_ao_sentence": "approved authorizations for controlling the flow of CUI are enforced."
  },
  {
    "text": "This is a NIST 800-171 control in the Access Control family. It corresponds to Level 2. The control ID is AC.L2-3.1.4 with title 'SEPARATION OF DUTIES'. Security requirement: Separate the duties of individuals to reduce the risk of malevolent activity without collusion.. Assessment objective (3.1.4[a]): the duties of individuals requiring separation are defined. POA&M allowed: Yes. SPRS score: 1.\nThis is a NIST 800-171 control in the Access Control family. It corresponds to Level 2. The control ID is AC.L2-3.1.4 with title 'SEPARATION OF DUTIES'. Security requirement: Separate the duties of individuals to reduce the risk of malevolent activity without collusion.. Assessment objective (3.1.4[b]): responsibilities for duties that require separation are assigned to separate individuals. POA&M allowed: Yes. SPRS score: 1.\nThis is a NIST 800-171 control in the Access Control family. It corresponds to Level 2. The control ID is AC.L2-3.1.4 with title 'SEPARATION OF DUTIES'. Security requirement: Separate the duties of individuals to reduce the risk of malevolent activity without collusion.. Assessment objective (3.1.4[c]): access privileges that enable individuals to exercise the duties that require separation are granted to separate individuals. POA&M allowed: Yes. SPRS score: 1.",
    "metadata": {
      "framework": "NIST 800-171",
      "family": "Access Control",
      "control_id": "3.1.4",
      "cmmc_id": "AC.L2-3.1.4",
      "title": "SEPARATION OF DUTIES",
      "sprs": 1,
      "cmmc_levels": [
        "Level 2"
      ],
      "poam_allowed": "Yes",
      "ao_ids": [
        "3.1.4[a]",
        "3.1.4[b]",
        "3.1.4[c]"
      ],
      "assessment_methods": [
        {
          "type": "Examine",
          "description": "[SELECT FROM: Access control policy; procedures addressing divisions of responsibility and separation of duties; security plan; system configuration settings and associated documentation; list of divisions of responsibility and separation of duties; system access authorizations; system audit logs and records; other relevant documents or records]."
        },
        {
          "type": "Interview",
          "description": "[SELECT FROM: Personnel with responsibilities for defining divisions of responsibility and separation of duties; personnel with information security responsibilities; system or network administrators]."
        },
        {
          "type": "Test",
          "description": "[SELECT FROM: Mechanisms implementing separation of duties policy]."
        }
      ]
    },
    "last_ao_sentence": "access privileges that enable individuals to exercise the duties that require separation are granted to separate individuals"
  },
  {
    "text": "This is a NIST 800-171 control in the Access Control family. It corresponds to Level 2. The control ID is AC.L2-3.1.5 with title 'LEAST PRIVILEGE'. Security requirement: Employ the principle of least privilege, including for specific security functions and privileged accounts.. Assessment objective (3.1.5[a]): privileged accounts are identified.. POA&M allowed: No. SPRS score: 3.\nThis is a NIST 800-171 control in the Access Control family. It corresponds to Level 2. The control ID is AC.L2-3.1.5 with title 'LEAST PRIVILEGE'. Security requirement: Employ the principle of least privilege, including for specific security functions and privileged accounts.. Assessment objective (3.1.5[b]): access to privileged accounts is authorized in accordance with the principle of least privilege.. POA&M allowed: No. SPRS score: 3.\nThis is a NIST 800-171 control in the Access Control family. It corresponds to Level 2. The control ID is AC.L2-3.1.5 with title 'LEAST PRIVILEGE'. Security requirement: Employ the principle of least privilege, including for specific security functions and privileged accounts.. Assessment objective (3.1.5[c]): security functions are identified.. POA&M allowed: No. SPRS score: 3.\nThis is a NIST 800-171 control in the Access Control family. It corresponds to Level 2. The control ID is AC.L2-3.1.5 with title 'LEAST PRIVILEGE'. Security requirement: Employ the principle of least privilege, including for specific security functions and privileged accounts.. Assessment objective (3.1.5[d]): access to security functions is authorized in accordance with the principle of least privilege.. POA&M allowed: No. SPRS score: 3.",
    "metadata": {
      "framework": "NIST 800-171",
      "family": "Access Control",
      "control_id": "3.1.5",
      "cmmc_id": "AC.L2-3.1.5",
      "title": "LEAST PRIVILEGE",
      "sprs": 3,
      "cmmc_levels": [
        "Level 2"
      ],
      "poam_allowed": "No",
      "ao_ids": [
        "3.1.5[a]",
        "3.1.5[b]",
        "3.1.5[c]",
        "3.1.5[d]"
      ],
      "assessment_methods": [
        {
          "type": "Examine",
          "description": "[SELECT FROM: Access control policy; procedures addressing account management; security plan; system design documentation; system configuration settings and associated documentation; list of active system accounts and the name of the individual associated with each account; list of conditions for group and role membership; notifications or records of recently transferred, separated, or terminated employees; list of recently disabled system accounts along with the name of the individual associated with each account; access authorization records; account management compliance reviews; system monitoring/audit records; other relevant documents or records; procedures addressing least privilege; list of security functions (deployed in hardware, software, and firmware) and security-relevant information for which access must be explicitly authorized; list of system-generated privileged accounts; list of system administration personnel]."
        },
        {
          "type": "Interview",
          "description": "[SELECT FROM: Personnel with account management responsibilities; system or network administrators; personnel with information security responsibilities; personnel with responsibilities for defining least privileges necessary to accomplish specified tasks]."
        },
        {
          "type": "Test",
          "description": "[SELECT FROM: Organizational processes for managing system accounts; mechanisms for implementing account management; mechanisms implementing least privilege functions; mechanisms prohibiting privileged access to the system]."
        }
      ]
    },
    "last_ao_sentence": "access to security functions is authorized in accordance with the principle of least privilege."
  },
  {
    "text": "This is a NIST 800-171 control in the Access Control family. It corresponds to Level 2. The control ID is AC.L2-3.1.6 with title 'NON-PRIVILEGED ACCOUNT USE'. Security requirement: Use non-privileged accounts or roles when accessing nonsecurity functions.. Assessment objective (3.1.6[a]): nonsecurity functions are identified.. POA&M allowed: No. SPRS score: 3.\nThis is a NIST 800-171 control in the Access Control family. It corresponds to Level 2. The control ID is AC.L2-3.1.6 with title 'NON-PRIVILEGED ACCOUNT USE'. Security requirement: Use non-privileged accounts or roles when accessing nonsecurity functions.. Assessment objective (3.1.6[b]): users are required to use non-privileged accounts or roles when accessing nonsecurity functions.. POA&M allowed: No. SPRS score: 3.",
    "metadata": {
      "framework": "NIST 800-171",
      "family": "Access Control",
      "control_id": "3.1.6",
      "cmmc_id": "AC.L2-3.1.6",
      "title": "NON-PRIVILEGED ACCOUNT USE",
      "sprs": 3,
      "cmmc_levels": [
        "Level 2"
      ],
      "poam_allowed": "No",
      "ao_ids": [
        "3.1.6[a]",
        "3.1.6[b]"
      ],
      "assessment_methods": [
        {
          "type": "Examine",
          "description": "[SELECT FROM: Access control policy; procedures addressing least privilege; security plan; list of system-generated security functions assigned to system accounts or roles; system configuration settings and associated documentation; system audit logs and records; other relevant documents or records]."
        },
        {
          "type": "Interview",
          "description": "[SELECT FROM: Personnel with responsibilities for defining least privileges necessary to accomplish specified organizational tasks; personnel with information security responsibilities; system or network administrators]."
        },
        {
          "type": "Test",
          "description": "[SELECT FROM: Mechanisms implementing least privilege functions]."
        }
      ]
    },
    "last_ao_sentence": "users are required to use non-privileged accounts or roles when accessing nonsecurity functions."
  },
  {
    "text": "This is a NIST 800-171 control in the Access Control family. It corresponds to Level 2. The control ID is AC.L2-3.1.7 with title 'PRIVILEGED FUNCTIONS'. Security requirement: Prevent non-privileged users from executing privileged functions and capture the execution of such functions in audit logs.. Assessment objective (3.1.7[a]): privileged functions are defined.. POA&M allowed: Yes. SPRS score: 1.\nThis is a NIST 800-171 control in the Access Control family. It corresponds to Level 2. The control ID is AC.L2-3.1.7 with title 'PRIVILEGED FUNCTIONS'. Security requirement: Prevent non-privileged users from executing privileged functions and capture the execution of such functions in audit logs.. Assessment objective (3.1.7[b]): non-privileged users are defined.. POA&M allowed: Yes. SPRS score: 1.\nThis is a NIST 800-171 control in the Access Control family. It corresponds to Level 2. The control ID is AC.L2-3.1.7 with title 'PRIVILEGED FUNCTIONS'. Security requirement: Prevent non-privileged users from executing privileged functions and capture the execution of such functions in audit logs.. Assessment objective (3.1.7[c]): non-privileged users are prevented from executing privileged functions.. POA&M allowed: Yes. SPRS score: 1.\nThis is a NIST 800-171 control in the Access Control family. It corresponds to Level 2. The control ID is AC.L2-3.1.7 with title 'PRIVILEGED FUNCTIONS'. Security requirement: Prevent non-privileged users from executing privileged functions and capture the execution of such functions in audit logs.. Assessment objective (3.1.7[d]): the execution of privileged functions is captured in audit logs.. POA&M allowed: Yes. SPRS score: 1.",
    "metadata": {
      "framework": "NIST 800-171",
      "family": "Access Control",
      "control_id": "3.1.7",
      "cmmc_id": "AC.L2-3.1.7",
      "title": "PRIVILEGED FUNCTIONS",
      "sprs": 1,
      "cmmc_levels": [
        "Level 2"
      ],
      "poam_allowed": "Yes",
      "ao_ids": [
        "3.1.7[a]",
        "3.1.7[b]",
        "3.1.7[c]",
        "3.1.7[d]"
      ],
      "assessment_methods": [
        {
          "type": "Examine",
          "description": "[SELECT FROM: Access control policy; procedures addressing least privilege; security plan; system design documentation; list of privileged functions and associated user account assignments; system configuration settings and associated documentation; system audit logs and records; other relevant documents or records]."
        },
        {
          "type": "Interview",
          "description": "[SELECT FROM: Personnel with responsibilities for defining least privileges necessary to accomplish specified tasks; personnel with information security responsibilities; system developers]."
        },
        {
          "type": "Test",
          "description": "[SELECT FROM: Mechanisms implementing least privilege functions for non-privileged users; mechanisms auditing the execution of privileged functions]."
        }
      ]
    },
    "last_ao_sentence": "the execution of privileged functions is captured in audit logs."
  },
  {
    "text": "This is a NIST 800-171 control in the Access Control family. It corresponds to Level 2. The control ID is AC.L2-3.1.8 with title 'UNSUCCESSFUL LOGON ATTEMPTS'. Security requirement: Limit unsuccessful logon attempts.. Assessment objective (3.1.8[a]): the means of limiting unsuccessful logon attempts is defined.. POA&M allowed: Yes. SPRS score: 1.\nThis is a NIST 800-171 control in the Access Control family. It corresponds to Level 2. The control ID is AC.L2-3.1.8 with title 'UNSUCCESSFUL LOGON ATTEMPTS'. Security requirement: Limit unsuccessful logon attempts.. Assessment objective (3.1.8[b]): the defined means of limiting unsuccessful logon attempts is implemented.. POA&M allowed: Yes. SPRS score: 1.",
    "metadata": {
      "framework": "NIST 800-171",
      "family": "Access Control",
      "control_id": "3.1.8",
      "cmmc_id": "AC.L2-3.1.8",
      "title": "UNSUCCESSFUL LOGON ATTEMPTS",
      "sprs": 1,
      "cmmc_levels": [
        "Level 2"
      ],
      "poam_allowed": "Yes",
      "ao_ids": [
        "3.1.8[a]",
        "3.1.8[b]"
      ],
      "assessment_methods": [
        {
          "type": "Examine",
          "description": "[SELECT FROM: Access control policy; procedures addressing unsuccessful logon attempts; security plan; system design documentation; system configuration settings and associated documentation; system audit logs and records; other relevant documents or records]."
        },
        {
          "type": "Interview",
          "description": "[SELECT FROM: Personnel with information security responsibilities; system developers; system or network administrators]."
        },
        {
          "type": "Test",
          "description": "[SELECT FROM: Mechanisms implementing access control policy for unsuccessful logon attempts]."
        }
      ]
    },
    "last_ao_sentence": "the defined means of limiting unsuccessful logon attempts is implemented."
  },
  {
    "text": "This is a NIST 800-171 control in the Access Control family. It corresponds to Level 2. The control ID is AC.L2-3.1.9 with title 'PRIVACY & SECURITY NOTICES'. Security requirement: Provide privacy and security notices consistent with applicable CUI rules.. Assessment objective (3.1.9[a]): privacy and security notices required by CUI-specified rules are identified, consistent, and associated with the specific CUI category. POA&M allowed: Yes. SPRS score: 1.\nThis is a NIST 800-171 control in the Access Control family. It corresponds to Level 2. The control ID is AC.L2-3.1.9 with title 'PRIVACY & SECURITY NOTICES'. Security requirement: Provide privacy and security notices consistent with applicable CUI rules.. Assessment objective (3.1.9[b]): privacy and security notices are displayed.. POA&M allowed: Yes. SPRS score: 1.",
    "metadata": {
      "framework": "NIST 800-171",
      "family": "Access Control",
      "control_id": "3.1.9",
      "cmmc_id": "AC.L2-3.1.9",
      "title": "PRIVACY & SECURITY NOTICES",
      "sprs": 1,
      "cmmc_levels": [
        "Level 2"
      ],
      "poam_allowed": "Yes",
      "ao_ids": [
        "3.1.9[a]",
        "3.1.9[b]"
      ],
      "assessment_methods": [
        {
          "type": "Examine",
          "description": "SELECT FROM: Access control policy; privacy and security policies, procedures addressing system use notification; documented approval of system use notification messages or banners; system audit logs and records; system design documentation; user acknowledgements of notification message or banner; security plan; system use notification messages; system configuration settings and associated documentation; other relevant documents or records]."
        },
        {
          "type": "Interview",
          "description": "[SELECT FROM: System or network administrators; personnel with information security responsibilities; personnel with responsibility for providing legal advice; system developers]."
        },
        {
          "type": "Test",
          "description": "[SELECT FROM: Mechanisms implementing system use notification]."
        }
      ]
    },
    "last_ao_sentence": "privacy and security notices are displayed."
  },
  {
    "text": "This is a NIST 800-171 control in the Access Control family. It corresponds to Level 2. The control ID is AC.L2-3.1.10 with title 'SESSION LOCK'. Security requirement: Use session lock with pattern-hiding displays to prevent access and viewing of data after a period of inactivity.. Assessment objective (3.1.10[a]): the period of inactivity after which the system initiates a session lock is defined.. POA&M allowed: Yes. SPRS score: 1.\nThis is a NIST 800-171 control in the Access Control family. It corresponds to Level 2. The control ID is AC.L2-3.1.10 with title 'SESSION LOCK'. Security requirement: Use session lock with pattern-hiding displays to prevent access and viewing of data after a period of inactivity.. Assessment objective (3.1.10[b]): access to the system and viewing of data is prevented by initiating a session lock after the defined period of inactivity.. POA&M allowed: Yes. SPRS score: 1.\nThis is a NIST 800-171 control in the Access Control family. It corresponds to Level 2. The control ID is AC.L2-3.1.10 with title 'SESSION LOCK'. Security requirement: Use session lock with pattern-hiding displays to prevent access and viewing of data after a period of inactivity.. Assessment objective (3.1.10[c]): previously visible information is concealed via a pattern-hiding display after the defined period of inactivity.. POA&M allowed: Yes. SPRS score: 1.",
    "metadata": {
      "framework": "NIST 800-171",
      "family": "Access Control",
      "control_id": "3.1.10",
      "cmmc_id": "AC.L2-3.1.10",
      "title": "SESSION LOCK",
      "sprs": 1,
      "cmmc_levels": [
        "Level 2"
      ],
      "poam_allowed": "Yes",
      "ao_ids": [
        "3.1.10[a]",
        "3.1.10[b]",
        "3.1.10[c]"
      ],
      "assessment_methods": [
        {
          "type": "Examine",
          "description": "[SELECT FROM: Access control policy; procedures addressing session lock; procedures addressing identification and authentication; system design documentation; system configuration settings and associated documentation; security plan; other relevant documents or records]."
        },
        {
          "type": "Interview",
          "description": "[SELECT FROM: System or network administrators; personnel with information security responsibilities; system developers]."
        },
        {
          "type": "Test",
          "description": "[SELECT FROM: Mechanisms implementing access control policy for session lock]."
        }
      ]
    },
    "last_ao_sentence": "previously visible information is concealed via a pattern-hiding display after the defined period of inactivity."
  },
  {
    "text": "This is a NIST 800-171 control in the Access Control family. It corresponds to Level 2. The control ID is AC.L2-3.1.11 with title 'SESSION TERMINATION'. Security requirement: Terminate (automatically) a user session after a defined condition.. Assessment objective (3.1.11[a]): conditions requiring a user session to terminate are defined.. POA&M allowed: Yes. SPRS score: 1.\nThis is a NIST 800-171 control in the Access Control family. It corresponds to Level 2. The control ID is AC.L2-3.1.11 with title 'SESSION TERMINATION'. Security requirement: Terminate (automatically) a user session after a defined condition.. Assessment objective (3.1.11[b]): a user session is automatically terminated after any of the defined conditions occur.. POA&M allowed: Yes. SPRS score: 1.",
    "metadata": {
      "framework": "NIST 800-171",
      "family": "Access Control",
      "control_id": "3.1.11",
      "cmmc_id": "AC.L2-3.1.11",
      "title": "SESSION TERMINATION",
      "sprs": 1,
      "cmmc_levels": [
        "Level 2"
      ],
      "poam_allowed": "Yes",
      "ao_ids": [
        "3.1.11[a]",
        "3.1.11[b]"
      ],
      "assessment_methods": [
        {
          "type": "Examine",
          "description": "[SELECT FROM: Access control policy; procedures addressing session termination; system design documentation; security plan; system configuration settings and associated documentation; list of conditions or trigger events requiring session disconnect; system audit logs and records; other relevant documents or records]."
        },
        {
          "type": "Interview",
          "description": "[SELECT FROM: System or network administrators; personnel with information security responsibilities; system developers]."
        },
        {
          "type": "Test",
          "description": "[SELECT FROM: Mechanisms implementing user session termination]."
        }
      ]
    },
    "last_ao_sentence": "a user session is automatically terminated after any of the defined conditions occur."
  },
  {
    "text": "This is a NIST 800-171 control in the Access Control family. It corresponds to Level 2. The control ID is AC.L2-3.1.12 with title 'CONTROL REMOTE ACCESS'. Security requirement: Monitor and control remote access sessions.. Assessment objective (3.1.12[a]): remote access sessions are permitted.. POA&M allowed: No. SPRS score: 5.\nThis is a NIST 800-171 control in the Access Control family. It corresponds to Level 2. The control ID is AC.L2-3.1.12 with title 'CONTROL REMOTE ACCESS'. Security requirement: Monitor and control remote access sessions.. Assessment objective (3.1.12[b]): the types of permitted remote access are identified.. POA&M allowed: No. SPRS score: 5.\nThis is a NIST 800-171 control in the Access Control family. It corresponds to Level 2. The control ID is AC.L2-3.1.12 with title 'CONTROL REMOTE ACCESS'. Security requirement: Monitor and control remote access sessions.. Assessment objective (3.1.12[c]): remote access sessions are controlled.. POA&M allowed: No. SPRS score: 5.\nThis is a NIST 800-171 control in the Access Control family. It corresponds to Level 2. The control ID is AC.L2-3.1.12 with title 'CONTROL REMOTE ACCESS'. Security requirement: Monitor and control remote access sessions.. Assessment objective (3.1.12[d]): remote access sessions are monitored.. POA&M allowed: No. SPRS score: 5.",
    "metadata": {
      "framework": "NIST 800-171",
      "family": "Access Control",
      "control_id": "3.1.12",
      "cmmc_id": "AC.L2-3.1.12",
      "title": "CONTROL REMOTE ACCESS",
      "sprs": 5,
      "cmmc_levels": [
        "Level 2"
      ],
      "poam_allowed": "No",
      "ao_ids": [
        "3.1.12[a]",
        "3.1.12[b]",
        "3.1.12[c]",
        "3.1.12[d]"
      ],
      "assessment_methods": [
        {
          "type": "Examine",
          "description": "[SELECT FROM: Access control policy; procedures addressing remote access implementation and usage (including restrictions); configuration management plan; security plan; system configuration settings and associated documentation; remote access authorizations; system audit logs and records; other relevant documents or records]."
        },
        {
          "type": "Interview",
          "description": "[SELECT FROM: Personnel with responsibilities for managing remote access connections; system or network administrators; personnel with information security responsibilities]."
        },
        {
          "type": "Test",
          "description": "[SELECT FROM: Remote access management capability for the system]."
        }
      ]
    },
    "last_ao_sentence": "remote access sessions are monitored."
  },
  {
    "text": "This is a NIST 800-171 control in the Access Control family. It corresponds to Level 2. The control ID is AC.L2-3.1.13 with title 'REMOTE ACCESS CONFIDENTIALITY'. Security requirement: Employ cryptographic mechanisms to protect the confidentiality of remote access sessions.. Assessment objective (3.1.13[a]): cryptographic mechanisms to protect the confidentiality of remote access sessions are identified.. POA&M allowed: No. SPRS score: 5.\nThis is a NIST 800-171 control in the Access Control family. It corresponds to Level 2. The control ID is AC.L2-3.1.13 with title 'REMOTE ACCESS CONFIDENTIALITY'. Security requirement: Employ cryptographic mechanisms to protect the confidentiality of remote access sessions.. Assessment objective (3.1.13[b]): cryptographic mechanisms to protect the confidentiality of remote access sessions are implemented.. POA&M allowed: No. SPRS score: 5.",
    "metadata": {
      "framework": "NIST 800-171",
      "family": "Access Control",
      "control_id": "3.1.13",
      "cmmc_id": "AC.L2-3.1.13",
      "title": "REMOTE ACCESS CONFIDENTIALITY",
      "sprs": 5,
      "cmmc_levels": [
        "Level 2"
      ],
      "poam_allowed": "No",
      "ao_ids": [
        "3.1.13[a]",
        "3.1.13[b]"
      ],
      "assessment_methods": [
        {
          "type": "Examine",
          "description": "[SELECT FROM: Access control policy; procedures addressing remote access to the system; security plan; system design documentation; system configuration settings and associated documentation; cryptographic mechanisms and associated configuration documentation; system audit logs and records; other relevant documents or records]."
        },
        {
          "type": "Interview",
          "description": "[SELECT FROM: System or network administrators; personnel with information security responsibilities; system developers]."
        },
        {
          "type": "Test",
          "description": "[SELECT FROM: Cryptographic mechanisms protecting remote access sessions]."
        }
      ]
    },
    "last_ao_sentence": "cryptographic mechanisms to protect the confidentiality of remote access sessions are implemented."
  },
  {
    "text": "This is a NIST 800-171 control in the Access Control family. It corresponds to Level 2. The control ID is AC.L2-3.1.14 with title 'REMOTE ACCESS ROUTING'. Security requirement: Route remote access via managed access control points.. Assessment objective (3.1.14[a]): managed access control points are identified and implemented.. POA&M allowed: Yes. SPRS score: 1.\nThis is a NIST 800-171 control in the Access Control family. It corresponds to Level 2. The control ID is AC.L2-3.1.14 with title 'REMOTE ACCESS ROUTING'. Security requirement: Route remote access via managed access control points.. Assessment objective (3.1.14[b]): remote access is routed through managed network access control points.. POA&M allowed: Yes. SPRS score: 1.",
    "metadata": {
      "framework": "NIST 800-171",
      "family": "Access Control",
      "control_id": "3.1.14",
      "cmmc_id": "AC.L2-3.1.14",
      "title": "REMOTE ACCESS ROUTING",
      "sprs": 1,
      "cmmc_levels": [
        "Level 2"
      ],
      "poam_allowed": "Yes",
      "ao_ids": [
        "3.1.14[a]",
        "3.1.14[b]"
      ],
      "assessment_methods": [
        {
          "type": "Examine",
          "description": "[SELECT FROM: Access control policy; procedures addressing remote access to the system; security plan; system design documentation; list of all managed network access control points; system configuration settings and associated documentation; system audit logs and records; other relevant documents or records]."
        },
        {
          "type": "Interview",
          "description": "[SELECT FROM: System or network administrators; personnel with information security responsibilities]."
        },
        {
          "type": "Test",
          "description": "[SELECT FROM: Mechanisms routing all remote accesses through managed network access control points]."
        }
      ]
    },
    "last_ao_sentence": "remote access is routed through managed network access control points."
  },
  {
    "text": "This is a NIST 800-171 control in the Access Control family. It corresponds to Level 2. The control ID is AC.L2-3.1.15 with title 'PRIVILEGED REMOTE ACCESS'. Security requirement: Authorize remote execution of privileged commands and remote access to security-relevant information.. Assessment objective (3.1.15[a]): privileged commands authorized for remote execution are identified.. POA&M allowed: Yes. SPRS score: 1.\nThis is a NIST 800-171 control in the Access Control family. It corresponds to Level 2. The control ID is AC.L2-3.1.15 with title 'PRIVILEGED REMOTE ACCESS'. Security requirement: Authorize remote execution of privileged commands and remote access to security-relevant information.. Assessment objective (3.1.15[b]): security-relevant information authorized to be accessed remotely is identified.. POA&M allowed: Yes. SPRS score: 1.\nThis is a NIST 800-171 control in the Access Control family. It corresponds to Level 2. The control ID is AC.L2-3.1.15 with title 'PRIVILEGED REMOTE ACCESS'. Security requirement: Authorize remote execution of privileged commands and remote access to security-relevant information.. Assessment objective (3.1.15[c]): the execution of the identified privileged commands via remote access is authorized.. POA&M allowed: Yes. SPRS score: 1.\nThis is a NIST 800-171 control in the Access Control family. It corresponds to Level 2. The control ID is AC.L2-3.1.15 with title 'PRIVILEGED REMOTE ACCESS'. Security requirement: Authorize remote execution of privileged commands and remote access to security-relevant information.. Assessment objective (3.1.15[d]): access to the identified security-relevant information via remote access is authorized.. POA&M allowed: Yes. SPRS score: 1.",
    "metadata": {
      "framework": "NIST 800-171",
      "family": "Access Control",
      "control_id": "3.1.15",
      "cmmc_id": "AC.L2-3.1.15",
      "title": "PRIVILEGED REMOTE ACCESS",
      "sprs": 1,
      "cmmc_levels": [
        "Level 2"
      ],
      "poam_allowed": "Yes",
      "ao_ids": [
        "3.1.15[a]",
        "3.1.15[b]",
        "3.1.15[c]",
        "3.1.15[d]"
      ],
      "assessment_methods": [
        {
          "type": "Examine",
          "description": "[SELECT FROM: Access control policy; procedures addressing remote access to the system; system configuration settings and associated documentation; security plan; system audit logs and records; other relevant documents or records]."
        },
        {
          "type": "Interview",
          "description": "[SELECT FROM: System or network administrators; personnel with information security responsibilities]."
        },
        {
          "type": "Test",
          "description": "[SELECT FROM: Mechanisms implementing remote access management]."
        }
      ]
    },
    "last_ao_sentence": "access to the identified security-relevant information via remote access is authorized."
  },
  {
    "text": "This is a NIST 800-171 control in the Access Control family. It corresponds to Level 2. The control ID is AC.L2-3.1.16 with title 'WIRELESS ACCESS AUTHORIZATION'. Security requirement: Authorize wireless access prior to allowing such connections.. Assessment objective (3.1.16[a]): wireless access points are identified.. POA&M allowed: No. SPRS score: 5.\nThis is a NIST 800-171 control in the Access Control family. It corresponds to Level 2. The control ID is AC.L2-3.1.16 with title 'WIRELESS ACCESS AUTHORIZATION'. Security requirement: Authorize wireless access prior to allowing such connections.. Assessment objective (3.1.16[b]): wireless access is authorized prior to allowing such connections.. POA&M allowed: No. SPRS score: 5.",
    "metadata": {
      "framework": "NIST 800-171",
      "family": "Access Control",
      "control_id": "3.1.16",
      "cmmc_id": "AC.L2-3.1.16",
      "title": "WIRELESS ACCESS AUTHORIZATION",
      "sprs": 5,
      "cmmc_levels": [
        "Level 2"
      ],
      "poam_allowed": "No",
      "ao_ids": [
        "3.1.16[a]",
        "3.1.16[b]"
      ],
      "assessment_methods": [
        {
          "type": "Examine",
          "description": "[SELECT FROM: Access control policy; configuration management plan; procedures addressing wireless access implementation and usage (including restrictions); security plan; system design documentation; system configuration settings and associated documentation; wireless access authorizations; system audit logs and records; other relevant documents or records]."
        },
        {
          "type": "Interview",
          "description": "[SELECT FROM: Personnel with responsibilities for managing wireless access connections; personnel with information security responsibilities]."
        },
        {
          "type": "Test",
          "description": "[SELECT FROM: Wireless access management capability for the system]."
        }
      ]
    },
    "last_ao_sentence": "wireless access is authorized prior to allowing such connections."
  },
  {
    "text": "This is a NIST 800-171 control in the Access Control family. It corresponds to Level 2. The control ID is AC.L2-3.1.17 with title 'WIRELESS ACCESS PROTECTION'. Security requirement: Protect wireless access using authentication and encryption.. Assessment objective (3.1.17[a]): wireless access to the system is protected using encryption.. POA&M allowed: No. SPRS score: 5.\nThis is a NIST 800-171 control in the Access Control family. It corresponds to Level 2. The control ID is AC.L2-3.1.17 with title 'WIRELESS ACCESS PROTECTION'. Security requirement: Protect wireless access using authentication and encryption.. Assessment objective (3.1.17[b]): wireless access to the system is protected using authentication.. POA&M allowed: No. SPRS score: 5.",
    "metadata": {
      "framework": "NIST 800-171",
      "family": "Access Control",
      "control_id": "3.1.17",
      "cmmc_id": "AC.L2-3.1.17",
      "title": "WIRELESS ACCESS PROTECTION",
      "sprs": 5,
      "cmmc_levels": [
        "Level 2"
      ],
      "poam_allowed": "No",
      "ao_ids": [
        "3.1.17[a]",
        "3.1.17[b]"
      ],
      "assessment_methods": [
        {
          "type": "Examine",
          "description": "[SELECT FROM: Access control policy; system design documentation; procedures addressing wireless implementation and usage (including restrictions); security plan; system configuration settings and associated documentation; system audit logs and records; other relevant documents or records]."
        },
        {
          "type": "Interview",
          "description": "[SELECT FROM: System or network administrators; personnel with information security responsibilities; system developers]."
        },
        {
          "type": "Test",
          "description": "[SELECT FROM: Mechanisms implementing wireless access protections to the system]."
        }
      ]
    },
    "last_ao_sentence": "wireless access to the system is protected using authentication."
  },
  {
    "text": "This is a NIST 800-171 control in the Access Control family. It corresponds to Level 2. The control ID is AC.L2-3.1.18 with title 'MOBILE DEVICE CONNECTION'. Security requirement: Control connection of mobile devices.. Assessment objective (3.1.18[a]): mobile devices that process, store, or transmit CUI are identified.. POA&M allowed: No. SPRS score: 5.\nThis is a NIST 800-171 control in the Access Control family. It corresponds to Level 2. The control ID is AC.L2-3.1.18 with title 'MOBILE DEVICE CONNECTION'. Security requirement: Control connection of mobile devices.. Assessment objective (3.1.18[b]): the connection of mobile devices is authorized.. POA&M allowed: No. SPRS score: 5.\nThis is a NIST 800-171 control in the Access Control family. It corresponds to Level 2. The control ID is AC.L2-3.1.18 with title 'MOBILE DEVICE CONNECTION'. Security requirement: Control connection of mobile devices.. Assessment objective (3.1.18[c]): mobile device connections are monitored and logged.. POA&M allowed: No. SPRS score: 5.",
    "metadata": {
      "framework": "NIST 800-171",
      "family": "Access Control",
      "control_id": "3.1.18",
      "cmmc_id": "AC.L2-3.1.18",
      "title": "MOBILE DEVICE CONNECTION",
      "sprs": 5,
      "cmmc_levels": [
        "Level 2"
      ],
      "poam_allowed": "No",
      "ao_ids": [
        "3.1.18[a]",
        "3.1.18[b]",
        "3.1.18[c]"
      ],
      "assessment_methods": [
        {
          "type": "Examine",
          "description": "[SELECT FROM: Access control policy; authorizations for mobile device connections to organizational systems; procedures addressing access control for mobile device usage (including restrictions); system design documentation; configuration management plan; security plan; system audit logs and records; system configuration settings and associated documentation; other relevant documents or records]."
        },
        {
          "type": "Interview",
          "description": "[SELECT FROM: Personnel using mobile devices to access organizational systems; system or network administrators; personnel with information security responsibilities]."
        },
        {
          "type": "Test",
          "description": "[SELECT FROM: Access control capability authorizing mobile device connections to organizational systems]."
        }
      ]
    },
    "last_ao_sentence": "mobile device connections are monitored and logged."
  },
  {
    "text": "This is a NIST 800-171 control in the Access Control family. It corresponds to Level 2. The control ID is AC.L2-3.1.19 with title 'ENCRYPT CUI ON MOBILE'. Security requirement: Encrypt CUI on mobile devices and mobile computing platforms.. Assessment objective (3.1.19[a]): mobile devices and mobile computing platforms that process, store, or transmit CUI are identified.. POA&M allowed: No. SPRS score: 3.\nThis is a NIST 800-171 control in the Access Control family. It corresponds to Level 2. The control ID is AC.L2-3.1.19 with title 'ENCRYPT CUI ON MOBILE'. Security requirement: Encrypt CUI on mobile devices and mobile computing platforms.. Assessment objective (3.1.19[b]): encryption is employed to protect CUI on identified mobile devices and mobile computing platforms.. POA&M allowed: No. SPRS score: 3.",
    "metadata": {
      "framework": "NIST 800-171",
      "family": "Access Control",
      "control_id": "3.1.19",
      "cmmc_id": "AC.L2-3.1.19",
      "title": "ENCRYPT CUI ON MOBILE",
      "sprs": 3,
      "cmmc_levels": [
        "Level 2"
      ],
      "poam_allowed": "No",
      "ao_ids": [
        "3.1.19[a]",
        "3.1.19[b]"
      ],
      "assessment_methods": [
        {
          "type": "Examine",
          "description": "[SELECT FROM: Access control policy; procedures addressing access control for mobile devices; system design documentation; system configuration settings and associated documentation; encryption mechanisms and associated configuration documentation; security plan; system audit logs and records; other relevant documents or records]."
        },
        {
          "type": "Interview",
          "description": "[SELECT FROM: Personnel with access control responsibilities for mobile devices; system or network administrators; personnel with information security responsibilities]."
        },
        {
          "type": "Test",
          "description": "[SELECT FROM: Encryption mechanisms protecting confidentiality of information on mobile devices]."
        }
      ]
    },
    "last_ao_sentence": "encryption is employed to protect CUI on identified mobile devices and mobile computing platforms."
  },
  {
    "text": "This is a NIST 800-171 control in the Access Control family. It corresponds to Level 1, Level 2. The control ID is AC.L1-3.1.20 with title 'EXTERNAL CONNECTIONS'. Security requirement: Verify and control/limit connections to and use of external systems.. Assessment objective (3.1.20[a]): connections to external systems are identified.. POA&M allowed: No. SPRS score: 1.\nThis is a NIST 800-171 control in the Access Control family. It corresponds to Level 1, Level 2. The control ID is AC.L1-3.1.20 with title 'EXTERNAL CONNECTIONS'. Security requirement: Verify and control/limit connections to and use of external systems.. Assessment objective (3.1.20[b]): use of external systems is identified.. POA&M allowed: No. SPRS score: 1.\nThis is a NIST 800-171 control in the Access Control family. It corresponds to Level 1, Level 2. The control ID is AC.L1-3.1.20 with title 'EXTERNAL CONNECTIONS'. Security requirement: Verify and control/limit connections to and use of external systems.. Assessment objective (3.1.20[c]): connections to external systems are verified.. POA&M allowed: No. SPRS score: 1.\nThis is a NIST 800-171 control in the Access Control family. It corresponds to Level 1, Level 2. The control ID is AC.L1-3.1.20 with title 'EXTERNAL CONNECTIONS'. Security requirement: Verify and control/limit connections to and use of external systems.. Assessment objective (3.1.20[d]): use of external systems is verified.. POA&M allowed: No. SPRS score: 1.\nThis is a NIST 800-171 control in the Access Control family. It corresponds to Level 1, Level 2. The control ID is AC.L1-3.1.20 with title 'EXTERNAL CONNECTIONS'. Security requirement: Verify and control/limit connections to and use of external systems.. Assessment objective (3.1.20[e]): connections to external systems are controlled/limited.. POA&M allowed: No. SPRS score: 1.\nThis is a NIST 800-171 control in the Access Control family. It corresponds to Level 1, Level 2. The control ID is AC.L1-3.1.20 with title 'EXTERNAL CONNECTIONS'. Security requirement: Verify and control/limit connections to and use of external systems.. Assessment objective (3.1.20[f]): use of external systems is controlled/limited.. POA&M allowed: No. SPRS score: 1.",
    "metadata": {
      "framework": "NIST 800-171",
      "family": "Access Control",
      "control_id": "3.1.20",
      "cmmc_id": "AC.L1-3.1.20",
      "title": "EXTERNAL CONNECTIONS",
      "sprs": 1,
      "cmmc_levels": [
        "Level 1",
        "Level 2"
      ],
      "poam_allowed": "No",
      "ao_ids": [
        "3.1.20[a]",
        "3.1.20[b]",
        "3.1.20[c]",
        "3.1.20[d]",
        "3.1.20[e]",
        "3.1.20[f]"
      ],
      "assessment_methods": [
        {
          "type": "Examine",
          "description": "[SELECT FROM: Access control policy; procedures addressing the use of external systems; terms and conditions for external systems; security plan; list of types of applications accessible from external systems; system configuration settings and associated documentation; other relevant documents or records]."
        },
        {
          "type": "Interview",
          "description": "[SELECT FROM: Personnel with responsibilities for defining terms and conditions for use of external systems to access organizational systems; system or network administrators; personnel with information security responsibilities]."
        },
        {
          "type": "Test",
          "description": "[SELECT FROM: Mechanisms implementing terms and conditions on use of external systems]."
        }
      ]
    },
    "last_ao_sentence": "use of external systems is controlled/limited."
  },
  {
    "text": "This is a NIST 800-171 control in the Access Control family. It corresponds to Level 2. The control ID is AC.L2-3.1.21 with title 'PORTABLE STORAGE USE'. Security requirement: Limit use of organizational portable storage devices on external systems.. Assessment objective (3.1.21[a]): use of organizational portable storage devices containing CUI on external systems is identified and documented.. POA&M allowed: Yes. SPRS score: 1.\nThis is a NIST 800-171 control in the Access Control family. It corresponds to Level 2. The control ID is AC.L2-3.1.21 with title 'PORTABLE STORAGE USE'. Security requirement: Limit use of organizational portable storage devices on external systems.. Assessment objective (3.1.21[b]): limits on the use of organizational portable storage devices containing CUI on external systems are defined.. POA&M allowed: Yes. SPRS score: 1.\nThis is a NIST 800-171 control in the Access Control family. It corresponds to Level 2. The control ID is AC.L2-3.1.21 with title 'PORTABLE STORAGE USE'. Security requirement: Limit use of organizational portable storage devices on external systems.. Assessment objective (3.1.21[c]): use of organizational portable storage devices containing CUI on external systems is limited as defined.. POA&M allowed: Yes. SPRS score: 1.",
    "metadata": {
      "framework": "NIST 800-171",
      "family": "Access Control",
      "control_id": "3.1.21",
      "cmmc_id": "AC.L2-3.1.21",
      "title": "PORTABLE STORAGE USE",
      "sprs": 1,
      "cmmc_levels": [
        "Level 2"
      ],
      "poam_allowed": "Yes",
      "ao_ids": [
        "3.1.21[a]",
        "3.1.21[b]",
        "3.1.21[c]"
      ],
      "assessment_methods": [
        {
          "type": "Examine",
          "description": "[SELECT FROM: Access control policy; procedures addressing the use of external systems; security plan; system configuration settings and associated documentation; system connection or processing agreements; account management documents; other relevant documents or records]."
        },
        {
          "type": "Interview",
          "description": "[SELECT FROM: Personnel with responsibilities for restricting or prohibiting use of organization-controlled storage devices on external systems; system or network administrators; personnel with information security responsibilities]."
        },
        {
          "type": "Test",
          "description": "[SELECT FROM: Mechanisms implementing restrictions on use of portable storage devices]."
        }
      ]
    },
    "last_ao_sentence": "use of organizational portable storage devices containing CUI on external systems is limited as defined."
  },
  {
    "text": "This is a NIST 800-171 control in the Access Control family. It corresponds to Level 1, Level 2. The control ID is AC.L1-3.1.22 with title 'CONTROL PUBLIC INFORMATION'. Security requirement: Control CUI posted or processed on publicly accessible systems.. Assessment objective (3.1.22[a]): individuals authorized to post or process information on publicly accessible systems are identified.. POA&M allowed: No. SPRS score: 1.\nThis is a NIST 800-171 control in the Access Control family. It corresponds to Level 1, Level 2. The control ID is AC.L1-3.1.22 with title 'CONTROL PUBLIC INFORMATION'. Security requirement: Control CUI posted or processed on publicly accessible systems.. Assessment objective (3.1.22[b]): procedures to ensure CUI is not posted or processed on publicly accessible systems are identified.. POA&M allowed: No. SPRS score: 1.\nThis is a NIST 800-171 control in the Access Control family. It corresponds to Level 1, Level 2. The control ID is AC.L1-3.1.22 with title 'CONTROL PUBLIC INFORMATION'. Security requirement: Control CUI posted or processed on publicly accessible systems.. Assessment objective (3.1.22[c]): a review process in in place prior to posting of any content to publicly accessible systems.. POA&M allowed: No. SPRS score: 1.\nThis is a NIST 800-171 control in the Access Control family. It corresponds to Level 1, Level 2. The control ID is AC.L1-3.1.22 with title 'CONTROL PUBLIC INFORMATION'. Security requirement: Control CUI posted or processed on publicly accessible systems.. Assessment objective (3.1.22[d]): content on publicly accessible systems is reviewed to ensure that it does not include\nFCI.. POA&M allowed: No. SPRS score: 1.\nThis is a NIST 800-171 control in the Access Control family. It corresponds to Level 1, Level 2. The control ID is AC.L1-3.1.22 with title 'CONTROL PUBLIC INFORMATION'. Security requirement: Control CUI posted or processed on publicly accessible systems.. Assessment objective (3.1.22[e]): mechanisms are in place to remove and address improper posting of FCI.. POA&M allowed: No. SPRS score: 1.",
    "metadata": {
      "framework": "NIST 800-171",
      "family": "Access Control",
      "control_id": "3.1.22",
      "cmmc_id": "AC.L1-3.1.22",
      "title": "CONTROL PUBLIC INFORMATION",
      "sprs": 1,
      "cmmc_levels": [
        "Level 1",
        "Level 2"
      ],
      "poam_allowed": "No",
      "ao_ids": [
        "3.1.22[a]",
        "3.1.22[b]",
        "3.1.22[c]",
        "3.1.22[d]",
        "3.1.22[e]"
      ],
      "assessment_methods": [
        {
          "type": "Examine",
          "description": "[SELECT FROM: Access control policy; procedures addressing publicly accessible content; security plan; list of users authorized to post publicly accessible content on organizational systems; training materials and/or records; records of publicly accessible information reviews; records of response to nonpublic information on public websites; system audit logs and records; security awareness training records; other relevant documents or records]."
        },
        {
          "type": "Interview",
          "description": "[SELECT FROM: Personnel with responsibilities for managing publicly accessible information posted on organizational systems; personnel with information security responsibilities]."
        },
        {
          "type": "Test",
          "description": "[SELECT FROM: Mechanisms implementing management of publicly accessible content]."
        }
      ]
    },
    "last_ao_sentence": "mechanisms are in place to remove and address improper posting of FCI."
  },
  {
    "text": "This is a NIST 800-171 control in the Awareness and Training family. It corresponds to Level 2. The control ID is AT.L2-3.2.1 with title 'ROLE-BASED RISK AWARENESS'. Security requirement: Ensure that managers, systems administrators, and users of organizational systems are made aware of the security risks associated with their activities and of the applicable policies, standards, and procedures related to the security of those systems.. Assessment objective (3.2.1[a]): security risks associated with organizational activities involving CUI are identified.. POA&M allowed: No. SPRS score: 5.\nThis is a NIST 800-171 control in the Awareness and Training family. It corresponds to Level 2. The control ID is AT.L2-3.2.1 with title 'ROLE-BASED RISK AWARENESS'. Security requirement: Ensure that managers, systems administrators, and users of organizational systems are made aware of the security risks associated with their activities and of the applicable policies, standards, and procedures related to the security of those systems.. Assessment objective (3.2.1[b]): policies, standards, and procedures related to the security of the system are identified.. POA&M allowed: No. SPRS score: 5.\nThis is a NIST 800-171 control in the Awareness and Training family. It corresponds to Level 2. The control ID is AT.L2-3.2.1 with title 'ROLE-BASED RISK AWARENESS'. Security requirement: Ensure that managers, systems administrators, and users of organizational systems are made aware of the security risks associated with their activities and of the applicable policies, standards, and procedures related to the security of those systems.. Assessment objective (3.2.1[c]): managers, systems administrators, and users of the system are made aware of the security risks associated with their activities.. POA&M allowed: No. SPRS score: 5.\nThis is a NIST 800-171 control in the Awareness and Training family. It corresponds to Level 2. The control ID is AT.L2-3.2.1 with title 'ROLE-BASED RISK AWARENESS'. Security requirement: Ensure that managers, systems administrators, and users of organizational systems are made aware of the security risks associated with their activities and of the applicable policies, standards, and procedures related to the security of those systems.. Assessment objective (3.2.1[d]): managers, systems administrators, and users of the system are made aware of the applicable policies, standards, and procedures related to the security of the system.. POA&M allowed: No. SPRS score: 5.",
    "metadata": {
      "framework": "NIST 800-171",
      "family": "Awareness and Training",
      "control_id": "3.2.1",
      "cmmc_id": "AT.L2-3.2.1",
      "title": "ROLE-BASED RISK AWARENESS",
      "sprs": 5,
      "cmmc_levels": [
        "Level 2"
      ],
      "poam_allowed": "No",
      "ao_ids": [
        "3.2.1[a]",
        "3.2.1[b]",
        "3.2.1[c]",
        "3.2.1[d]"
      ],
      "assessment_methods": [
        {
          "type": "Examine",
          "description": "[SELECT FROM: Security awareness and training policy; procedures addressing security awareness training implementation; relevant codes of federal regulations; security awareness training curriculum; security awareness training materials; security plan; training records; other relevant documents or records]."
        },
        {
          "type": "Interview",
          "description": "[SELECT FROM: Personnel with responsibilities for security awareness training; personnel with information security responsibilities; personnel composing the general system user community]."
        },
        {
          "type": "Test",
          "description": "[SELECT FROM: Mechanisms managing security awareness training; mechanisms managing role-based security training]."
        }
      ]
    },
    "last_ao_sentence": "managers, systems administrators, and users of the system are made aware of the applicable policies, standards, and procedures related to the security of the system."
  },
  {
    "text": "This is a NIST 800-171 control in the Awareness and Training family. It corresponds to Level 2. The control ID is AT.L2-3.2.2 with title 'ROLE-BASED TRAINING'. Security requirement: Ensure that organizational personnel are adequately trained to carry out their assigned information security-related duties and responsibilities.. Assessment objective (3.2.2[a]): information security-related duties, roles, and responsibilities are defined.. POA&M allowed: No. SPRS score: 5.\nThis is a NIST 800-171 control in the Awareness and Training family. It corresponds to Level 2. The control ID is AT.L2-3.2.2 with title 'ROLE-BASED TRAINING'. Security requirement: Ensure that organizational personnel are adequately trained to carry out their assigned information security-related duties and responsibilities.. Assessment objective (3.2.2[b]): information security-related duties, roles, and responsibilities are assigned to designated personnel.. POA&M allowed: No. SPRS score: 5.\nThis is a NIST 800-171 control in the Awareness and Training family. It corresponds to Level 2. The control ID is AT.L2-3.2.2 with title 'ROLE-BASED TRAINING'. Security requirement: Ensure that organizational personnel are adequately trained to carry out their assigned information security-related duties and responsibilities.. Assessment objective (3.2.2[c]): personnel are adequately trained to carry out their assigned information security-related duties, roles, and responsibilities.. POA&M allowed: No. SPRS score: 5.",
    "metadata": {
      "framework": "NIST 800-171",
      "family": "Awareness and Training",
      "control_id": "3.2.2",
      "cmmc_id": "AT.L2-3.2.2",
      "title": "ROLE-BASED TRAINING",
      "sprs": 5,
      "cmmc_levels": [
        "Level 2"
      ],
      "poam_allowed": "No",
      "ao_ids": [
        "3.2.2[a]",
        "3.2.2[b]",
        "3.2.2[c]"
      ],
      "assessment_methods": [
        {
          "type": "Examine",
          "description": "[SELECT FROM: Security awareness and training policy; procedures addressing security training implementation; codes of federal regulations; security training curriculum; security training materials; security plan; training records; other relevant documents or records]."
        },
        {
          "type": "Interview",
          "description": "[SELECT FROM: Personnel with responsibilities for role-based security training; personnel with assigned system security roles and responsibilities]."
        },
        {
          "type": "Test",
          "description": "[SELECT FROM: Mechanisms managing role-based security training]."
        }
      ]
    },
    "last_ao_sentence": "personnel are adequately trained to carry out their assigned information security-related duties, roles, and responsibilities."
  },
  {
    "text": "This is a NIST 800-171 control in the Awareness and Training family. It corresponds to Level 2. The control ID is AT.L2-3.2.3 with title 'INSIDER THREAT AWARENESS'. Security requirement: Provide security awareness training on recognizing and reporting potential indicators of insider threat.. Assessment objective (3.2.3[a]): potential indicators associated with insider threats are identified.. POA&M allowed: Yes. SPRS score: 1.\nThis is a NIST 800-171 control in the Awareness and Training family. It corresponds to Level 2. The control ID is AT.L2-3.2.3 with title 'INSIDER THREAT AWARENESS'. Security requirement: Provide security awareness training on recognizing and reporting potential indicators of insider threat.. Assessment objective (3.2.3[b]): security awareness training on recognizing and reporting potential indicators of insider threat is provided to managers and employees.. POA&M allowed: Yes. SPRS score: 1.",
    "metadata": {
      "framework": "NIST 800-171",
      "family": "Awareness and Training",
      "control_id": "3.2.3",
      "cmmc_id": "AT.L2-3.2.3",
      "title": "INSIDER THREAT AWARENESS",
      "sprs": 1,
      "cmmc_levels": [
        "Level 2"
      ],
      "poam_allowed": "Yes",
      "ao_ids": [
        "3.2.3[a]",
        "3.2.3[b]"
      ],
      "assessment_methods": [
        {
          "type": "Examine",
          "description": "[SELECT FROM: Security awareness and training policy; procedures addressing security awareness training implementation; security awareness training curriculum; security awareness training materials; insider threat policy and procedures; security plan; other relevant documents or records]."
        },
        {
          "type": "Interview",
          "description": "[SELECT FROM: Personnel that participate in security awareness training; personnel with responsibilities for basic security awareness training; personnel with information security responsibilities]."
        },
        {
          "type": "Test",
          "description": "[SELECT FROM: Mechanisms managing insider threat training]."
        }
      ]
    },
    "last_ao_sentence": "security awareness training on recognizing and reporting potential indicators of insider threat is provided to managers and employees."
  },
  {
    "text": "This is a NIST 800-171 control in the Audit and Accountability family. It corresponds to Level 2. The control ID is AU.L2-3.3.1 with title 'SYSTEM AUDITING'. Security requirement: Create and retain system audit logs and records to the extent needed to enable the monitoring, analysis, investigation, and reporting of unlawful or unauthorized system activity.. Assessment objective (3.3.1[a]): audit logs needed (i.e., event types to be logged) to enable the monitoring, analysis, investigation, and reporting of unlawful or unauthorized system activity are specified.. POA&M allowed: No. SPRS score: 5.\nThis is a NIST 800-171 control in the Audit and Accountability family. It corresponds to Level 2. The control ID is AU.L2-3.3.1 with title 'SYSTEM AUDITING'. Security requirement: Create and retain system audit logs and records to the extent needed to enable the monitoring, analysis, investigation, and reporting of unlawful or unauthorized system activity.. Assessment objective (3.3.1[b]): the content of audit records needed to support monitoring, analysis, investigation, and reporting of unlawful or unauthorized system activity is defined.. POA&M allowed: No. SPRS score: 5.\nThis is a NIST 800-171 control in the Audit and Accountability family. It corresponds to Level 2. The control ID is AU.L2-3.3.1 with title 'SYSTEM AUDITING'. Security requirement: Create and retain system audit logs and records to the extent needed to enable the monitoring, analysis, investigation, and reporting of unlawful or unauthorized system activity.. Assessment objective (3.3.1[c]): audit records are created (generated).. POA&M allowed: No. SPRS score: 5.\nThis is a NIST 800-171 control in the Audit and Accountability family. It corresponds to Level 2. The control ID is AU.L2-3.3.1 with title 'SYSTEM AUDITING'. Security requirement: Create and retain system audit logs and records to the extent needed to enable the monitoring, analysis, investigation, and reporting of unlawful or unauthorized system activity.. Assessment objective (3.3.1[d]): audit records, once created, contain the defined content.. POA&M allowed: No. SPRS score: 5.\nThis is a NIST 800-171 control in the Audit and Accountability family. It corresponds to Level 2. The control ID is AU.L2-3.3.1 with title 'SYSTEM AUDITING'. Security requirement: Create and retain system audit logs and records to the extent needed to enable the monitoring, analysis, investigation, and reporting of unlawful or unauthorized system activity.. Assessment objective (3.3.1[e]): retention requirements for audit records are defined.. POA&M allowed: No. SPRS score: 5.\nThis is a NIST 800-171 control in the Audit and Accountability family. It corresponds to Level 2. The control ID is AU.L2-3.3.1 with title 'SYSTEM AUDITING'. Security requirement: Create and retain system audit logs and records to the extent needed to enable the monitoring, analysis, investigation, and reporting of unlawful or unauthorized system activity.. Assessment objective (3.3.1[f]): audit records are retained as defined.. POA&M allowed: No. SPRS score: 5.",
    "metadata": {
      "framework": "NIST 800-171",
      "family": "Audit and Accountability",
      "control_id": "3.3.1",
      "cmmc_id": "AU.L2-3.3.1",
      "title": "SYSTEM AUDITING",
      "sprs": 5,
      "cmmc_levels": [
        "Level 2"
      ],
      "poam_allowed": "No",
      "ao_ids": [
        "3.3.1[a]",
        "3.3.1[b]",
        "3.3.1[c]",
        "3.3.1[d]",
        "3.3.1[e]",
        "3.3.1[f]"
      ],
      "assessment_methods": [
        {
          "type": "Examine",
          "description": "[SELECT FROM: Audit and accountability policy; procedures addressing auditable events; security plan; system design documentation; system configuration settings and associated documentation; system audit logs and records; system auditable events; system incident reports; other relevant documents or records]."
        },
        {
          "type": "Interview",
          "description": "[SELECT FROM: Personnel with audit and accountability responsibilities; personnel with information security responsibilities; system or network administrators]."
        },
        {
          "type": "Test",
          "description": "[SELECT FROM: Mechanisms implementing system audit logging]."
        }
      ]
    },
    "last_ao_sentence": "audit records are retained as defined."
  },
  {
    "text": "This is a NIST 800-171 control in the Audit and Accountability family. It corresponds to Level 2. The control ID is AU.L2-3.3.2 with title 'USER ACCOUNTABILITY'. Security requirement: Ensure that the actions of individual system users can be uniquely traced to those users so they can be held accountable for their actions.. Assessment objective (3.3.2[a]): the content of the audit records needed to support the ability to uniquely trace users to their actions is defined.. POA&M allowed: No. SPRS score: 3.\nThis is a NIST 800-171 control in the Audit and Accountability family. It corresponds to Level 2. The control ID is AU.L2-3.3.2 with title 'USER ACCOUNTABILITY'. Security requirement: Ensure that the actions of individual system users can be uniquely traced to those users so they can be held accountable for their actions.. Assessment objective (3.3.2[b]): audit records, once created, contain the defined content.. POA&M allowed: No. SPRS score: 3.",
    "metadata": {
      "framework": "NIST 800-171",
      "family": "Audit and Accountability",
      "control_id": "3.3.2",
      "cmmc_id": "AU.L2-3.3.2",
      "title": "USER ACCOUNTABILITY",
      "sprs": 3,
      "cmmc_levels": [
        "Level 2"
      ],
      "poam_allowed": "No",
      "ao_ids": [
        "3.3.2[a]",
        "3.3.2[b]"
      ],
      "assessment_methods": [
        {
          "type": "Examine",
          "description": "[SELECT FROM: Audit and accountability policy; procedures addressing audit records and event types; security plan; system design documentation; system configuration settings and associated documentation; system audit logs and records; system events; system incident reports; other relevant documents or records]."
        },
        {
          "type": "Interview",
          "description": "[SELECT FROM: Personnel with audit and accountability responsibilities; personnel with information security responsibilities; system or network administrators]."
        },
        {
          "type": "Test",
          "description": "[SELECT FROM: Mechanisms implementing system audit logging]."
        }
      ]
    },
    "last_ao_sentence": "audit records, once created, contain the defined content."
  },
  {
    "text": "This is a NIST 800-171 control in the Audit and Accountability family. It corresponds to Level 2. The control ID is AU.L2-3.3.3 with title 'EVENT REVIEW'. Security requirement: Review and update logged events.. Assessment objective (3.3.3[a]): a process for determining when to review logged events is defined.. POA&M allowed: Yes. SPRS score: 1.\nThis is a NIST 800-171 control in the Audit and Accountability family. It corresponds to Level 2. The control ID is AU.L2-3.3.3 with title 'EVENT REVIEW'. Security requirement: Review and update logged events.. Assessment objective (3.3.3[b]): event types being logged are reviewed in accordance with the defined review process.. POA&M allowed: Yes. SPRS score: 1.\nThis is a NIST 800-171 control in the Audit and Accountability family. It corresponds to Level 2. The control ID is AU.L2-3.3.3 with title 'EVENT REVIEW'. Security requirement: Review and update logged events.. Assessment objective (3.3.3[c]): event types being logged are updated based on the review.. POA&M allowed: Yes. SPRS score: 1.",
    "metadata": {
      "framework": "NIST 800-171",
      "family": "Audit and Accountability",
      "control_id": "3.3.3",
      "cmmc_id": "AU.L2-3.3.3",
      "title": "EVENT REVIEW",
      "sprs": 1,
      "cmmc_levels": [
        "Level 2"
      ],
      "poam_allowed": "Yes",
      "ao_ids": [
        "3.3.3[a]",
        "3.3.3[b]",
        "3.3.3[c]"
      ],
      "assessment_methods": [
        {
          "type": "Examine",
          "description": "[SELECT FROM: Audit and accountability policy; procedures addressing audit records and event types; security plan; list of organization-defined event types to be logged; reviewed and updated records of logged event types; system audit logs and records; system incident reports; other relevant documents or records]."
        },
        {
          "type": "Interview",
          "description": "[SELECT FROM: Personnel with audit and accountability responsibilities; personnel with information security responsibilities]."
        },
        {
          "type": "Test",
          "description": "[SELECT FROM: Mechanisms supporting review and update of logged event types]."
        }
      ]
    },
    "last_ao_sentence": "event types being logged are updated based on the review."
  },
  {
    "text": "This is a NIST 800-171 control in the Audit and Accountability family. It corresponds to Level 2. The control ID is AU.L2-3.3.4 with title 'AUDIT FAILURE ALERTING'. Security requirement: Alert in the event of an audit logging process failure.. Assessment objective (3.3.4[a]): personnel or roles to be alerted in the event of an audit logging process failure are identified.. POA&M allowed: Yes. SPRS score: 1.\nThis is a NIST 800-171 control in the Audit and Accountability family. It corresponds to Level 2. The control ID is AU.L2-3.3.4 with title 'AUDIT FAILURE ALERTING'. Security requirement: Alert in the event of an audit logging process failure.. Assessment objective (3.3.4[b]): types of audit logging process failures for which alert will be generated are defined.. POA&M allowed: Yes. SPRS score: 1.\nThis is a NIST 800-171 control in the Audit and Accountability family. It corresponds to Level 2. The control ID is AU.L2-3.3.4 with title 'AUDIT FAILURE ALERTING'. Security requirement: Alert in the event of an audit logging process failure.. Assessment objective (3.3.4[c]): identified personnel or roles are alerted in the event of an audit logging process failure.. POA&M allowed: Yes. SPRS score: 1.",
    "metadata": {
      "framework": "NIST 800-171",
      "family": "Audit and Accountability",
      "control_id": "3.3.4",
      "cmmc_id": "AU.L2-3.3.4",
      "title": "AUDIT FAILURE ALERTING",
      "sprs": 1,
      "cmmc_levels": [
        "Level 2"
      ],
      "poam_allowed": "Yes",
      "ao_ids": [
        "3.3.4[a]",
        "3.3.4[b]",
        "3.3.4[c]"
      ],
      "assessment_methods": [
        {
          "type": "Examine",
          "description": "[SELECT FROM: Audit and accountability policy; procedures addressing response to audit logging processing failures; system design documentation; security plan; system configuration settings and associated documentation; list of personnel to be notified in case of an audit logging processing failure; system incident reports; system audit logs and records; other relevant documents or records]."
        },
        {
          "type": "Interview",
          "description": "[SELECT FROM: Personnel with audit and accountability responsibilities; personnel with information security responsibilities; system or network administrators; system developers]."
        },
        {
          "type": "Test",
          "description": "[SELECT FROM: Mechanisms implementing system response to audit logging processing failures]."
        }
      ]
    },
    "last_ao_sentence": "identified personnel or roles are alerted in the event of an audit logging process failure."
  },
  {
    "text": "This is a NIST 800-171 control in the Audit and Accountability family. It corresponds to Level 2. The control ID is AU.L2-3.3.5 with title 'AUDIT CORRELATION'. Security requirement: Correlate audit record review, analysis, and reporting processes for investigation and response to indications of unlawful, unauthorized, suspicious, or unusual activity.. Assessment objective (3.3.5[a]): audit record review, analysis, and reporting processes for investigation and response to indications of unlawful, unauthorized, suspicious, or unusual activity are defined.. POA&M allowed: No. SPRS score: 5.\nThis is a NIST 800-171 control in the Audit and Accountability family. It corresponds to Level 2. The control ID is AU.L2-3.3.5 with title 'AUDIT CORRELATION'. Security requirement: Correlate audit record review, analysis, and reporting processes for investigation and response to indications of unlawful, unauthorized, suspicious, or unusual activity.. Assessment objective (3.3.5[b]): defined audit record review, analysis, and reporting processes are correlated.. POA&M allowed: No. SPRS score: 5.",
    "metadata": {
      "framework": "NIST 800-171",
      "family": "Audit and Accountability",
      "control_id": "3.3.5",
      "cmmc_id": "AU.L2-3.3.5",
      "title": "AUDIT CORRELATION",
      "sprs": 5,
      "cmmc_levels": [
        "Level 2"
      ],
      "poam_allowed": "No",
      "ao_ids": [
        "3.3.5[a]",
        "3.3.5[b]"
      ],
      "assessment_methods": [
        {
          "type": "Examine",
          "description": "[SELECT FROM: Audit and accountability policy; procedures addressing audit record review, analysis, and reporting; security plan; system design documentation; system configuration settings and associated documentation; system audit logs and records across different repositories; other relevant documents or records]."
        },
        {
          "type": "Interview",
          "description": "[SELECT FROM: Personnel with audit record review, analysis, and reporting responsibilities; personnel with information security responsibilities]."
        },
        {
          "type": "Test",
          "description": ": [SELECT FROM: Mechanisms supporting analysis and correlation of audit records]."
        }
      ]
    },
    "last_ao_sentence": "defined audit record review, analysis, and reporting processes are correlated."
  },
  {
    "text": "This is a NIST 800-171 control in the Audit and Accountability family. It corresponds to Level 2. The control ID is AU.L2-3.3.6 with title 'REDUCTION & REPORTING'. Security requirement: Provide audit record reduction and report generation to support on-demand analysis and reporting.. Assessment objective (3.3.6[a]): an audit record reduction capability that supports on-demand analysis is provided.. POA&M allowed: Yes. SPRS score: 1.\nThis is a NIST 800-171 control in the Audit and Accountability family. It corresponds to Level 2. The control ID is AU.L2-3.3.6 with title 'REDUCTION & REPORTING'. Security requirement: Provide audit record reduction and report generation to support on-demand analysis and reporting.. Assessment objective (3.3.6[b]): a report generation capability that supports on-demand reporting is provided.. POA&M allowed: Yes. SPRS score: 1.",
    "metadata": {
      "framework": "NIST 800-171",
      "family": "Audit and Accountability",
      "control_id": "3.3.6",
      "cmmc_id": "AU.L2-3.3.6",
      "title": "REDUCTION & REPORTING",
      "sprs": 1,
      "cmmc_levels": [
        "Level 2"
      ],
      "poam_allowed": "Yes",
      "ao_ids": [
        "3.3.6[a]",
        "3.3.6[b]"
      ],
      "assessment_methods": [
        {
          "type": "Examine",
          "description": "[SELECT FROM: Audit and accountability policy; procedures addressing audit record reduction and report generation; system design documentation; security plan; system configuration settings and associated documentation; audit record reduction, review, analysis, and reporting tools; system audit logs and records; other relevant documents or records]."
        },
        {
          "type": "Interview",
          "description": "[SELECT FROM: Personnel with audit record reduction and report generation responsibilities; personnel with information security responsibilities]."
        },
        {
          "type": "Test",
          "description": "[SELECT FROM: Audit record reduction and report generation capability]."
        }
      ]
    },
    "last_ao_sentence": "a report generation capability that supports on-demand reporting is provided."
  },
  {
    "text": "This is a NIST 800-171 control in the Audit and Accountability family. It corresponds to Level 2. The control ID is AU.L2-3.3.7 with title 'AUTHORITATIVE TIME SOURCE'. Security requirement: Provide a system capability that compares and synchronizes internal system clocks with an authoritative source to generate time stamps for audit records.. Assessment objective (3.3.7[a]): internal system clocks are used to generate time stamps for audit records.. POA&M allowed: Yes. SPRS score: 1.\nThis is a NIST 800-171 control in the Audit and Accountability family. It corresponds to Level 2. The control ID is AU.L2-3.3.7 with title 'AUTHORITATIVE TIME SOURCE'. Security requirement: Provide a system capability that compares and synchronizes internal system clocks with an authoritative source to generate time stamps for audit records.. Assessment objective (3.3.7[b]): an authoritative source with which to compare and synchronize internal system clocks is specified.. POA&M allowed: Yes. SPRS score: 1.\nThis is a NIST 800-171 control in the Audit and Accountability family. It corresponds to Level 2. The control ID is AU.L2-3.3.7 with title 'AUTHORITATIVE TIME SOURCE'. Security requirement: Provide a system capability that compares and synchronizes internal system clocks with an authoritative source to generate time stamps for audit records.. Assessment objective (3.3.7[c]): internal system clocks used to generate time stamps for audit records are compared to and synchronized with the specified authoritative time source.. POA&M allowed: Yes. SPRS score: 1.",
    "metadata": {
      "framework": "NIST 800-171",
      "family": "Audit and Accountability",
      "control_id": "3.3.7",
      "cmmc_id": "AU.L2-3.3.7",
      "title": "AUTHORITATIVE TIME SOURCE",
      "sprs": 1,
      "cmmc_levels": [
        "Level 2"
      ],
      "poam_allowed": "Yes",
      "ao_ids": [
        "3.3.7[a]",
        "3.3.7[b]",
        "3.3.7[c]"
      ],
      "assessment_methods": [
        {
          "type": "Examine",
          "description": "[SELECT FROM: Audit and accountability policy; procedures addressing time stamp generation; system design documentation; security plan; system configuration settings and associated documentation; system audit logs and records; other relevant documents or records]."
        },
        {
          "type": "Interview",
          "description": "[SELECT FROM: Personnel with information security responsibilities; system or network administrators; system developers]."
        },
        {
          "type": "Test",
          "description": "[SELECT FROM: Mechanisms implementing time stamp generation]."
        }
      ]
    },
    "last_ao_sentence": "internal system clocks used to generate time stamps for audit records are compared to and synchronized with the specified authoritative time source."
  },
  {
    "text": "This is a NIST 800-171 control in the Audit and Accountability family. It corresponds to Level 2. The control ID is AU.L2-3.3.8 with title 'AUDIT PROTECTION'. Security requirement: Protect audit information and audit logging tools from unauthorized access, modification, and deletion.. Assessment objective (3.3.8[a]): audit information is protected from unauthorized access.. POA&M allowed: Yes. SPRS score: 1.\nThis is a NIST 800-171 control in the Audit and Accountability family. It corresponds to Level 2. The control ID is AU.L2-3.3.8 with title 'AUDIT PROTECTION'. Security requirement: Protect audit information and audit logging tools from unauthorized access, modification, and deletion.. Assessment objective (3.3.8[b]): audit information is protected from unauthorized modification.. POA&M allowed: Yes. SPRS score: 1.\nThis is a NIST 800-171 control in the Audit and Accountability family. It corresponds to Level 2. The control ID is AU.L2-3.3.8 with title 'AUDIT PROTECTION'. Security requirement: Protect audit information and audit logging tools from unauthorized access, modification, and deletion.. Assessment objective (3.3.8[c]): audit information is protected from unauthorized deletion.. POA&M allowed: Yes. SPRS score: 1.\nThis is a NIST 800-171 control in the Audit and Accountability family. It corresponds to Level 2. The control ID is AU.L2-3.3.8 with title 'AUDIT PROTECTION'. Security requirement: Protect audit information and audit logging tools from unauthorized access, modification, and deletion.. Assessment objective (3.3.8[d]): audit logging tools are protected from unauthorized access.. POA&M allowed: Yes. SPRS score: 1.\nThis is a NIST 800-171 control in the Audit and Accountability family. It corresponds to Level 2. The control ID is AU.L2-3.3.8 with title 'AUDIT PROTECTION'. Security requirement: Protect audit information and audit logging tools from unauthorized access, modification, and deletion.. Assessment objective (3.3.8[e]): audit logging tools are protected from unauthorized modification.. POA&M allowed: Yes. SPRS score: 1.\nThis is a NIST 800-171 control in the Audit and Accountability family. It corresponds to Level 2. The control ID is AU.L2-3.3.8 with title 'AUDIT PROTECTION'. Security requirement: Protect audit information and audit logging tools from unauthorized access, modification, and deletion.. Assessment objective (3.3.8[f]): audit logging tools are protected from unauthorized deletion.. POA&M allowed: Yes. SPRS score: 1.",
    "metadata": {
      "framework": "NIST 800-171",
      "family": "Audit and Accountability",
      "control_id": "3.3.8",
      "cmmc_id": "AU.L2-3.3.8",
      "title": "AUDIT PROTECTION",
      "sprs": 1,
      "cmmc_levels": [
        "Level 2"
      ],
      "poam_allowed": "Yes",
      "ao_ids": [
        "3.3.8[a]",
        "3.3.8[b]",
        "3.3.8[c]",
        "3.3.8[d]",
        "3.3.8[e]",
        "3.3.8[f]"
      ],
      "assessment_methods": [
        {
          "type": "Examine",
          "description": "[SELECT FROM: Audit and accountability policy; access control policy and procedures; procedures addressing protection of audit information; security plan; system design documentation; system configuration settings and associated documentation, system audit logs and records; audit logging tools; other relevant documents or records]."
        },
        {
          "type": "Interview",
          "description": "[SELECT FROM: Personnel with audit and accountability responsibilities; personnel with information security responsibilities; system or network administrators; system developers]."
        },
        {
          "type": "Test",
          "description": "[SELECT FROM: Mechanisms implementing audit information protection]."
        }
      ]
    },
    "last_ao_sentence": "audit logging tools are protected from unauthorized deletion."
  },
  {
    "text": "This is a NIST 800-171 control in the Audit and Accountability family. It corresponds to Level 2. The control ID is AU.L2-3.3.9 with title 'AUDIT MANAGEMENT'. Security requirement: Limit management of audit logging functionality to a subset of privileged users.. Assessment objective (3.3.9[a]): a subset of privileged users granted access to manage audit logging functionality is defined.. POA&M allowed: Yes. SPRS score: 1.\nThis is a NIST 800-171 control in the Audit and Accountability family. It corresponds to Level 2. The control ID is AU.L2-3.3.9 with title 'AUDIT MANAGEMENT'. Security requirement: Limit management of audit logging functionality to a subset of privileged users.. Assessment objective (3.3.9[b]): management of audit logging functionality is limited to the defined subset of privileged users.. POA&M allowed: Yes. SPRS score: 1.",
    "metadata": {
      "framework": "NIST 800-171",
      "family": "Audit and Accountability",
      "control_id": "3.3.9",
      "cmmc_id": "AU.L2-3.3.9",
      "title": "AUDIT MANAGEMENT",
      "sprs": 1,
      "cmmc_levels": [
        "Level 2"
      ],
      "poam_allowed": "Yes",
      "ao_ids": [
        "3.3.9[a]",
        "3.3.9[b]"
      ],
      "assessment_methods": [
        {
          "type": "Examine",
          "description": "[SELECT FROM: Audit and accountability policy; access control policy and procedures; procedures addressing protection of audit information; security plan; system design documentation; system configuration settings and associated documentation; access authorizations; system-generated list of privileged users with access to management of audit logging functionality; access control list; system audit logs and records; other relevant documents or records]."
        },
        {
          "type": "Interview",
          "description": "[SELECT FROM: Personnel with audit and accountability responsibilities; personnel with information security responsibilities; system or network administrators; system developers]."
        },
        {
          "type": "Test",
          "description": "[SELECT FROM: Mechanisms managing access to audit logging functionality]."
        }
      ]
    },
    "last_ao_sentence": "management of audit logging functionality is limited to the defined subset of privileged users."
  },
  {
    "text": "This is a NIST 800-171 control in the Configuration Management family. It corresponds to Level 2. The control ID is CM.L2-3.4.1 with title 'SYSTEM BASELINING'. Security requirement: Establish and maintain baseline configurations and inventories of organizational systems (including hardware, software, firmware, and documentation) throughout the respective system development life cycles.. Assessment objective (3.4.1[a]): a baseline configuration is established.. POA&M allowed: No. SPRS score: 5.\nThis is a NIST 800-171 control in the Configuration Management family. It corresponds to Level 2. The control ID is CM.L2-3.4.1 with title 'SYSTEM BASELINING'. Security requirement: Establish and maintain baseline configurations and inventories of organizational systems (including hardware, software, firmware, and documentation) throughout the respective system development life cycles.. Assessment objective (3.4.1[b]): the baseline configuration includes hardware, software, firmware, and documentation.. POA&M allowed: No. SPRS score: 5.\nThis is a NIST 800-171 control in the Configuration Management family. It corresponds to Level 2. The control ID is CM.L2-3.4.1 with title 'SYSTEM BASELINING'. Security requirement: Establish and maintain baseline configurations and inventories of organizational systems (including hardware, software, firmware, and documentation) throughout the respective system development life cycles.. Assessment objective (3.4.1[c]): the baseline configuration is maintained (reviewed and updated) throughout the system development life cycle.. POA&M allowed: No. SPRS score: 5.\nThis is a NIST 800-171 control in the Configuration Management family. It corresponds to Level 2. The control ID is CM.L2-3.4.1 with title 'SYSTEM BASELINING'. Security requirement: Establish and maintain baseline configurations and inventories of organizational systems (including hardware, software, firmware, and documentation) throughout the respective system development life cycles.. Assessment objective (3.4.1[d]): a system inventory is established.. POA&M allowed: No. SPRS score: 5.\nThis is a NIST 800-171 control in the Configuration Management family. It corresponds to Level 2. The control ID is CM.L2-3.4.1 with title 'SYSTEM BASELINING'. Security requirement: Establish and maintain baseline configurations and inventories of organizational systems (including hardware, software, firmware, and documentation) throughout the respective system development life cycles.. Assessment objective (3.4.1[e]): the system inventory includes hardware, software, firmware, and documentation.. POA&M allowed: No. SPRS score: 5.\nThis is a NIST 800-171 control in the Configuration Management family. It corresponds to Level 2. The control ID is CM.L2-3.4.1 with title 'SYSTEM BASELINING'. Security requirement: Establish and maintain baseline configurations and inventories of organizational systems (including hardware, software, firmware, and documentation) throughout the respective system development life cycles.. Assessment objective (3.4.1[f]): the inventory is maintained (reviewed and updated) throughout the system development life cycle.. POA&M allowed: No. SPRS score: 5.",
    "metadata": {
      "framework": "NIST 800-171",
      "family": "Configuration Management",
      "control_id": "3.4.1",
      "cmmc_id": "CM.L2-3.4.1",
      "title": "SYSTEM BASELINING",
      "sprs": 5,
      "cmmc_levels": [
        "Level 2"
      ],
      "poam_allowed": "No",
      "ao_ids": [
        "3.4.1[a]",
        "3.4.1[b]",
        "3.4.1[c]",
        "3.4.1[d]",
        "3.4.1[e]",
        "3.4.1[f]"
      ],
      "assessment_methods": [
        {
          "type": "Examine",
          "description": "[SELECT FROM: Configuration management policy; procedures addressing the baseline configuration of the system; procedures addressing system inventory; security plan; configuration management plan; system inventory records; inventory review and update records; enterprise architecture documentation; system design documentation; system architecture and configuration documentation; system configuration settings and associated documentation; change control records; system component installation records; system component removal records; other relevant documents or records]."
        },
        {
          "type": "Interview",
          "description": "[SELECT FROM:  Personnel with configuration management responsibilities; personnel with responsibilities for establishing the system inventory; personnel with responsibilities for updating the system inventory; personnel with information security responsibilities; system or network administrators]."
        },
        {
          "type": "Test",
          "description": "[SELECT FROM:  Organizational processes for managing baseline configurations; mechanisms supporting configuration control of the baseline configuration; organizational processes for developing and documenting an inventory of system components; organizational processes for updating inventory of system components; mechanisms supporting or implementing the system inventory; mechanisms implementing updating of the system inventory]."
        }
      ]
    },
    "last_ao_sentence": "the inventory is maintained (reviewed and updated) throughout the system development life cycle."
  },
  {
    "text": "This is a NIST 800-171 control in the Configuration Management family. It corresponds to Level 2. The control ID is CM.L2-3.4.2 with title 'SECURITY CONFIGURATION ENFORCEMENT'. Security requirement: Establish and enforce security configuration settings for information technology products employed in organizational systems.. Assessment objective (3.4.2[a]): security configuration settings for information technology products employed in the system are established and included in the baseline configuration.. POA&M allowed: No. SPRS score: 5.\nThis is a NIST 800-171 control in the Configuration Management family. It corresponds to Level 2. The control ID is CM.L2-3.4.2 with title 'SECURITY CONFIGURATION ENFORCEMENT'. Security requirement: Establish and enforce security configuration settings for information technology products employed in organizational systems.. Assessment objective (3.4.2[b]): security configuration settings for information technology products employed in the system are enforced.. POA&M allowed: No. SPRS score: 5.",
    "metadata": {
      "framework": "NIST 800-171",
      "family": "Configuration Management",
      "control_id": "3.4.2",
      "cmmc_id": "CM.L2-3.4.2",
      "title": "SECURITY CONFIGURATION ENFORCEMENT",
      "sprs": 5,
      "cmmc_levels": [
        "Level 2"
      ],
      "poam_allowed": "No",
      "ao_ids": [
        "3.4.2[a]",
        "3.4.2[b]"
      ],
      "assessment_methods": [
        {
          "type": "Examine",
          "description": "[SELECT FROM:  Configuration management policy; procedures addressing configuration settings for the system; configuration management plan; security plan; system design documentation; system configuration settings and associated documentation; security configuration checklists; evidence supporting approved deviations from established configuration settings; change control records; system audit logs and records; other relevant documents or records]."
        },
        {
          "type": "Interview",
          "description": "[SELECT FROM: Personnel with security configuration management responsibilities; personnel with information security responsibilities; system or network administrators]."
        },
        {
          "type": "Test",
          "description": "[SELECT FROM: Organizational processes for managing configuration settings; mechanisms that implement, monitor, and/or control system configuration settings; mechanisms that identify and/or document deviations from established configuration settings]."
        }
      ]
    },
    "last_ao_sentence": "security configuration settings for information technology products employed in the system are enforced."
  },
  {
    "text": "This is a NIST 800-171 control in the Configuration Management family. It corresponds to Level 2. The control ID is CM.L2-3.4.3 with title 'SYSTEM CHANGE MANAGEMENT'. Security requirement: Track, review, approve or disapprove, and log changes to organizational systems.. Assessment objective (3.4.3[a]): changes to the system are tracked.. POA&M allowed: Yes. SPRS score: 1.\nThis is a NIST 800-171 control in the Configuration Management family. It corresponds to Level 2. The control ID is CM.L2-3.4.3 with title 'SYSTEM CHANGE MANAGEMENT'. Security requirement: Track, review, approve or disapprove, and log changes to organizational systems.. Assessment objective (3.4.3[b]): changes to the system are reviewed.. POA&M allowed: Yes. SPRS score: 1.\nThis is a NIST 800-171 control in the Configuration Management family. It corresponds to Level 2. The control ID is CM.L2-3.4.3 with title 'SYSTEM CHANGE MANAGEMENT'. Security requirement: Track, review, approve or disapprove, and log changes to organizational systems.. Assessment objective (3.4.3[c]): changes to the system are approved or disapproved.. POA&M allowed: Yes. SPRS score: 1.\nThis is a NIST 800-171 control in the Configuration Management family. It corresponds to Level 2. The control ID is CM.L2-3.4.3 with title 'SYSTEM CHANGE MANAGEMENT'. Security requirement: Track, review, approve or disapprove, and log changes to organizational systems.. Assessment objective (3.4.3[d]): changes to the system are logged.. POA&M allowed: Yes. SPRS score: 1.",
    "metadata": {
      "framework": "NIST 800-171",
      "family": "Configuration Management",
      "control_id": "3.4.3",
      "cmmc_id": "CM.L2-3.4.3",
      "title": "SYSTEM CHANGE MANAGEMENT",
      "sprs": 1,
      "cmmc_levels": [
        "Level 2"
      ],
      "poam_allowed": "Yes",
      "ao_ids": [
        "3.4.3[a]",
        "3.4.3[b]",
        "3.4.3[c]",
        "3.4.3[d]"
      ],
      "assessment_methods": [
        {
          "type": "Examine",
          "description": "[SELECT FROM: Configuration management policy; procedures addressing system configuration change control; configuration management plan; system architecture and configuration documentation; security plan; change control records; system audit logs and records; change control audit and review reports; agenda/minutes from configuration change control oversight meetings; other relevant documents or records]."
        },
        {
          "type": "Interview",
          "description": "[SELECT FROM: Personnel with configuration change control responsibilities; personnel with information security responsibilities; system or network administrators; members of change control board or similar]."
        },
        {
          "type": "Test",
          "description": "[SELECT FROM: Organizational processes for configuration change control; mechanisms that implement configuration change control]."
        }
      ]
    },
    "last_ao_sentence": "changes to the system are logged."
  },
  {
    "text": "This is a NIST 800-171 control in the Configuration Management family. It corresponds to Level 2. The control ID is CM.L2-3.4.4 with title 'SECURITY IMPACT ANALYSIS'. Security requirement: Analyze the security impact of changes prior to implementation.. Assessment objective (3.4.4): Determine if the security impact of changes to each organizational system is analyzed prior to implementation.. POA&M allowed: Yes. SPRS score: 1.",
    "metadata": {
      "framework": "NIST 800-171",
      "family": "Configuration Management",
      "control_id": "3.4.4",
      "cmmc_id": "CM.L2-3.4.4",
      "title": "SECURITY IMPACT ANALYSIS",
      "sprs": 1,
      "cmmc_levels": [
        "Level 2"
      ],
      "poam_allowed": "Yes",
      "ao_ids": [
        "3.4.4"
      ],
      "assessment_methods": [
        {
          "type": "Examine",
          "description": "[SELECT FROM: Configuration management policy; procedures addressing security impact analysis for changes to the system; configuration management plan; security impact analysis documentation; security plan; analysis tools and associated outputs; change control records; system audit logs and records; other relevant documents or records]."
        },
        {
          "type": "Interview",
          "description": "[SELECT FROM: Personnel with responsibility for conducting security impact analysis; personnel with information security responsibilities; system or network administrators]."
        },
        {
          "type": "Test",
          "description": "[SELECT FROM: Organizational processes for security impact analysis]."
        }
      ]
    },
    "last_ao_sentence": "Determine if the security impact of changes to each organizational system is analyzed prior to implementation."
  },
  {
    "text": "This is a NIST 800-171 control in the Configuration Management family. It corresponds to Level 2. The control ID is CM.L2-3.4.5 with title 'ACCESS RESTRICTIONS FOR CHANGE'. Security requirement: Define, document, approve, and enforce physical and logical access restrictions associated with changes to organizational systems.. Assessment objective (3.4.5[a]): physical access restrictions associated with changes to the system are defined.. POA&M allowed: No. SPRS score: 5.\nThis is a NIST 800-171 control in the Configuration Management family. It corresponds to Level 2. The control ID is CM.L2-3.4.5 with title 'ACCESS RESTRICTIONS FOR CHANGE'. Security requirement: Define, document, approve, and enforce physical and logical access restrictions associated with changes to organizational systems.. Assessment objective (3.4.5[b]): physical access restrictions associated with changes to the system are documented.. POA&M allowed: No. SPRS score: 5.\nThis is a NIST 800-171 control in the Configuration Management family. It corresponds to Level 2. The control ID is CM.L2-3.4.5 with title 'ACCESS RESTRICTIONS FOR CHANGE'. Security requirement: Define, document, approve, and enforce physical and logical access restrictions associated with changes to organizational systems.. Assessment objective (3.4.5[c]): physical access restrictions associated with changes to the system are approved.. POA&M allowed: No. SPRS score: 5.\nThis is a NIST 800-171 control in the Configuration Management family. It corresponds to Level 2. The control ID is CM.L2-3.4.5 with title 'ACCESS RESTRICTIONS FOR CHANGE'. Security requirement: Define, document, approve, and enforce physical and logical access restrictions associated with changes to organizational systems.. Assessment objective (3.4.5[d]): physical access restrictions associated with changes to the system are enforced.. POA&M allowed: No. SPRS score: 5.\nThis is a NIST 800-171 control in the Configuration Management family. It corresponds to Level 2. The control ID is CM.L2-3.4.5 with title 'ACCESS RESTRICTIONS FOR CHANGE'. Security requirement: Define, document, approve, and enforce physical and logical access restrictions associated with changes to organizational systems.. Assessment objective (3.4.5[e]): logical access restrictions associated with changes to the system are defined.. POA&M allowed: No. SPRS score: 5.\nThis is a NIST 800-171 control in the Configuration Management family. It corresponds to Level 2. The control ID is CM.L2-3.4.5 with title 'ACCESS RESTRICTIONS FOR CHANGE'. Security requirement: Define, document, approve, and enforce physical and logical access restrictions associated with changes to organizational systems.. Assessment objective (3.4.5[f]): logical access restrictions associated with changes to the system are documented.. POA&M allowed: No. SPRS score: 5.\nThis is a NIST 800-171 control in the Configuration Management family. It corresponds to Level 2. The control ID is CM.L2-3.4.5 with title 'ACCESS RESTRICTIONS FOR CHANGE'. Security requirement: Define, document, approve, and enforce physical and logical access restrictions associated with changes to organizational systems.. Assessment objective (3.4.5[g]): logical access restrictions associated with changes to the system are approved.. POA&M allowed: No. SPRS score: 5.\nThis is a NIST 800-171 control in the Configuration Management family. It corresponds to Level 2. The control ID is CM.L2-3.4.5 with title 'ACCESS RESTRICTIONS FOR CHANGE'. Security requirement: Define, document, approve, and enforce physical and logical access restrictions associated with changes to organizational systems.. Assessment objective (3.4.5[h]): logical access restrictions associated with changes to the system are enforced.. POA&M allowed: No. SPRS score: 5.",
    "metadata": {
      "framework": "NIST 800-171",
      "family": "Configuration Management",
      "control_id": "3.4.5",
      "cmmc_id": "CM.L2-3.4.5",
      "title": "ACCESS RESTRICTIONS FOR CHANGE",
      "sprs": 5,
      "cmmc_levels": [
        "Level 2"
      ],
      "poam_allowed": "No",
      "ao_ids": [
        "3.4.5[a]",
        "3.4.5[b]",
        "3.4.5[c]",
        "3.4.5[d]",
        "3.4.5[e]",
        "3.4.5[f]",
        "3.4.5[g]",
        "3.4.5[h]"
      ],
      "assessment_methods": [
        {
          "type": "Examine",
          "description": "[SELECT FROM: Configuration management policy; procedures addressing access restrictions for changes to the system; security plan; configuration management plan; system design documentation; system architecture and configuration documentation; system configuration settings and associated documentation; logical access approvals; physical access approvals; access credentials; change control records; system audit logs and records; other relevant documents or records]."
        },
        {
          "type": "Interview",
          "description": "[SELECT FROM: Personnel with logical access control responsibilities; personnel with physical access control responsibilities; personnel with information security responsibilities; system or network administrators]."
        },
        {
          "type": "Test",
          "description": "[SELECT FROM: Organizational processes for managing access restrictions associated with changes to the system; mechanisms supporting, implementing, and enforcing access restrictions associated with changes to the system]."
        }
      ]
    },
    "last_ao_sentence": "logical access restrictions associated with changes to the system are enforced."
  },
  {
    "text": "This is a NIST 800-171 control in the Configuration Management family. It corresponds to Level 2. The control ID is CM.L2-3.4.6 with title 'LEAST FUNCTIONALITY'. Security requirement: Employ the principle of least functionality by configuring organizational systems to provide only essential capabilities.. Assessment objective (3.4.6[a]): essential system capabilities are defined based on the principle of least functionality.. POA&M allowed: No. SPRS score: 5.\nThis is a NIST 800-171 control in the Configuration Management family. It corresponds to Level 2. The control ID is CM.L2-3.4.6 with title 'LEAST FUNCTIONALITY'. Security requirement: Employ the principle of least functionality by configuring organizational systems to provide only essential capabilities.. Assessment objective (3.4.6[b]): the system is configured to provide only the defined essential capabilities.. POA&M allowed: No. SPRS score: 5.",
    "metadata": {
      "framework": "NIST 800-171",
      "family": "Configuration Management",
      "control_id": "3.4.6",
      "cmmc_id": "CM.L2-3.4.6",
      "title": "LEAST FUNCTIONALITY",
      "sprs": 5,
      "cmmc_levels": [
        "Level 2"
      ],
      "poam_allowed": "No",
      "ao_ids": [
        "3.4.6[a]",
        "3.4.6[b]"
      ],
      "assessment_methods": [
        {
          "type": "Examine",
          "description": "[SELECT FROM: Configuration management policy; configuration management plan; procedures addressing least functionality in the system; security plan; system design documentation; system configuration settings and associated documentation; security configuration checklists; other relevant documents or records]."
        },
        {
          "type": "Interview",
          "description": "[SELECT FROM: Personnel with security configuration management responsibilities; personnel with information security responsibilities; system or network administrators]."
        },
        {
          "type": "Test",
          "description": "[SELECT FROM: Organizational processes prohibiting or restricting functions, ports, protocols, or services; mechanisms implementing restrictions or prohibition of functions, ports, protocols, or services]."
        }
      ]
    },
    "last_ao_sentence": "the system is configured to provide only the defined essential capabilities."
  },
  {
    "text": "This is a NIST 800-171 control in the Configuration Management family. It corresponds to Level 2. The control ID is CM.L2-3.4.7 with title 'NONESSENTIAL FUNCTIONALITY'. Security requirement: Restrict, disable, or prevent the use of nonessential programs, functions, ports, protocols, and services.. Assessment objective (3.4.7[a]): essential programs are defined.. POA&M allowed: No. SPRS score: 5.\nThis is a NIST 800-171 control in the Configuration Management family. It corresponds to Level 2. The control ID is CM.L2-3.4.7 with title 'NONESSENTIAL FUNCTIONALITY'. Security requirement: Restrict, disable, or prevent the use of nonessential programs, functions, ports, protocols, and services.. Assessment objective (3.4.7[b]): the use of nonessential programs is defined.. POA&M allowed: No. SPRS score: 5.\nThis is a NIST 800-171 control in the Configuration Management family. It corresponds to Level 2. The control ID is CM.L2-3.4.7 with title 'NONESSENTIAL FUNCTIONALITY'. Security requirement: Restrict, disable, or prevent the use of nonessential programs, functions, ports, protocols, and services.. Assessment objective (3.4.7[c]): the use of nonessential programs is restricted, disabled, or prevented as defined.. POA&M allowed: No. SPRS score: 5.\nThis is a NIST 800-171 control in the Configuration Management family. It corresponds to Level 2. The control ID is CM.L2-3.4.7 with title 'NONESSENTIAL FUNCTIONALITY'. Security requirement: Restrict, disable, or prevent the use of nonessential programs, functions, ports, protocols, and services.. Assessment objective (3.4.7[d]): essential functions are defined.. POA&M allowed: No. SPRS score: 5.\nThis is a NIST 800-171 control in the Configuration Management family. It corresponds to Level 2. The control ID is CM.L2-3.4.7 with title 'NONESSENTIAL FUNCTIONALITY'. Security requirement: Restrict, disable, or prevent the use of nonessential programs, functions, ports, protocols, and services.. Assessment objective (3.4.7[e]): the use of nonessential functions is defined.. POA&M allowed: No. SPRS score: 5.\nThis is a NIST 800-171 control in the Configuration Management family. It corresponds to Level 2. The control ID is CM.L2-3.4.7 with title 'NONESSENTIAL FUNCTIONALITY'. Security requirement: Restrict, disable, or prevent the use of nonessential programs, functions, ports, protocols, and services.. Assessment objective (3.4.7[f]): the use of nonessential functions is restricted, disabled, or prevented as defined.. POA&M allowed: No. SPRS score: 5.\nThis is a NIST 800-171 control in the Configuration Management family. It corresponds to Level 2. The control ID is CM.L2-3.4.7 with title 'NONESSENTIAL FUNCTIONALITY'. Security requirement: Restrict, disable, or prevent the use of nonessential programs, functions, ports, protocols, and services.. Assessment objective (3.4.7[g]): essential ports are defined.. POA&M allowed: No. SPRS score: 5.\nThis is a NIST 800-171 control in the Configuration Management family. It corresponds to Level 2. The control ID is CM.L2-3.4.7 with title 'NONESSENTIAL FUNCTIONALITY'. Security requirement: Restrict, disable, or prevent the use of nonessential programs, functions, ports, protocols, and services.. Assessment objective (3.4.7[h]): the use of nonessential ports is defined.. POA&M allowed: No. SPRS score: 5.\nThis is a NIST 800-171 control in the Configuration Management family. It corresponds to Level 2. The control ID is CM.L2-3.4.7 with title 'NONESSENTIAL FUNCTIONALITY'. Security requirement: Restrict, disable, or prevent the use of nonessential programs, functions, ports, protocols, and services.. Assessment objective (3.4.7[i]): the use of nonessential ports is restricted, disabled, or prevented as defined.. POA&M allowed: No. SPRS score: 5.\nThis is a NIST 800-171 control in the Configuration Management family. It corresponds to Level 2. The control ID is CM.L2-3.4.7 with title 'NONESSENTIAL FUNCTIONALITY'. Security requirement: Restrict, disable, or prevent the use of nonessential programs, functions, ports, protocols, and services.. Assessment objective (3.4.7[j]): essential protocols are defined.. POA&M allowed: No. SPRS score: 5.\nThis is a NIST 800-171 control in the Configuration Management family. It corresponds to Level 2. The control ID is CM.L2-3.4.7 with title 'NONESSENTIAL FUNCTIONALITY'. Security requirement: Restrict, disable, or prevent the use of nonessential programs, functions, ports, protocols, and services.. Assessment objective (3.4.7[k]): the use of nonessential protocols is defined.. POA&M allowed: No. SPRS score: 5.\nThis is a NIST 800-171 control in the Configuration Management family. It corresponds to Level 2. The control ID is CM.L2-3.4.7 with title 'NONESSENTIAL FUNCTIONALITY'. Security requirement: Restrict, disable, or prevent the use of nonessential programs, functions, ports, protocols, and services.. Assessment objective (3.4.7[l]): the use of nonessential protocols is restricted, disabled, or prevented as defined.. POA&M allowed: No. SPRS score: 5.\nThis is a NIST 800-171 control in the Configuration Management family. It corresponds to Level 2. The control ID is CM.L2-3.4.7 with title 'NONESSENTIAL FUNCTIONALITY'. Security requirement: Restrict, disable, or prevent the use of nonessential programs, functions, ports, protocols, and services.. Assessment objective (3.4.7[m]): essential services are defined.. POA&M allowed: No. SPRS score: 5.\nThis is a NIST 800-171 control in the Configuration Management family. It corresponds to Level 2. The control ID is CM.L2-3.4.7 with title 'NONESSENTIAL FUNCTIONALITY'. Security requirement: Restrict, disable, or prevent the use of nonessential programs, functions, ports, protocols, and services.. Assessment objective (3.4.7[n]): the use of nonessential services is defined.. POA&M allowed: No. SPRS score: 5.\nThis is a NIST 800-171 control in the Configuration Management family. It corresponds to Level 2. The control ID is CM.L2-3.4.7 with title 'NONESSENTIAL FUNCTIONALITY'. Security requirement: Restrict, disable, or prevent the use of nonessential programs, functions, ports, protocols, and services.. Assessment objective (3.4.7[o]): the use of nonessential services is restricted, disabled, or prevented as defined.. POA&M allowed: No. SPRS score: 5.",
    "metadata": {
      "framework": "NIST 800-171",
      "family": "Configuration Management",
      "control_id": "3.4.7",
      "cmmc_id": "CM.L2-3.4.7",
      "title": "NONESSENTIAL FUNCTIONALITY",
      "sprs": 5,
      "cmmc_levels": [
        "Level 2"
      ],
      "poam_allowed": "No",
      "ao_ids": [
        "3.4.7[a]",
        "3.4.7[b]",
        "3.4.7[c]",
        "3.4.7[d]",
        "3.4.7[e]",
        "3.4.7[f]",
        "3.4.7[g]",
        "3.4.7[h]",
        "3.4.7[i]",
        "3.4.7[j]",
        "3.4.7[k]",
        "3.4.7[l]",
        "3.4.7[m]",
        "3.4.7[n]",
        "3.4.7[o]"
      ],
      "assessment_methods": [
        {
          "type": "Examine",
          "description": "[SELECT FROM: Configuration management policy; procedures addressing least functionality in the system; configuration management plan; security plan; system design documentation; system configuration settings and associated documentation;  specifications for preventing software program execution; security configuration checklists; documented reviews of programs, functions, ports, protocols, and/or services; change control records; system audit logs and records; other relevant documents or records]."
        },
        {
          "type": "Interview",
          "description": "[SELECT FROM: Personnel with responsibilities for reviewing programs, functions, ports, protocols, and services on the system; personnel with information security responsibilities; system or network administrators; system developers]."
        },
        {
          "type": "Test",
          "description": "[SELECT FROM: Organizational processes for reviewing and disabling nonessential programs, functions, ports, protocols, or services; mechanisms implementing review and handling of nonessential programs, functions, ports, protocols, or services; organizational processes preventing program execution on the system; organizational processes for software program usage and restrictions; mechanisms supporting or implementing software program usage and restrictions; mechanisms preventing program execution on the system]."
        }
      ]
    },
    "last_ao_sentence": "the use of nonessential services is restricted, disabled, or prevented as defined."
  },
  {
    "text": "This is a NIST 800-171 control in the Configuration Management family. It corresponds to Level 2. The control ID is CM.L2-3.4.8 with title 'APPLICATION EXECUTION POLICY'. Security requirement: Apply deny-by-exception (blacklisting) policy to prevent the use of unauthorized software or deny-all, permit-by-exception (whitelisting) policy to allow the execution of authorized software.. Assessment objective (3.4.8[a]): a policy specifying whether whitelisting or blacklisting is to be implemented is specified.. POA&M allowed: No. SPRS score: 5.\nThis is a NIST 800-171 control in the Configuration Management family. It corresponds to Level 2. The control ID is CM.L2-3.4.8 with title 'APPLICATION EXECUTION POLICY'. Security requirement: Apply deny-by-exception (blacklisting) policy to prevent the use of unauthorized software or deny-all, permit-by-exception (whitelisting) policy to allow the execution of authorized software.. Assessment objective (3.4.8[b]): the software allowed to execute under whitelisting or denied use under blacklisting is specified.. POA&M allowed: No. SPRS score: 5.\nThis is a NIST 800-171 control in the Configuration Management family. It corresponds to Level 2. The control ID is CM.L2-3.4.8 with title 'APPLICATION EXECUTION POLICY'. Security requirement: Apply deny-by-exception (blacklisting) policy to prevent the use of unauthorized software or deny-all, permit-by-exception (whitelisting) policy to allow the execution of authorized software.. Assessment objective (3.4.8[c]): whitelisting to allow the execution of authorized software or blacklisting to prevent the use of unauthorized software is implemented as specified.. POA&M allowed: No. SPRS score: 5.",
    "metadata": {
      "framework": "NIST 800-171",
      "family": "Configuration Management",
      "control_id": "3.4.8",
      "cmmc_id": "CM.L2-3.4.8",
      "title": "APPLICATION EXECUTION POLICY",
      "sprs": 5,
      "cmmc_levels": [
        "Level 2"
      ],
      "poam_allowed": "No",
      "ao_ids": [
        "3.4.8[a]",
        "3.4.8[b]",
        "3.4.8[c]"
      ],
      "assessment_methods": [
        {
          "type": "Examine",
          "description": "[SELECT FROM: Configuration management policy; procedures addressing least functionality in the system; security plan; configuration management plan; system design documentation; system configuration settings and associated documentation; list of software programs not authorized to execute on the system; list of software programs authorized to execute on the system; security configuration checklists; review and update records associated with list of authorized or unauthorized software programs; change control records; system audit logs and records; other relevant documents or records]."
        },
        {
          "type": "Interview",
          "description": "[SELECT FROM: Personnel with responsibilities for identifying software authorized or not authorized to execute on the system; personnel with information security responsibilities; system or network administrators]."
        },
        {
          "type": "Test",
          "description": "[SELECT FROM: Organizational process for identifying, reviewing, and updating programs authorized or not authorized to execute on the system; process for implementing blacklisting or whitelisting; mechanisms supporting or implementing blacklisting or whitelisting]."
        }
      ]
    },
    "last_ao_sentence": "whitelisting to allow the execution of authorized software or blacklisting to prevent the use of unauthorized software is implemented as specified."
  },
  {
    "text": "This is a NIST 800-171 control in the Configuration Management family. It corresponds to Level 2. The control ID is CM.L2-3.4.9 with title 'USER-INSTALLED SOFTWARE'. Security requirement: Control and monitor user-installed software.. Assessment objective (3.4.9[a]): a policy for controlling the installation of software by users is established.. POA&M allowed: Yes. SPRS score: 1.\nThis is a NIST 800-171 control in the Configuration Management family. It corresponds to Level 2. The control ID is CM.L2-3.4.9 with title 'USER-INSTALLED SOFTWARE'. Security requirement: Control and monitor user-installed software.. Assessment objective (3.4.9[b]): installation of software by users is controlled based on the established policy.. POA&M allowed: Yes. SPRS score: 1.\nThis is a NIST 800-171 control in the Configuration Management family. It corresponds to Level 2. The control ID is CM.L2-3.4.9 with title 'USER-INSTALLED SOFTWARE'. Security requirement: Control and monitor user-installed software.. Assessment objective (3.4.9[c]): installation of software by users is monitored.. POA&M allowed: Yes. SPRS score: 1.",
    "metadata": {
      "framework": "NIST 800-171",
      "family": "Configuration Management",
      "control_id": "3.4.9",
      "cmmc_id": "CM.L2-3.4.9",
      "title": "USER-INSTALLED SOFTWARE",
      "sprs": 1,
      "cmmc_levels": [
        "Level 2"
      ],
      "poam_allowed": "Yes",
      "ao_ids": [
        "3.4.9[a]",
        "3.4.9[b]",
        "3.4.9[c]"
      ],
      "assessment_methods": [
        {
          "type": "Examine",
          "description": "[SELECT FROM: Configuration management policy; procedures addressing user installed software; configuration management plan; security plan; system design documentation; system configuration settings and associated documentation; list of rules governing user-installed software; system monitoring records; system audit logs and records; continuous monitoring strategy; other relevant documents or records]."
        },
        {
          "type": "Interview",
          "description": "[SELECT FROM: Personnel with responsibilities for governing user-installed software; personnel operating, using, or maintaining the system; personnel monitoring compliance with user-installed software policy; personnel with information security responsibilities; system or network administrators]."
        },
        {
          "type": "Test",
          "description": "[SELECT FROM: Organizational processes governing user-installed software on the system; mechanisms enforcing rules or methods for governing the installation of software by users; mechanisms monitoring policy compliance]."
        }
      ]
    },
    "last_ao_sentence": "installation of software by users is monitored."
  },
  {
    "text": "This is a NIST 800-171 control in the Identification and Authentication family. It corresponds to Level 1, Level 2. The control ID is IA.L1-3.5.1 with title 'IDENTIFICATION'. Security requirement: Identify system users, processes acting on behalf of users, and devices.. Assessment objective (3.5.1[a]): system users are identified.. POA&M allowed: No. SPRS score: 5.\nThis is a NIST 800-171 control in the Identification and Authentication family. It corresponds to Level 1, Level 2. The control ID is IA.L1-3.5.1 with title 'IDENTIFICATION'. Security requirement: Identify system users, processes acting on behalf of users, and devices.. Assessment objective (3.5.1[b]): processes acting on behalf of users are identified.. POA&M allowed: No. SPRS score: 5.\nThis is a NIST 800-171 control in the Identification and Authentication family. It corresponds to Level 1, Level 2. The control ID is IA.L1-3.5.1 with title 'IDENTIFICATION'. Security requirement: Identify system users, processes acting on behalf of users, and devices.. Assessment objective (3.5.1[c]): devices accessing the system are identified.. POA&M allowed: No. SPRS score: 5.",
    "metadata": {
      "framework": "NIST 800-171",
      "family": "Identification and Authentication",
      "control_id": "3.5.1",
      "cmmc_id": "IA.L1-3.5.1",
      "title": "IDENTIFICATION",
      "sprs": 5,
      "cmmc_levels": [
        "Level 1",
        "Level 2"
      ],
      "poam_allowed": "No",
      "ao_ids": [
        "3.5.1[a]",
        "3.5.1[b]",
        "3.5.1[c]"
      ],
      "assessment_methods": [
        {
          "type": "Examine",
          "description": "[SELECT FROM: Identification and authentication policy; procedures addressing user identification and authentication; security plan, system design documentation; system configuration settings and associated documentation; system audit logs and records; list of system accounts; other relevant documents or records]."
        },
        {
          "type": "Interview",
          "description": "[SELECT FROM: Personnel with system operations responsibilities; personnel with information security responsibilities; system or network administrators; personnel with account management responsibilities; system developers]."
        },
        {
          "type": "Test",
          "description": "[SELECT FROM: Organizational processes for uniquely identifying and authenticating users; mechanisms supporting or implementing identification and authentication capability]."
        }
      ]
    },
    "last_ao_sentence": "devices accessing the system are identified."
  },
  {
    "text": "This is a NIST 800-171 control in the Identification and Authentication family. It corresponds to Level 1, Level 2. The control ID is IA.L1-3.5.2 with title 'AUTHENTICATION'. Security requirement: Authenticate (or verify) the identities of users, processes, or devices, as a prerequisite to allowing access to organizational systems. Assessment objective (3.5.2[a]): the identity of each user is authenticated or verified as a prerequisite to system access.. POA&M allowed: No. SPRS score: 5.\nThis is a NIST 800-171 control in the Identification and Authentication family. It corresponds to Level 1, Level 2. The control ID is IA.L1-3.5.2 with title 'AUTHENTICATION'. Security requirement: Authenticate (or verify) the identities of users, processes, or devices, as a prerequisite to allowing access to organizational systems. Assessment objective (3.5.2[b]): the identity of each process acting on behalf of a user is authenticated or verified as a prerequisite to system access.. POA&M allowed: No. SPRS score: 5.\nThis is a NIST 800-171 control in the Identification and Authentication family. It corresponds to Level 1, Level 2. The control ID is IA.L1-3.5.2 with title 'AUTHENTICATION'. Security requirement: Authenticate (or verify) the identities of users, processes, or devices, as a prerequisite to allowing access to organizational systems. Assessment objective (3.5.2[c]): the identity of each device accessing or connecting to the system is authenticated or verified as a prerequisite to system access.. POA&M allowed: No. SPRS score: 5.",
    "metadata": {
      "framework": "NIST 800-171",
      "family": "Identification and Authentication",
      "control_id": "3.5.2",
      "cmmc_id": "IA.L1-3.5.2",
      "title": "AUTHENTICATION",
      "sprs": 5,
      "cmmc_levels": [
        "Level 1",
        "Level 2"
      ],
      "poam_allowed": "No",
      "ao_ids": [
        "3.5.2[a]",
        "3.5.2[b]",
        "3.5.2[c]"
      ],
      "assessment_methods": [
        {
          "type": "Examine",
          "description": "[SELECT FROM: Identification and authentication policy; procedures addressing authenticator management; security plan; system design documentation; system configuration settings and associated documentation; list of system authenticator types; change control records associated with managing system authenticators; system audit logs and records; other relevant documents or records]."
        },
        {
          "type": "Interview",
          "description": "[SELECT FROM: Personnel with authenticator management responsibilities; personnel with information security responsibilities; system or network administrators]."
        },
        {
          "type": "Test",
          "description": "[SELECT FROM: Mechanisms supporting or implementing authenticator management capability]."
        }
      ]
    },
    "last_ao_sentence": "the identity of each device accessing or connecting to the system is authenticated or verified as a prerequisite to system access."
  },
  {
    "text": "This is a NIST 800-171 control in the Identification and Authentication family. It corresponds to Level 2. The control ID is IA.L2-3.5.3 with title 'MULTIFACTOR AUTHENTICATION'. Security requirement: Use multifactor authentication for local and network access to privileged accounts and for network access to non-privileged accounts.. Assessment objective (3.5.3[a]): privileged accounts are identified.. POA&M allowed: No. SPRS score: 5.\nThis is a NIST 800-171 control in the Identification and Authentication family. It corresponds to Level 2. The control ID is IA.L2-3.5.3 with title 'MULTIFACTOR AUTHENTICATION'. Security requirement: Use multifactor authentication for local and network access to privileged accounts and for network access to non-privileged accounts.. Assessment objective (3.5.3[b]): multifactor authentication is implemented for local access to privileged accounts.. POA&M allowed: No. SPRS score: 5.\nThis is a NIST 800-171 control in the Identification and Authentication family. It corresponds to Level 2. The control ID is IA.L2-3.5.3 with title 'MULTIFACTOR AUTHENTICATION'. Security requirement: Use multifactor authentication for local and network access to privileged accounts and for network access to non-privileged accounts.. Assessment objective (3.5.3[c]): multifactor authentication is implemented for network access to privileged accounts.. POA&M allowed: No. SPRS score: 5.\nThis is a NIST 800-171 control in the Identification and Authentication family. It corresponds to Level 2. The control ID is IA.L2-3.5.3 with title 'MULTIFACTOR AUTHENTICATION'. Security requirement: Use multifactor authentication for local and network access to privileged accounts and for network access to non-privileged accounts.. Assessment objective (3.5.3[d]): multifactor authentication is implemented for network access to non-privileged accounts.. POA&M allowed: No. SPRS score: 5.",
    "metadata": {
      "framework": "NIST 800-171",
      "family": "Identification and Authentication",
      "control_id": "3.5.3",
      "cmmc_id": "IA.L2-3.5.3",
      "title": "MULTIFACTOR AUTHENTICATION",
      "sprs": 5,
      "cmmc_levels": [
        "Level 2"
      ],
      "poam_allowed": "No",
      "ao_ids": [
        "3.5.3[a]",
        "3.5.3[b]",
        "3.5.3[c]",
        "3.5.3[d]"
      ],
      "assessment_methods": [
        {
          "type": "Examine",
          "description": "[SELECT FROM: Identification and authentication policy; procedures addressing user identification and authentication; security plan; system design documentation; system configuration settings and associated documentation; system audit logs and records; list of system accounts; other relevant documents or records]."
        },
        {
          "type": "Interview",
          "description": "[SELECT FROM: Personnel with system operations responsibilities; personnel with account management responsibilities; personnel with information security responsibilities; system or network administrators; system developers]."
        },
        {
          "type": "Test",
          "description": "[SELECT FROM: Mechanisms supporting or implementing multifactor authentication capability]."
        }
      ]
    },
    "last_ao_sentence": "multifactor authentication is implemented for network access to non-privileged accounts."
  },
  {
    "text": "This is a NIST 800-171 control in the Identification and Authentication family. It corresponds to Level 2. The control ID is IA.L2-3.5.4 with title 'REPLAY-RESISTANT AUTHENTICATION'. Security requirement: Employ replay-resistant authentication mechanisms for network access to privileged and non-privileged accounts.. Assessment objective (3.5.4): Determine if replay-resistant authentication mechanisms are implemented for all network account access to privileged and non-privileged accounts.. POA&M allowed: Yes. SPRS score: 1.",
    "metadata": {
      "framework": "NIST 800-171",
      "family": "Identification and Authentication",
      "control_id": "3.5.4",
      "cmmc_id": "IA.L2-3.5.4",
      "title": "REPLAY-RESISTANT AUTHENTICATION",
      "sprs": 1,
      "cmmc_levels": [
        "Level 2"
      ],
      "poam_allowed": "Yes",
      "ao_ids": [
        "3.5.4"
      ],
      "assessment_methods": [
        {
          "type": "Examine",
          "description": "[SELECT FROM: Identification and authentication policy; procedures addressing user identification and authentication; security plan; system design documentation; system configuration settings and associated documentation; system audit logs and records; list of privileged system accounts; other relevant documents or records]."
        },
        {
          "type": "Interview",
          "description": "[SELECT FROM: Personnel with system operations responsibilities; personnel with account management responsibilities; personnel with information security responsibilities; system or network administrators; system developers]."
        },
        {
          "type": "Test",
          "description": "[SELECT FROM: Mechanisms supporting or implementing identification and authentication capability or replay resistant authentication mechanisms]."
        }
      ]
    },
    "last_ao_sentence": "Determine if replay-resistant authentication mechanisms are implemented for all network account access to privileged and non-privileged accounts."
  },
  {
    "text": "This is a NIST 800-171 control in the Identification and Authentication family. It corresponds to Level 2. The control ID is IA.L2-3.5.5 with title 'IDENTIFIER REUSE'. Security requirement: Prevent reuse of identifiers for a defined period.. Assessment objective (3.5.5[a]): a period within which identifiers cannot be reused is defined.. POA&M allowed: Yes. SPRS score: 1.\nThis is a NIST 800-171 control in the Identification and Authentication family. It corresponds to Level 2. The control ID is IA.L2-3.5.5 with title 'IDENTIFIER REUSE'. Security requirement: Prevent reuse of identifiers for a defined period.. Assessment objective (3.5.5[b]): reuse of identifiers is prevented within the defined period.. POA&M allowed: Yes. SPRS score: 1.",
    "metadata": {
      "framework": "NIST 800-171",
      "family": "Identification and Authentication",
      "control_id": "3.5.5",
      "cmmc_id": "IA.L2-3.5.5",
      "title": "IDENTIFIER REUSE",
      "sprs": 1,
      "cmmc_levels": [
        "Level 2"
      ],
      "poam_allowed": "Yes",
      "ao_ids": [
        "3.5.5[a]",
        "3.5.5[b]"
      ],
      "assessment_methods": [
        {
          "type": "Examine",
          "description": "[SELECT FROM: Identification and authentication policy; procedures addressing identifier management; procedures addressing account management; security plan; system design documentation; system configuration settings and associated documentation; list of system accounts; list of identifiers generated from physical access control devices; other relevant documents or records]."
        },
        {
          "type": "Interview",
          "description": "[SELECT FROM: Personnel with identifier management responsibilities; personnel with information security responsibilities; system or network administrators; system developers]."
        },
        {
          "type": "Test",
          "description": "[SELECT FROM: Mechanisms supporting or implementing identifier management]."
        }
      ]
    },
    "last_ao_sentence": "reuse of identifiers is prevented within the defined period."
  },
  {
    "text": "This is a NIST 800-171 control in the Identification and Authentication family. It corresponds to Level 2. The control ID is IA.L2-3.5.6 with title 'IDENTIFIER HANDLING'. Security requirement: Disable identifiers after a defined period of inactivity.. Assessment objective (3.5.6[a]): a period of inactivity after which an identifier is disabled is defined.. POA&M allowed: Yes. SPRS score: 1.\nThis is a NIST 800-171 control in the Identification and Authentication family. It corresponds to Level 2. The control ID is IA.L2-3.5.6 with title 'IDENTIFIER HANDLING'. Security requirement: Disable identifiers after a defined period of inactivity.. Assessment objective (3.5.6[b]): identifiers are disabled after the defined period of inactivity.. POA&M allowed: Yes. SPRS score: 1.",
    "metadata": {
      "framework": "NIST 800-171",
      "family": "Identification and Authentication",
      "control_id": "3.5.6",
      "cmmc_id": "IA.L2-3.5.6",
      "title": "IDENTIFIER HANDLING",
      "sprs": 1,
      "cmmc_levels": [
        "Level 2"
      ],
      "poam_allowed": "Yes",
      "ao_ids": [
        "3.5.6[a]",
        "3.5.6[b]"
      ],
      "assessment_methods": [
        {
          "type": "Examine",
          "description": "[SELECT FROM: Identification and authentication policy; procedures addressing identifier management; procedures addressing account management; security plan; system design documentation; system configuration settings and associated documentation; list of system accounts; list of identifiers generated from physical access control devices; other relevant documents or records]."
        },
        {
          "type": "Interview",
          "description": "[SELECT FROM: Personnel with identifier management responsibilities; personnel with information security responsibilities; system or network administrators; system developers]."
        },
        {
          "type": "Test",
          "description": "[SELECT FROM: Mechanisms supporting or implementing identifier management]."
        }
      ]
    },
    "last_ao_sentence": "identifiers are disabled after the defined period of inactivity."
  },
  {
    "text": "This is a NIST 800-171 control in the Identification and Authentication family. It corresponds to Level 2. The control ID is IA.L2-3.5.7 with title 'PASSWORD COMPLEXITY'. Security requirement: Enforce a minimum password complexity and change of characters when new passwords are created.. Assessment objective (3.5.7[a]): password complexity requirements are defined.. POA&M allowed: Yes. SPRS score: 1.\nThis is a NIST 800-171 control in the Identification and Authentication family. It corresponds to Level 2. The control ID is IA.L2-3.5.7 with title 'PASSWORD COMPLEXITY'. Security requirement: Enforce a minimum password complexity and change of characters when new passwords are created.. Assessment objective (3.5.7[b]): password change of character requirements are defined.. POA&M allowed: Yes. SPRS score: 1.\nThis is a NIST 800-171 control in the Identification and Authentication family. It corresponds to Level 2. The control ID is IA.L2-3.5.7 with title 'PASSWORD COMPLEXITY'. Security requirement: Enforce a minimum password complexity and change of characters when new passwords are created.. Assessment objective (3.5.7[c]): minimum password complexity requirements as defined are enforced when new passwords are created.. POA&M allowed: Yes. SPRS score: 1.\nThis is a NIST 800-171 control in the Identification and Authentication family. It corresponds to Level 2. The control ID is IA.L2-3.5.7 with title 'PASSWORD COMPLEXITY'. Security requirement: Enforce a minimum password complexity and change of characters when new passwords are created.. Assessment objective (3.5.7[d]): minimum password change of character requirements as defined are enforced when new passwords are created.. POA&M allowed: Yes. SPRS score: 1.",
    "metadata": {
      "framework": "NIST 800-171",
      "family": "Identification and Authentication",
      "control_id": "3.5.7",
      "cmmc_id": "IA.L2-3.5.7",
      "title": "PASSWORD COMPLEXITY",
      "sprs": 1,
      "cmmc_levels": [
        "Level 2"
      ],
      "poam_allowed": "Yes",
      "ao_ids": [
        "3.5.7[a]",
        "3.5.7[b]",
        "3.5.7[c]",
        "3.5.7[d]"
      ],
      "assessment_methods": [
        {
          "type": "Examine",
          "description": "[SELECT FROM: Identification and authentication policy; password policy; procedures addressing authenticator management; security plan; system design documentation; system configuration settings and associated documentation; password configurations and associated documentation; other relevant documents or records]."
        },
        {
          "type": "Interview",
          "description": "[SELECT FROM: Personnel with authenticator management responsibilities; personnel with information security responsibilities; system or network administrators; system developers]."
        },
        {
          "type": "Test",
          "description": "[SELECT FROM: Mechanisms supporting or implementing password-based authenticator management capability]."
        }
      ]
    },
    "last_ao_sentence": "minimum password change of character requirements as defined are enforced when new passwords are created."
  },
  {
    "text": "This is a NIST 800-171 control in the Identification and Authentication family. It corresponds to Level 2. The control ID is IA.L2-3.5.8 with title 'PASSWORD REUSE'. Security requirement: Prohibit password reuse for a specified number of generations.. Assessment objective (3.5.8[a]): the number of generations during which a password cannot be reused is specified.. POA&M allowed: Yes. SPRS score: 1.\nThis is a NIST 800-171 control in the Identification and Authentication family. It corresponds to Level 2. The control ID is IA.L2-3.5.8 with title 'PASSWORD REUSE'. Security requirement: Prohibit password reuse for a specified number of generations.. Assessment objective (3.5.8[b]): reuse of passwords is prohibited during the specified number of generations.. POA&M allowed: Yes. SPRS score: 1.",
    "metadata": {
      "framework": "NIST 800-171",
      "family": "Identification and Authentication",
      "control_id": "3.5.8",
      "cmmc_id": "IA.L2-3.5.8",
      "title": "PASSWORD REUSE",
      "sprs": 1,
      "cmmc_levels": [
        "Level 2"
      ],
      "poam_allowed": "Yes",
      "ao_ids": [
        "3.5.8[a]",
        "3.5.8[b]"
      ],
      "assessment_methods": [
        {
          "type": "Examine",
          "description": "[SELECT FROM: Identification and authentication policy; password policy; procedures addressing authenticator management; security plan; system design documentation; system configuration settings and associated documentation; password configurations and associated documentation; other relevant documents or records]."
        },
        {
          "type": "Interview",
          "description": "[SELECT FROM: Personnel with authenticator management responsibilities; personnel with information security responsibilities; system or network administrators; system developers]."
        },
        {
          "type": "Test",
          "description": "[SELECT FROM: Mechanisms supporting or implementing password-based authenticator management capability]."
        }
      ]
    },
    "last_ao_sentence": "reuse of passwords is prohibited during the specified number of generations."
  },
  {
    "text": "This is a NIST 800-171 control in the Identification and Authentication family. It corresponds to Level 2. The control ID is IA.L2-3.5.9 with title 'TEMPORARY PASSWORDS'. Security requirement: Allow temporary password use for system logons with an immediate change to a permanent password. Assessment objective (3.5.9): Determine if an immediate change to a permanent password is required when a temporary password is used for system logon.. POA&M allowed: Yes. SPRS score: 1.",
    "metadata": {
      "framework": "NIST 800-171",
      "family": "Identification and Authentication",
      "control_id": "3.5.9",
      "cmmc_id": "IA.L2-3.5.9",
      "title": "TEMPORARY PASSWORDS",
      "sprs": 1,
      "cmmc_levels": [
        "Level 2"
      ],
      "poam_allowed": "Yes",
      "ao_ids": [
        "3.5.9"
      ],
      "assessment_methods": [
        {
          "type": "Examine",
          "description": "[SELECT FROM: Identification and authentication policy; password policy; procedures addressing authenticator management; security plan; system design documentation; system configuration settings and associated documentation; password configurations and associated documentation; other relevant documents or records]."
        },
        {
          "type": "Interview",
          "description": "[SELECT FROM: Personnel with authenticator management responsibilities; personnel with information security responsibilities; system or network administrators; system developers]."
        },
        {
          "type": "Test",
          "description": "[SELECT FROM: Mechanisms supporting or implementing password-based authenticator management capability]."
        }
      ]
    },
    "last_ao_sentence": "Determine if an immediate change to a permanent password is required when a temporary password is used for system logon."
  },
  {
    "text": "This is a NIST 800-171 control in the Identification and Authentication family. It corresponds to Level 2. The control ID is IA.L2-3.5.10 with title 'CRYPTOGRAPHICALLY-PROTECTED PASSWORDS'. Security requirement: Store and transmit only cryptographically-protected passwords.. Assessment objective (3.5.10[a]): passwords are cryptographically protected in storage.. POA&M allowed: No. SPRS score: 5.\nThis is a NIST 800-171 control in the Identification and Authentication family. It corresponds to Level 2. The control ID is IA.L2-3.5.10 with title 'CRYPTOGRAPHICALLY-PROTECTED PASSWORDS'. Security requirement: Store and transmit only cryptographically-protected passwords.. Assessment objective (3.5.10[b]): passwords are cryptographically protected in transit.. POA&M allowed: No. SPRS score: 5.",
    "metadata": {
      "framework": "NIST 800-171",
      "family": "Identification and Authentication",
      "control_id": "3.5.10",
      "cmmc_id": "IA.L2-3.5.10",
      "title": "CRYPTOGRAPHICALLY-PROTECTED PASSWORDS",
      "sprs": 5,
      "cmmc_levels": [
        "Level 2"
      ],
      "poam_allowed": "No",
      "ao_ids": [
        "3.5.10[a]",
        "3.5.10[b]"
      ],
      "assessment_methods": [
        {
          "type": "Examine",
          "description": "[SELECT FROM: Identification and authentication policy; password policy; procedures addressing authenticator management; security plan; system design documentation; system configuration settings and associated documentation; password configurations and associated documentation; other relevant documents or records]."
        },
        {
          "type": "Interview",
          "description": "[SELECT FROM: Personnel with authenticator management responsibilities; personnel with information security responsibilities; system or network administrators; system developers]."
        },
        {
          "type": "Test",
          "description": "[SELECT FROM: Mechanisms supporting or implementing password-based authenticator management capability]."
        }
      ]
    },
    "last_ao_sentence": "passwords are cryptographically protected in transit."
  },
  {
    "text": "This is a NIST 800-171 control in the Identification and Authentication family. It corresponds to Level 2. The control ID is IA.L2-3.5.11 with title 'OBSCURE FEEDBACK'. Security requirement: Obscure feedback of authentication information.. Assessment objective (3.5.11): Determine if authentication information is obscured during the authentication process.. POA&M allowed: Yes. SPRS score: 1.",
    "metadata": {
      "framework": "NIST 800-171",
      "family": "Identification and Authentication",
      "control_id": "3.5.11",
      "cmmc_id": "IA.L2-3.5.11",
      "title": "OBSCURE FEEDBACK",
      "sprs": 1,
      "cmmc_levels": [
        "Level 2"
      ],
      "poam_allowed": "Yes",
      "ao_ids": [
        "3.5.11"
      ],
      "assessment_methods": [
        {
          "type": "Examine",
          "description": "[SELECT FROM: Identification and authentication policy; procedures addressing authenticator feedback; security plan; system design documentation; system configuration settings and associated documentation; system audit logs and records; other relevant documents or records]."
        },
        {
          "type": "Interview",
          "description": "[SELECT FROM: Personnel with information security responsibilities; system or network administrators; system developers]."
        },
        {
          "type": "Test",
          "description": "[SELECT FROM:  Mechanisms supporting or implementing the obscuring of feedback of authentication information during authentication]."
        }
      ]
    },
    "last_ao_sentence": "Determine if authentication information is obscured during the authentication process."
  },
  {
    "text": "This is a NIST 800-171 control in the Incident Response family. It corresponds to Level 2. The control ID is IR.L2-3.6.1 with title 'INCIDENT HANDLING'. Security requirement: Establish an operational incident-handling capability for organizational systems that includes preparation, detection, analysis, containment, recovery, and user response activities.. Assessment objective (3.6.1[a]): an operational incident-handling capability is established.. POA&M allowed: No. SPRS score: 5.\nThis is a NIST 800-171 control in the Incident Response family. It corresponds to Level 2. The control ID is IR.L2-3.6.1 with title 'INCIDENT HANDLING'. Security requirement: Establish an operational incident-handling capability for organizational systems that includes preparation, detection, analysis, containment, recovery, and user response activities.. Assessment objective (3.6.1[b]): the operational incident-handling capability includes preparation.. POA&M allowed: No. SPRS score: 5.\nThis is a NIST 800-171 control in the Incident Response family. It corresponds to Level 2. The control ID is IR.L2-3.6.1 with title 'INCIDENT HANDLING'. Security requirement: Establish an operational incident-handling capability for organizational systems that includes preparation, detection, analysis, containment, recovery, and user response activities.. Assessment objective (3.6.1[c]): the operational incident-handling capability includes detection.. POA&M allowed: No. SPRS score: 5.\nThis is a NIST 800-171 control in the Incident Response family. It corresponds to Level 2. The control ID is IR.L2-3.6.1 with title 'INCIDENT HANDLING'. Security requirement: Establish an operational incident-handling capability for organizational systems that includes preparation, detection, analysis, containment, recovery, and user response activities.. Assessment objective (3.6.1[d]): the operational incident-handling capability includes analysis.. POA&M allowed: No. SPRS score: 5.\nThis is a NIST 800-171 control in the Incident Response family. It corresponds to Level 2. The control ID is IR.L2-3.6.1 with title 'INCIDENT HANDLING'. Security requirement: Establish an operational incident-handling capability for organizational systems that includes preparation, detection, analysis, containment, recovery, and user response activities.. Assessment objective (3.6.1[e]): the operational incident-handling capability includes containment.. POA&M allowed: No. SPRS score: 5.\nThis is a NIST 800-171 control in the Incident Response family. It corresponds to Level 2. The control ID is IR.L2-3.6.1 with title 'INCIDENT HANDLING'. Security requirement: Establish an operational incident-handling capability for organizational systems that includes preparation, detection, analysis, containment, recovery, and user response activities.. Assessment objective (3.6.1[f]): the operational incident-handling capability includes recovery.. POA&M allowed: No. SPRS score: 5.\nThis is a NIST 800-171 control in the Incident Response family. It corresponds to Level 2. The control ID is IR.L2-3.6.1 with title 'INCIDENT HANDLING'. Security requirement: Establish an operational incident-handling capability for organizational systems that includes preparation, detection, analysis, containment, recovery, and user response activities.. Assessment objective (3.6.1[g]): the operational incident-handling capability includes user response activities.. POA&M allowed: No. SPRS score: 5.",
    "metadata": {
      "framework": "NIST 800-171",
      "family": "Incident Response",
      "control_id": "3.6.1",
      "cmmc_id": "IR.L2-3.6.1",
      "title": "INCIDENT HANDLING",
      "sprs": 5,
      "cmmc_levels": [
        "Level 2"
      ],
      "poam_allowed": "No",
      "ao_ids": [
        "3.6.1[a]",
        "3.6.1[b]",
        "3.6.1[c]",
        "3.6.1[d]",
        "3.6.1[e]",
        "3.6.1[f]",
        "3.6.1[g]"
      ],
      "assessment_methods": [
        {
          "type": "Examine",
          "description": "[SELECT FROM: Incident response policy; contingency planning policy; procedures addressing incident handling; procedures addressing incident response assistance; incident response plan; contingency plan; security plan; procedures addressing incident response training; incident response training curriculum; incident response training materials; incident response training records; other relevant documents or records]."
        },
        {
          "type": "Interview",
          "description": "[SELECT FROM: Personnel with incident handling responsibilities; personnel with contingency planning responsibilities; personnel with incident response training and operational responsibilities; personnel with incident response assistance and support responsibilities; personnel with access to incident response support and assistance capability; personnel with information security responsibilities]."
        },
        {
          "type": "Test",
          "description": "[SELECT FROM: Incident-handling capability for the organization; organizational processes for incident response assistance; mechanisms supporting or implementing incident response assistance]."
        }
      ]
    },
    "last_ao_sentence": "the operational incident-handling capability includes user response activities."
  },
  {
    "text": "This is a NIST 800-171 control in the Incident Response family. It corresponds to Level 2. The control ID is IR.L2-3.6.2 with title 'INCIDENT REPORTING'. Security requirement: Track, document, and report incidents to designated officials and/or authorities both internal and external to the organization.. Assessment objective (3.6.2[a]): incidents are tracked.. POA&M allowed: No. SPRS score: 5.\nThis is a NIST 800-171 control in the Incident Response family. It corresponds to Level 2. The control ID is IR.L2-3.6.2 with title 'INCIDENT REPORTING'. Security requirement: Track, document, and report incidents to designated officials and/or authorities both internal and external to the organization.. Assessment objective (3.6.2[b]): incidents are documented.. POA&M allowed: No. SPRS score: 5.\nThis is a NIST 800-171 control in the Incident Response family. It corresponds to Level 2. The control ID is IR.L2-3.6.2 with title 'INCIDENT REPORTING'. Security requirement: Track, document, and report incidents to designated officials and/or authorities both internal and external to the organization.. Assessment objective (3.6.2[c]): authorities to whom incidents are to be reported are identified.. POA&M allowed: No. SPRS score: 5.\nThis is a NIST 800-171 control in the Incident Response family. It corresponds to Level 2. The control ID is IR.L2-3.6.2 with title 'INCIDENT REPORTING'. Security requirement: Track, document, and report incidents to designated officials and/or authorities both internal and external to the organization.. Assessment objective (3.6.2[d]): organizational officials to whom incidents are to be reported are identified.. POA&M allowed: No. SPRS score: 5.\nThis is a NIST 800-171 control in the Incident Response family. It corresponds to Level 2. The control ID is IR.L2-3.6.2 with title 'INCIDENT REPORTING'. Security requirement: Track, document, and report incidents to designated officials and/or authorities both internal and external to the organization.. Assessment objective (3.6.2[e]): identified authorities are notified of incidents.. POA&M allowed: No. SPRS score: 5.\nThis is a NIST 800-171 control in the Incident Response family. It corresponds to Level 2. The control ID is IR.L2-3.6.2 with title 'INCIDENT REPORTING'. Security requirement: Track, document, and report incidents to designated officials and/or authorities both internal and external to the organization.. Assessment objective (3.6.2[f]): identified organizational officials are notified of incidents.. POA&M allowed: No. SPRS score: 5.",
    "metadata": {
      "framework": "NIST 800-171",
      "family": "Incident Response",
      "control_id": "3.6.2",
      "cmmc_id": "IR.L2-3.6.2",
      "title": "INCIDENT REPORTING",
      "sprs": 5,
      "cmmc_levels": [
        "Level 2"
      ],
      "poam_allowed": "No",
      "ao_ids": [
        "3.6.2[a]",
        "3.6.2[b]",
        "3.6.2[c]",
        "3.6.2[d]",
        "3.6.2[e]",
        "3.6.2[f]"
      ],
      "assessment_methods": [
        {
          "type": "Examine",
          "description": "[SELECT FROM: Incident response policy; procedures addressing incident monitoring; incident response records and documentation; procedures addressing incident reporting; incident reporting records and documentation; incident response plan; security plan; other relevant documents or records]."
        },
        {
          "type": "Interview",
          "description": "[SELECT FROM: Personnel with incident monitoring responsibilities; personnel with incident reporting responsibilities; personnel who have or should have reported incidents; personnel (authorities) to whom incident information is to be reported; personnel with information security responsibilities]."
        },
        {
          "type": "Test",
          "description": "[SELECT FROM: Incident monitoring capability for the organization; mechanisms supporting or implementing tracking and documenting of system security incidents; organizational processes for incident reporting; mechanisms supporting or implementing incident reporting]."
        }
      ]
    },
    "last_ao_sentence": "identified organizational officials are notified of incidents."
  },
  {
    "text": "This is a NIST 800-171 control in the Incident Response family. It corresponds to Level 2. The control ID is IR.L2-3.6.3 with title 'INCIDENT RESPONSE TESTING'. Security requirement: Test the organizational incident response capability.. Assessment objective (3.6.3): Determine if the incident response capability is tested.. POA&M allowed: Yes. SPRS score: 1.",
    "metadata": {
      "framework": "NIST 800-171",
      "family": "Incident Response",
      "control_id": "3.6.3",
      "cmmc_id": "IR.L2-3.6.3",
      "title": "INCIDENT RESPONSE TESTING",
      "sprs": 1,
      "cmmc_levels": [
        "Level 2"
      ],
      "poam_allowed": "Yes",
      "ao_ids": [
        "3.6.3"
      ],
      "assessment_methods": [
        {
          "type": "Examine",
          "description": "[SELECT FROM: Incident response policy; contingency planning policy; procedures addressing incident response testing; procedures addressing contingency plan testing; incident response testing material; incident response test results; incident response test plan; incident response plan; contingency plan; security plan; other relevant documents or records]."
        },
        {
          "type": "Interview",
          "description": "[SELECT FROM: Personnel with incident response testing responsibilities; personnel with information security responsibilities]."
        },
        {
          "type": "Test",
          "description": "[SELECT FROM: Incident monitoring capability for the organization; mechanisms supporting or implementing tracking and documenting of system security incidents; organizational processes for incident reporting; mechanisms supporting or implementing incident reporting]."
        }
      ]
    },
    "last_ao_sentence": "Determine if the incident response capability is tested."
  },
  {
    "text": "This is a NIST 800-171 control in the Maintenance family. It corresponds to Level 2. The control ID is MA.L2-3.7.1 with title 'PERFORM MAINTENANCE'. Security requirement: Perform maintenance on organizational systems.. Assessment objective (3.7.1): Determine if system maintenance is performed.. POA&M allowed: No. SPRS score: 3.",
    "metadata": {
      "framework": "NIST 800-171",
      "family": "Maintenance",
      "control_id": "3.7.1",
      "cmmc_id": "MA.L2-3.7.1",
      "title": "PERFORM MAINTENANCE",
      "sprs": 3,
      "cmmc_levels": [
        "Level 2"
      ],
      "poam_allowed": "No",
      "ao_ids": [
        "3.7.1"
      ],
      "assessment_methods": [
        {
          "type": "Examine",
          "description": "[SELECT FROM: System maintenance policy; procedures addressing controlled system maintenance; maintenance records; manufacturer or vendor maintenance specifications; equipment sanitization records; media sanitization records; security plan; other relevant documents or records]."
        },
        {
          "type": "Interview",
          "description": "[select from: Personnel with system maintenance responsibilities; personnel with information security responsibilities; personnel responsible for media sanitization; system or network administrators]."
        },
        {
          "type": "Test",
          "description": "[SELECT FROM: Organizational processes for scheduling, performing, documenting, reviewing, approving, and monitoring maintenance and repairs for systems; organizational processes for sanitizing system components; mechanisms supporting or implementing controlled maintenance; mechanisms implementing sanitization of system components]."
        }
      ]
    },
    "last_ao_sentence": "Determine if system maintenance is performed."
  },
  {
    "text": "This is a NIST 800-171 control in the Maintenance family. It corresponds to Level 2. The control ID is MA.L2-3.7.2 with title 'SYSTEM MAINTENANCE CONTROL'. Security requirement: Provide controls on the tools, techniques, mechanisms, and personnel used to conduct system maintenance.. Assessment objective (3.7.2[a]): tools used to conduct system maintenance are controlled.. POA&M allowed: No. SPRS score: 5.\nThis is a NIST 800-171 control in the Maintenance family. It corresponds to Level 2. The control ID is MA.L2-3.7.2 with title 'SYSTEM MAINTENANCE CONTROL'. Security requirement: Provide controls on the tools, techniques, mechanisms, and personnel used to conduct system maintenance.. Assessment objective (3.7.2[b]): techniques used to conduct system maintenance are controlled.. POA&M allowed: No. SPRS score: 5.\nThis is a NIST 800-171 control in the Maintenance family. It corresponds to Level 2. The control ID is MA.L2-3.7.2 with title 'SYSTEM MAINTENANCE CONTROL'. Security requirement: Provide controls on the tools, techniques, mechanisms, and personnel used to conduct system maintenance.. Assessment objective (3.7.2[c]): mechanisms used to conduct system maintenance are controlled.. POA&M allowed: No. SPRS score: 5.\nThis is a NIST 800-171 control in the Maintenance family. It corresponds to Level 2. The control ID is MA.L2-3.7.2 with title 'SYSTEM MAINTENANCE CONTROL'. Security requirement: Provide controls on the tools, techniques, mechanisms, and personnel used to conduct system maintenance.. Assessment objective (3.7.2[d]): personnel used to conduct system maintenance are controlled.. POA&M allowed: No. SPRS score: 5.",
    "metadata": {
      "framework": "NIST 800-171",
      "family": "Maintenance",
      "control_id": "3.7.2",
      "cmmc_id": "MA.L2-3.7.2",
      "title": "SYSTEM MAINTENANCE CONTROL",
      "sprs": 5,
      "cmmc_levels": [
        "Level 2"
      ],
      "poam_allowed": "No",
      "ao_ids": [
        "3.7.2[a]",
        "3.7.2[b]",
        "3.7.2[c]",
        "3.7.2[d]"
      ],
      "assessment_methods": [
        {
          "type": "Examine",
          "description": "[SELECT FROM: System maintenance policy; procedures addressing system maintenance tools and media; maintenance records; system maintenance tools and associated documentation; maintenance tool inspection records; security plan; other relevant documents or records]."
        },
        {
          "type": "Interview",
          "description": "[SELECT FROM: Personnel with system maintenance responsibilities; personnel with information security responsibilities]."
        },
        {
          "type": "Test",
          "description": "[SELECT FROM: Organizational processes for approving, controlling, and monitoring maintenance tools; mechanisms supporting or implementing approval, control, and monitoring of maintenance tools; organizational processes for inspecting maintenance tools; mechanisms supporting or implementing inspection of maintenance tools; organizational process for inspecting media for malicious code; mechanisms supporting or implementing inspection of media used for maintenance]."
        }
      ]
    },
    "last_ao_sentence": "personnel used to conduct system maintenance are controlled."
  },
  {
    "text": "This is a NIST 800-171 control in the Maintenance family. It corresponds to Level 2. The control ID is MA.L2-3.7.3 with title 'EQUIPMENT SANITIZATION'. Security requirement: Ensure equipment removed for off-site maintenance is sanitized of any CUI.. Assessment objective (3.7.3): Determine if equipment to be removed from organizational spaces for off-site maintenance is sanitized of any CUI.. POA&M allowed: Yes. SPRS score: 1.",
    "metadata": {
      "framework": "NIST 800-171",
      "family": "Maintenance",
      "control_id": "3.7.3",
      "cmmc_id": "MA.L2-3.7.3",
      "title": "EQUIPMENT SANITIZATION",
      "sprs": 1,
      "cmmc_levels": [
        "Level 2"
      ],
      "poam_allowed": "Yes",
      "ao_ids": [
        "3.7.3"
      ],
      "assessment_methods": [
        {
          "type": "Examine",
          "description": "[SELECT FROM: System maintenance policy; procedures addressing controlled system maintenance; maintenance records; manufacturer or vendor maintenance specifications; equipment sanitization records; media sanitization records; security plan; other relevant documents or records]."
        },
        {
          "type": "Interview",
          "description": "[select from: Personnel with system maintenance responsibilities; personnel with information security responsibilities; personnel responsible for media sanitization; system or network administrators]."
        },
        {
          "type": "Test",
          "description": "[SELECT FROM: Organizational processes for scheduling, performing, documenting, reviewing, approving, and monitoring maintenance and repairs for systems; organizational processes for sanitizing system components; mechanisms supporting or implementing controlled maintenance; mechanisms implementing sanitization of system components]."
        }
      ]
    },
    "last_ao_sentence": "Determine if equipment to be removed from organizational spaces for off-site maintenance is sanitized of any CUI."
  },
  {
    "text": "This is a NIST 800-171 control in the Maintenance family. It corresponds to Level 2. The control ID is MA.L2-3.7.4 with title 'MEDIA INSPECTION'. Security requirement: Check media containing diagnostic and test programs for malicious code before the media are used in organizational systems. Assessment objective (3.7.4): Determine if media containing diagnostic and test programs are checked for malicious code before being used in organizational systems that process, store, or transmit CUI.. POA&M allowed: No. SPRS score: 3.",
    "metadata": {
      "framework": "NIST 800-171",
      "family": "Maintenance",
      "control_id": "3.7.4",
      "cmmc_id": "MA.L2-3.7.4",
      "title": "MEDIA INSPECTION",
      "sprs": 3,
      "cmmc_levels": [
        "Level 2"
      ],
      "poam_allowed": "No",
      "ao_ids": [
        "3.7.4"
      ],
      "assessment_methods": [
        {
          "type": "Examine",
          "description": "[SELECT FROM: System maintenance policy; procedures addressing system maintenance tools; system maintenance tools and associated documentation; maintenance records; security plan; other relevant documents or records]."
        },
        {
          "type": "Interview",
          "description": "[SELECT FROM: Personnel with system maintenance responsibilities; personnel with information security responsibilities]."
        },
        {
          "type": "Test",
          "description": "[select from:  Organizational process for inspecting media for malicious code; mechanisms supporting or implementing inspection of media used for maintenance]."
        }
      ]
    },
    "last_ao_sentence": "Determine if media containing diagnostic and test programs are checked for malicious code before being used in organizational systems that process, store, or transmit CUI."
  },
  {
    "text": "This is a NIST 800-171 control in the Maintenance family. It corresponds to Level 2. The control ID is MA.L2-3.7.5 with title 'NONLOCAL MAINTENANCE'. Security requirement: Require multifactor authentication to establish nonlocal maintenance sessions via external network connections and terminate such connections when nonlocal maintenance is complete.. Assessment objective (3.7.5[a]): multifactor authentication is required to establish nonlocal maintenance sessions via external network connections.. POA&M allowed: No. SPRS score: 5.\nThis is a NIST 800-171 control in the Maintenance family. It corresponds to Level 2. The control ID is MA.L2-3.7.5 with title 'NONLOCAL MAINTENANCE'. Security requirement: Require multifactor authentication to establish nonlocal maintenance sessions via external network connections and terminate such connections when nonlocal maintenance is complete.. Assessment objective (3.7.5[b]): nonlocal maintenance sessions established via external network connections are terminated when nonlocal maintenance is complete.. POA&M allowed: No. SPRS score: 5.",
    "metadata": {
      "framework": "NIST 800-171",
      "family": "Maintenance",
      "control_id": "3.7.5",
      "cmmc_id": "MA.L2-3.7.5",
      "title": "NONLOCAL MAINTENANCE",
      "sprs": 5,
      "cmmc_levels": [
        "Level 2"
      ],
      "poam_allowed": "No",
      "ao_ids": [
        "3.7.5[a]",
        "3.7.5[b]"
      ],
      "assessment_methods": [
        {
          "type": "Examine",
          "description": "[SELECT FROM: System maintenance policy; procedures addressing nonlocal system maintenance; security plan; system design documentation; system configuration settings and associated documentation; maintenance records; diagnostic records; other relevant documents or records]."
        },
        {
          "type": "Interview",
          "description": "[SELECT FROM: Personnel with system maintenance responsibilities; personnel with information security responsibilities; system or network administrators]."
        },
        {
          "type": "Test",
          "description": "[select from: Organizational processes for managing nonlocal maintenance; mechanisms implementing, supporting, and managing nonlocal maintenance; mechanisms for strong authentication of nonlocal maintenance diagnostic sessions; mechanisms for terminating nonlocal maintenance sessions and network connections]."
        }
      ]
    },
    "last_ao_sentence": "nonlocal maintenance sessions established via external network connections are terminated when nonlocal maintenance is complete."
  },
  {
    "text": "This is a NIST 800-171 control in the Maintenance family. It corresponds to Level 2. The control ID is MA.L2-3.7.6 with title 'MAINTENANCE PERSONNEL'. Security requirement: Supervise the maintenance activities of maintenance personnel without required access authorization.. Assessment objective (3.7.6): Determine if maintenance personnel without required access authorization are supervised during maintenance activities.. POA&M allowed: Yes. SPRS score: 1.",
    "metadata": {
      "framework": "NIST 800-171",
      "family": "Maintenance",
      "control_id": "3.7.6",
      "cmmc_id": "MA.L2-3.7.6",
      "title": "MAINTENANCE PERSONNEL",
      "sprs": 1,
      "cmmc_levels": [
        "Level 2"
      ],
      "poam_allowed": "Yes",
      "ao_ids": [
        "3.7.6"
      ],
      "assessment_methods": [
        {
          "type": "Examine",
          "description": "[SELECT FROM: System maintenance policy; procedures addressing maintenance personnel; service provider contracts; service-level agreements; list of authorized personnel; maintenance records; access control records; security plan; other relevant documents or records]."
        },
        {
          "type": "Interview",
          "description": "[SELECT FROM: Personnel with system maintenance responsibilities; personnel with information security responsibilities]."
        },
        {
          "type": "Test",
          "description": "[SELECT FROM:  Organizational processes for authorizing and managing maintenance personnel; mechanisms supporting or implementing authorization of maintenance personnel]."
        }
      ]
    },
    "last_ao_sentence": "Determine if maintenance personnel without required access authorization are supervised during maintenance activities."
  },
  {
    "text": "This is a NIST 800-171 control in the Media Protection family. It corresponds to Level 2. The control ID is MP.L2-3.8.1 with title 'MEDIA PROTECTION'. Security requirement: Protect (i.e., physically control and securely store) system media containing CUI, both paper and digital.. Assessment objective (3.8.1[a]): paper media containing CUI is physically controlled.. POA&M allowed: No. SPRS score: 3.\nThis is a NIST 800-171 control in the Media Protection family. It corresponds to Level 2. The control ID is MP.L2-3.8.1 with title 'MEDIA PROTECTION'. Security requirement: Protect (i.e., physically control and securely store) system media containing CUI, both paper and digital.. Assessment objective (3.8.1[b]): digital media containing CUI is physically controlled.. POA&M allowed: No. SPRS score: 3.\nThis is a NIST 800-171 control in the Media Protection family. It corresponds to Level 2. The control ID is MP.L2-3.8.1 with title 'MEDIA PROTECTION'. Security requirement: Protect (i.e., physically control and securely store) system media containing CUI, both paper and digital.. Assessment objective (3.8.1[c]): paper media containing CUI is securely stored.. POA&M allowed: No. SPRS score: 3.\nThis is a NIST 800-171 control in the Media Protection family. It corresponds to Level 2. The control ID is MP.L2-3.8.1 with title 'MEDIA PROTECTION'. Security requirement: Protect (i.e., physically control and securely store) system media containing CUI, both paper and digital.. Assessment objective (3.8.1[d]): digital media containing CUI is securely stored.. POA&M allowed: No. SPRS score: 3.",
    "metadata": {
      "framework": "NIST 800-171",
      "family": "Media Protection",
      "control_id": "3.8.1",
      "cmmc_id": "MP.L2-3.8.1",
      "title": "MEDIA PROTECTION",
      "sprs": 3,
      "cmmc_levels": [
        "Level 2"
      ],
      "poam_allowed": "No",
      "ao_ids": [
        "3.8.1[a]",
        "3.8.1[b]",
        "3.8.1[c]",
        "3.8.1[d]"
      ],
      "assessment_methods": [
        {
          "type": "Examine",
          "description": "[SELECT FROM: System media protection policy; procedures addressing media access restrictions; access control policy and procedures; physical and environmental protection policy and procedures; security plan; media storage facilities; access control records; other relevant documents or records]."
        },
        {
          "type": "Interview",
          "description": "[SELECT FROM: Personnel with system media protection responsibilities; personnel with information security responsibilities; system or network administrators]."
        },
        {
          "type": "Test",
          "description": "[SELECT FROM: Organizational processes for restricting information media; mechanisms supporting or implementing media access restrictions]."
        }
      ]
    },
    "last_ao_sentence": "digital media containing CUI is securely stored."
  },
  {
    "text": "This is a NIST 800-171 control in the Media Protection family. It corresponds to Level 2. The control ID is MP.L2-3.8.2 with title 'MEDIA ACCESS'. Security requirement: Limit access to CUI on system media to authorized users.. Assessment objective (3.8.2): Determine if access to CUI on system media is limited to authorized users.. POA&M allowed: No. SPRS score: 3.",
    "metadata": {
      "framework": "NIST 800-171",
      "family": "Media Protection",
      "control_id": "3.8.2",
      "cmmc_id": "MP.L2-3.8.2",
      "title": "MEDIA ACCESS",
      "sprs": 3,
      "cmmc_levels": [
        "Level 2"
      ],
      "poam_allowed": "No",
      "ao_ids": [
        "3.8.2"
      ],
      "assessment_methods": [
        {
          "type": "Examine",
          "description": "[SELECT FROM: System media protection policy; procedures addressing media storage; physical and environmental protection policy and procedures; access control policy and procedures; security plan; system media; designated controlled areas; other relevant documents or records]."
        },
        {
          "type": "Interview",
          "description": "[SELECT FROM: Personnel with system media protection and storage responsibilities; personnel with information security responsibilities]."
        },
        {
          "type": "Test",
          "description": "[SELECT FROM: Organizational processes for storing media; mechanisms supporting or implementing secure media storage and media protection]."
        }
      ]
    },
    "last_ao_sentence": "Determine if access to CUI on system media is limited to authorized users."
  },
  {
    "text": "This is a NIST 800-171 control in the Media Protection family. It corresponds to Level 1, Level 2. The control ID is MP.L1-3.8.3 with title 'MEDIA DISPOSAL'. Security requirement: Sanitize or destroy system media containing CUI before disposal or release for reuse.. Assessment objective (3.8.3[a]): system media containing CUI is sanitized or destroyed before disposal.. POA&M allowed: No. SPRS score: 5.\nThis is a NIST 800-171 control in the Media Protection family. It corresponds to Level 1, Level 2. The control ID is MP.L1-3.8.3 with title 'MEDIA DISPOSAL'. Security requirement: Sanitize or destroy system media containing CUI before disposal or release for reuse.. Assessment objective (3.8.3[b]): system media containing CUI is sanitized before it is released for reuse.. POA&M allowed: No. SPRS score: 5.",
    "metadata": {
      "framework": "NIST 800-171",
      "family": "Media Protection",
      "control_id": "3.8.3",
      "cmmc_id": "MP.L1-3.8.3",
      "title": "MEDIA DISPOSAL",
      "sprs": 5,
      "cmmc_levels": [
        "Level 1",
        "Level 2"
      ],
      "poam_allowed": "No",
      "ao_ids": [
        "3.8.3[a]",
        "3.8.3[b]"
      ],
      "assessment_methods": [
        {
          "type": "Examine",
          "description": "[SELECT FROM: System media protection policy; procedures addressing media sanitization and disposal; applicable standards and policies addressing media sanitization; security plan; media sanitization records; system audit logs and records; system design documentation; system configuration settings and associated documentation; other relevant documents or records]."
        },
        {
          "type": "Interview",
          "description": "[SELECT FROM: Personnel with media sanitization responsibilities; personnel with information security responsibilities; system or network administrators]."
        },
        {
          "type": "Test",
          "description": "[SELECT FROM: Organizational processes for media sanitization; mechanisms supporting or implementing media sanitization]."
        }
      ]
    },
    "last_ao_sentence": "system media containing CUI is sanitized before it is released for reuse."
  },
  {
    "text": "This is a NIST 800-171 control in the Media Protection family. It corresponds to Level 2. The control ID is MP.L2-3.8.4 with title 'MEDIA MARKINGS'. Security requirement: Mark media with necessary CUI markings and distribution limitations.. Assessment objective (3.8.4[a]): media containing CUI is marked with applicable CUI markings.. POA&M allowed: Yes. SPRS score: 1.\nThis is a NIST 800-171 control in the Media Protection family. It corresponds to Level 2. The control ID is MP.L2-3.8.4 with title 'MEDIA MARKINGS'. Security requirement: Mark media with necessary CUI markings and distribution limitations.. Assessment objective (3.8.4[b]): media containing CUI is marked with distribution limitations.. POA&M allowed: Yes. SPRS score: 1.",
    "metadata": {
      "framework": "NIST 800-171",
      "family": "Media Protection",
      "control_id": "3.8.4",
      "cmmc_id": "MP.L2-3.8.4",
      "title": "MEDIA MARKINGS",
      "sprs": 1,
      "cmmc_levels": [
        "Level 2"
      ],
      "poam_allowed": "Yes",
      "ao_ids": [
        "3.8.4[a]",
        "3.8.4[b]"
      ],
      "assessment_methods": [
        {
          "type": "Examine",
          "description": "[SELECT FROM: System media protection policy; procedures addressing media marking; physical and environmental protection policy and procedures; security plan; list of system media marking security attributes; designated controlled areas; other relevant documents or records]."
        },
        {
          "type": "Interview",
          "description": "[SELECT FROM: Personnel with system media protection and marking responsibilities; personnel with information security responsibilities]."
        },
        {
          "type": "Test",
          "description": "[SELECT FROM: Organizational processes for marking information media; mechanisms supporting or implementing media marking]."
        }
      ]
    },
    "last_ao_sentence": "media containing CUI is marked with distribution limitations."
  },
  {
    "text": "This is a NIST 800-171 control in the Media Protection family. It corresponds to Level 2. The control ID is MP.L2-3.8.5 with title 'MEDIA ACCOUNTABILITY'. Security requirement: Control access to media containing CUI and maintain accountability for media during transport outside of controlled areas.. Assessment objective (3.8.5[a]): access to media containing CUI is controlled.. POA&M allowed: Yes. SPRS score: 1.\nThis is a NIST 800-171 control in the Media Protection family. It corresponds to Level 2. The control ID is MP.L2-3.8.5 with title 'MEDIA ACCOUNTABILITY'. Security requirement: Control access to media containing CUI and maintain accountability for media during transport outside of controlled areas.. Assessment objective (3.8.5[b]): accountability for media containing CUI is maintained during transport outside of controlled areas.. POA&M allowed: Yes. SPRS score: 1.",
    "metadata": {
      "framework": "NIST 800-171",
      "family": "Media Protection",
      "control_id": "3.8.5",
      "cmmc_id": "MP.L2-3.8.5",
      "title": "MEDIA ACCOUNTABILITY",
      "sprs": 1,
      "cmmc_levels": [
        "Level 2"
      ],
      "poam_allowed": "Yes",
      "ao_ids": [
        "3.8.5[a]",
        "3.8.5[b]"
      ],
      "assessment_methods": [
        {
          "type": "Examine",
          "description": "SELECT FROM: System media protection policy; procedures addressing media storage; physical and environmental protection policy and procedures; access control policy and procedures; security plan; system media; designated controlled areas; other relevant documents or records]."
        },
        {
          "type": "Interview",
          "description": "[SELECT FROM: Personnel with system media protection and storage responsibilities; personnel with information security responsibilities; system or network administrators]."
        },
        {
          "type": "Test",
          "description": "[SELECT FROM: Organizational processes for storing media; mechanisms supporting or implementing media storage and media protection]."
        }
      ]
    },
    "last_ao_sentence": "accountability for media containing CUI is maintained during transport outside of controlled areas."
  },
  {
    "text": "This is a NIST 800-171 control in the Media Protection family. It corresponds to Level 2. The control ID is MP.L2-3.8.6 with title 'PORTABLE STORAGE ENCRYPTION'. Security requirement: Implement cryptographic mechanisms to protect the confidentiality of CUI stored on digital media during transport unless otherwise protected by alternative physical safeguards.. Assessment objective (3.8.6): Determine if the confidentiality of CUI stored on digital media is protected during transport using cryptographic mechanisms or alternative physical safeguards.. POA&M allowed: Yes. SPRS score: 1.",
    "metadata": {
      "framework": "NIST 800-171",
      "family": "Media Protection",
      "control_id": "3.8.6",
      "cmmc_id": "MP.L2-3.8.6",
      "title": "PORTABLE STORAGE ENCRYPTION",
      "sprs": 1,
      "cmmc_levels": [
        "Level 2"
      ],
      "poam_allowed": "Yes",
      "ao_ids": [
        "3.8.6"
      ],
      "assessment_methods": [
        {
          "type": "Examine",
          "description": "[SELECT FROM: System media protection policy; procedures addressing media transport; system design documentation; security plan; system configuration settings and associated documentation; system media transport records; system audit logs and records; other relevant documents or records]."
        },
        {
          "type": "Interview",
          "description": "[SELECT FROM: Personnel with system media transport responsibilities; personnel with information security responsibilities]."
        },
        {
          "type": "Test",
          "description": "[SELECT FROM: Cryptographic mechanisms protecting information on digital media during transportation outside controlled areas]."
        }
      ]
    },
    "last_ao_sentence": "Determine if the confidentiality of CUI stored on digital media is protected during transport using cryptographic mechanisms or alternative physical safeguards."
  },
  {
    "text": "This is a NIST 800-171 control in the Media Protection family. It corresponds to Level 2. The control ID is MP.L2-3.8.7 with title 'REMOVEABLE MEDIA'. Security requirement: Control the use of removable media on system components.. Assessment objective (3.8.7): Determine if the use of removable media on system components containing CUI is controlled.. POA&M allowed: No. SPRS score: 5.",
    "metadata": {
      "framework": "NIST 800-171",
      "family": "Media Protection",
      "control_id": "3.8.7",
      "cmmc_id": "MP.L2-3.8.7",
      "title": "REMOVEABLE MEDIA",
      "sprs": 5,
      "cmmc_levels": [
        "Level 2"
      ],
      "poam_allowed": "No",
      "ao_ids": [
        "3.8.7"
      ],
      "assessment_methods": [
        {
          "type": "Examine",
          "description": "[SELECT FROM: System media protection policy; system use policy; procedures addressing media usage restrictions; security plan; rules of behavior; system design documentation; system configuration settings and associated documentation; system audit logs and records; other relevant documents or records]."
        },
        {
          "type": "Interview",
          "description": "[SELECT FROM: Personnel with system media use responsibilities; personnel with information security responsibilities; system or network administrators]."
        },
        {
          "type": "Test",
          "description": "[SELECT FROM: Organizational processes for media use; mechanisms restricting or prohibiting use of system media on systems or system components]."
        }
      ]
    },
    "last_ao_sentence": "Determine if the use of removable media on system components containing CUI is controlled."
  },
  {
    "text": "This is a NIST 800-171 control in the Media Protection family. It corresponds to Level 2. The control ID is MP.L2-3.8.8 with title 'SHARED MEDIA'. Security requirement: Prohibit the use of portable storage devices when such devices have no identifiable owner.. Assessment objective (3.8.8): Determine if the use of portable storage devices is prohibited when such devices have no identifiable owner.. POA&M allowed: No. SPRS score: 3.",
    "metadata": {
      "framework": "NIST 800-171",
      "family": "Media Protection",
      "control_id": "3.8.8",
      "cmmc_id": "MP.L2-3.8.8",
      "title": "SHARED MEDIA",
      "sprs": 3,
      "cmmc_levels": [
        "Level 2"
      ],
      "poam_allowed": "No",
      "ao_ids": [
        "3.8.8"
      ],
      "assessment_methods": [
        {
          "type": "Examine",
          "description": "[SELECT FROM: System media protection policy; system use policy; procedures addressing media usage restrictions; security plan; rules of behavior; system design documentation; system configuration settings and associated documentation; system audit logs and records; other relevant documents or records]."
        },
        {
          "type": "Interview",
          "description": "[SELECT FROM: Personnel with system media use responsibilities; personnel with information security responsibilities; system or network administrators]."
        },
        {
          "type": "Test",
          "description": "[SELECT FROM:  Organizational processes for media use; mechanisms prohibiting use of media on systems or system components]."
        }
      ]
    },
    "last_ao_sentence": "Determine if the use of portable storage devices is prohibited when such devices have no identifiable owner."
  },
  {
    "text": "This is a NIST 800-171 control in the Media Protection family. It corresponds to Level 2. The control ID is MP.L2-3.8.9 with title 'PROTECT BACKUPS'. Security requirement: Protect the confidentiality of backup CUI at storage locations.. Assessment objective (3.8.9): Determine if the confidentiality of backup CUI is protected at storage locations.. POA&M allowed: Yes. SPRS score: 1.",
    "metadata": {
      "framework": "NIST 800-171",
      "family": "Media Protection",
      "control_id": "3.8.9",
      "cmmc_id": "MP.L2-3.8.9",
      "title": "PROTECT BACKUPS",
      "sprs": 1,
      "cmmc_levels": [
        "Level 2"
      ],
      "poam_allowed": "Yes",
      "ao_ids": [
        "3.8.9"
      ],
      "assessment_methods": [
        {
          "type": "Examine",
          "description": "[SELECT FROM: Procedures addressing system backup; security plan; backup storage location(s); system backup logs or records; other relevant documents or records]."
        },
        {
          "type": "Interview",
          "description": "[[SELECT FROM: Personnel with system backup responsibilities; personnel with information security responsibilities]."
        },
        {
          "type": "Test",
          "description": "[SELECT FROM: Organizational processes for conducting system backups; mechanisms supporting or implementing system backups]."
        }
      ]
    },
    "last_ao_sentence": "Determine if the confidentiality of backup CUI is protected at storage locations."
  },
  {
    "text": "This is a NIST 800-171 control in the Personnel Security family. It corresponds to Level 2. The control ID is PS.L2-3.9.1 with title 'SCREEN INDIVIDUALS'. Security requirement: Screen individuals prior to authorizing access to organizational systems containing CUI.. Assessment objective (3.9.1): Determine if individuals are screened prior to authorizing access to organizational systems.. POA&M allowed: No. SPRS score: 3.",
    "metadata": {
      "framework": "NIST 800-171",
      "family": "Personnel Security",
      "control_id": "3.9.1",
      "cmmc_id": "PS.L2-3.9.1",
      "title": "SCREEN INDIVIDUALS",
      "sprs": 3,
      "cmmc_levels": [
        "Level 2"
      ],
      "poam_allowed": "No",
      "ao_ids": [
        "3.9.1"
      ],
      "assessment_methods": [
        {
          "type": "Examine",
          "description": "[SELECT FROM: Personnel security policy; procedures addressing personnel screening; records of screened personnel; security plan; other relevant documents or records]."
        },
        {
          "type": "Interview",
          "description": "[SELECT FROM: Personnel with personnel security responsibilities; personnel with information security responsibilities]."
        },
        {
          "type": "Test",
          "description": "[SELECT FROM: Organizational processes for personnel screening]."
        }
      ]
    },
    "last_ao_sentence": "Determine if individuals are screened prior to authorizing access to organizational systems."
  },
  {
    "text": "This is a NIST 800-171 control in the Personnel Security family. It corresponds to Level 2. The control ID is PS.L2-3.9.2 with title 'PERSONNEL ACTIONS'. Security requirement: Ensure that organizational systems containing CUI are protected during and after personnel actions such as terminations and transfers.. Assessment objective (3.9.2[a]): a policy and/or process for terminating system access authorization and any credentials coincident with personnel actions is established.. POA&M allowed: No. SPRS score: 5.\nThis is a NIST 800-171 control in the Personnel Security family. It corresponds to Level 2. The control ID is PS.L2-3.9.2 with title 'PERSONNEL ACTIONS'. Security requirement: Ensure that organizational systems containing CUI are protected during and after personnel actions such as terminations and transfers.. Assessment objective (3.9.2[b]): system access and credentials are terminated consistent with personnel actions such as termination or transfer.. POA&M allowed: No. SPRS score: 5.\nThis is a NIST 800-171 control in the Personnel Security family. It corresponds to Level 2. The control ID is PS.L2-3.9.2 with title 'PERSONNEL ACTIONS'. Security requirement: Ensure that organizational systems containing CUI are protected during and after personnel actions such as terminations and transfers.. Assessment objective (3.9.2[c]): the system is protected during and after personnel transfer actions.. POA&M allowed: No. SPRS score: 5.",
    "metadata": {
      "framework": "NIST 800-171",
      "family": "Personnel Security",
      "control_id": "3.9.2",
      "cmmc_id": "PS.L2-3.9.2",
      "title": "PERSONNEL ACTIONS",
      "sprs": 5,
      "cmmc_levels": [
        "Level 2"
      ],
      "poam_allowed": "No",
      "ao_ids": [
        "3.9.2[a]",
        "3.9.2[b]",
        "3.9.2[c]"
      ],
      "assessment_methods": [
        {
          "type": "Examine",
          "description": "[SELECT FROM: Personnel security policy; procedures addressing personnel transfer and termination; records of personnel transfer and termination actions; list of system accounts; records of terminated or revoked authenticators and credentials; records of exit interviews; other relevant documents or records]."
        },
        {
          "type": "Interview",
          "description": "[SELECT FROM: Personnel with personnel security responsibilities; personnel with account management responsibilities; system or network administrators; personnel with information security responsibilities]."
        },
        {
          "type": "Test",
          "description": "[SELECT FROM:  Organizational processes for personnel transfer and termination; mechanisms supporting or implementing personnel transfer and termination notifications; mechanisms for disabling system access and revoking authenticators]."
        }
      ]
    },
    "last_ao_sentence": "the system is protected during and after personnel transfer actions."
  },
  {
    "text": "This is a NIST 800-171 control in the Physical Protection family. It corresponds to Level 1, Level 2. The control ID is PE.L1-3.10.1 with title 'LIMIT PHYSICAL ACCESS'. Security requirement: Limit physical access to organizational systems, equipment, and the respective operating environments to authorized individuals.. Assessment objective (3.10.1[a]): authorized individuals allowed physical access are identified.. POA&M allowed: No. SPRS score: 5.\nThis is a NIST 800-171 control in the Physical Protection family. It corresponds to Level 1, Level 2. The control ID is PE.L1-3.10.1 with title 'LIMIT PHYSICAL ACCESS'. Security requirement: Limit physical access to organizational systems, equipment, and the respective operating environments to authorized individuals.. Assessment objective (3.10.1[b]): physical access to organizational systems is limited to authorized individuals.. POA&M allowed: No. SPRS score: 5.\nThis is a NIST 800-171 control in the Physical Protection family. It corresponds to Level 1, Level 2. The control ID is PE.L1-3.10.1 with title 'LIMIT PHYSICAL ACCESS'. Security requirement: Limit physical access to organizational systems, equipment, and the respective operating environments to authorized individuals.. Assessment objective (3.10.1[c]): physical access to equipment is limited to authorized individuals.. POA&M allowed: No. SPRS score: 5.\nThis is a NIST 800-171 control in the Physical Protection family. It corresponds to Level 1, Level 2. The control ID is PE.L1-3.10.1 with title 'LIMIT PHYSICAL ACCESS'. Security requirement: Limit physical access to organizational systems, equipment, and the respective operating environments to authorized individuals.. Assessment objective (3.10.1[d]): physical access to operating environments is limited to authorized individuals.. POA&M allowed: No. SPRS score: 5.",
    "metadata": {
      "framework": "NIST 800-171",
      "family": "Physical Protection",
      "control_id": "3.10.1",
      "cmmc_id": "PE.L1-3.10.1",
      "title": "LIMIT PHYSICAL ACCESS",
      "sprs": 5,
      "cmmc_levels": [
        "Level 1",
        "Level 2"
      ],
      "poam_allowed": "No",
      "ao_ids": [
        "3.10.1[a]",
        "3.10.1[b]",
        "3.10.1[c]",
        "3.10.1[d]"
      ],
      "assessment_methods": [
        {
          "type": "Examine",
          "description": "[SELECT FROM: Physical and environmental protection policy; procedures addressing physical access authorizations; security plan; authorized personnel access list; authorization credentials; physical access list reviews; physical access termination records and associated documentation; other relevant documents or records]."
        },
        {
          "type": "Interview",
          "description": "[SELECT FROM: Personnel with physical access authorization responsibilities; personnel with physical access to system facility; personnel with information security responsibilities]."
        },
        {
          "type": "Test",
          "description": "[SELECT FROM: Organizational processes for physical access authorizations; mechanisms supporting or implementing physical access authorizations]."
        }
      ]
    },
    "last_ao_sentence": "physical access to operating environments is limited to authorized individuals."
  },
  {
    "text": "This is a NIST 800-171 control in the Physical Protection family. It corresponds to Level 2. The control ID is PE.L2-3.10.2 with title 'MONITOR FACILITY'. Security requirement: Protect and monitor the physical facility and support infrastructure for organizational systems.. Assessment objective (3.10.2[a]): the physical facility where that system resides is protected.. POA&M allowed: No. SPRS score: 5.\nThis is a NIST 800-171 control in the Physical Protection family. It corresponds to Level 2. The control ID is PE.L2-3.10.2 with title 'MONITOR FACILITY'. Security requirement: Protect and monitor the physical facility and support infrastructure for organizational systems.. Assessment objective (3.10.2[b]): the support infrastructure for that system is protected.. POA&M allowed: No. SPRS score: 5.\nThis is a NIST 800-171 control in the Physical Protection family. It corresponds to Level 2. The control ID is PE.L2-3.10.2 with title 'MONITOR FACILITY'. Security requirement: Protect and monitor the physical facility and support infrastructure for organizational systems.. Assessment objective (3.10.2[c]): the physical facility where that system resides is monitored.. POA&M allowed: No. SPRS score: 5.\nThis is a NIST 800-171 control in the Physical Protection family. It corresponds to Level 2. The control ID is PE.L2-3.10.2 with title 'MONITOR FACILITY'. Security requirement: Protect and monitor the physical facility and support infrastructure for organizational systems.. Assessment objective (3.10.2[d]): the support infrastructure for that system is monitored.. POA&M allowed: No. SPRS score: 5.",
    "metadata": {
      "framework": "NIST 800-171",
      "family": "Physical Protection",
      "control_id": "3.10.2",
      "cmmc_id": "PE.L2-3.10.2",
      "title": "MONITOR FACILITY",
      "sprs": 5,
      "cmmc_levels": [
        "Level 2"
      ],
      "poam_allowed": "No",
      "ao_ids": [
        "3.10.2[a]",
        "3.10.2[b]",
        "3.10.2[c]",
        "3.10.2[d]"
      ],
      "assessment_methods": [
        {
          "type": "Examine",
          "description": "[SELECT FROM: Physical and environmental protection policy; procedures addressing physical access monitoring; security plan; physical access logs or records; physical access monitoring records; physical access log reviews; other relevant documents or records]."
        },
        {
          "type": "Interview",
          "description": "[SELECT FROM: Personnel with physical access monitoring responsibilities; personnel with incident response responsibilities; personnel with information security responsibilities]."
        },
        {
          "type": "Test",
          "description": "[SELECT FROM: Organizational processes for monitoring physical access; mechanisms supporting or implementing physical access monitoring; mechanisms supporting or implementing the review of physical access logs]."
        }
      ]
    },
    "last_ao_sentence": "the support infrastructure for that system is monitored."
  },
  {
    "text": "This is a NIST 800-171 control in the Physical Protection family. It corresponds to Level 1, Level 2. The control ID is PE.L1-3.10.3 with title 'ESCORT VISITORS'. Security requirement: Escort visitors and monitor visitor activity.. Assessment objective (3.10.3[a]): visitors are escorted.. POA&M allowed: No. SPRS score: 1.\nThis is a NIST 800-171 control in the Physical Protection family. It corresponds to Level 1, Level 2. The control ID is PE.L1-3.10.3 with title 'ESCORT VISITORS'. Security requirement: Escort visitors and monitor visitor activity.. Assessment objective (3.10.3[b]): visitor activity is monitored.. POA&M allowed: No. SPRS score: 1.",
    "metadata": {
      "framework": "NIST 800-171",
      "family": "Physical Protection",
      "control_id": "3.10.3",
      "cmmc_id": "PE.L1-3.10.3",
      "title": "ESCORT VISITORS",
      "sprs": 1,
      "cmmc_levels": [
        "Level 1",
        "Level 2"
      ],
      "poam_allowed": "No",
      "ao_ids": [
        "3.10.3[a]",
        "3.10.3[b]"
      ],
      "assessment_methods": [
        {
          "type": "Examine",
          "description": "[SELECT FROM: Physical and environmental protection policy; procedures addressing physical access control; security plan; physical access control logs or records; inventory records of physical access control devices; system entry and exit points; records of key and lock combination changes; storage locations for physical access control devices; physical access control devices; list of security safeguards controlling access to designated publicly accessible areas within facility; other relevant documents or records]."
        },
        {
          "type": "Interview",
          "description": "[SELECT FROM: Personnel with physical access control responsibilities; personnel with information security responsibilities]."
        },
        {
          "type": "Test",
          "description": "[SELECT FROM: Organizational processes for physical access control; mechanisms supporting or implementing physical access control; physical access control devices]."
        }
      ]
    },
    "last_ao_sentence": "visitor activity is monitored."
  },
  {
    "text": "This is a NIST 800-171 control in the Physical Protection family. It corresponds to Level 1, Level 2. The control ID is PE.L1-3.10.4 with title 'PHYSICAL ACCESS LOGS'. Security requirement: Maintain audit logs of physical access.. Assessment objective (3.10.4): Determine if audit logs of physical access are maintained.. POA&M allowed: No. SPRS score: 1.",
    "metadata": {
      "framework": "NIST 800-171",
      "family": "Physical Protection",
      "control_id": "3.10.4",
      "cmmc_id": "PE.L1-3.10.4",
      "title": "PHYSICAL ACCESS LOGS",
      "sprs": 1,
      "cmmc_levels": [
        "Level 1",
        "Level 2"
      ],
      "poam_allowed": "No",
      "ao_ids": [
        "3.10.4"
      ],
      "assessment_methods": [
        {
          "type": "Examine",
          "description": "[SELECT FROM: Physical and environmental protection policy; procedures addressing physical access control; security plan; physical access control logs or records; inventory records of physical access control devices; system entry and exit points; records of key and lock combination changes; storage locations for physical access control devices; physical access control devices; list of security safeguards controlling access to designated publicly accessible areas within facility; other relevant documents or records]."
        },
        {
          "type": "Interview",
          "description": "[SELECT FROM: Personnel with physical access control responsibilities; personnel with information security responsibilities"
        },
        {
          "type": "Test",
          "description": "[SELECT FROM: Organizational processes for physical access control; mechanisms supporting or implementing physical access control; physical access control devices]."
        }
      ]
    },
    "last_ao_sentence": "Determine if audit logs of physical access are maintained."
  },
  {
    "text": "This is a NIST 800-171 control in the Physical Protection family. It corresponds to Level 1, Level 2. The control ID is PE.L1-3.10.5 with title 'MANAGE PHYSICAL ACCESS'. Security requirement: Control and manage physical access devices.. Assessment objective (3.10.5[a]): physical access devices are identified.. POA&M allowed: No. SPRS score: 1.\nThis is a NIST 800-171 control in the Physical Protection family. It corresponds to Level 1, Level 2. The control ID is PE.L1-3.10.5 with title 'MANAGE PHYSICAL ACCESS'. Security requirement: Control and manage physical access devices.. Assessment objective (3.10.5[b]): physical access devices are controlled.. POA&M allowed: No. SPRS score: 1.\nThis is a NIST 800-171 control in the Physical Protection family. It corresponds to Level 1, Level 2. The control ID is PE.L1-3.10.5 with title 'MANAGE PHYSICAL ACCESS'. Security requirement: Control and manage physical access devices.. Assessment objective (3.10.5[c]): physical access devices are managed.. POA&M allowed: No. SPRS score: 1.",
    "metadata": {
      "framework": "NIST 800-171",
      "family": "Physical Protection",
      "control_id": "3.10.5",
      "cmmc_id": "PE.L1-3.10.5",
      "title": "MANAGE PHYSICAL ACCESS",
      "sprs": 1,
      "cmmc_levels": [
        "Level 1",
        "Level 2"
      ],
      "poam_allowed": "No",
      "ao_ids": [
        "3.10.5[a]",
        "3.10.5[b]",
        "3.10.5[c]"
      ],
      "assessment_methods": [
        {
          "type": "Examine",
          "description": "[SELECT FROM: Physical and environmental protection policy; procedures addressing physical access control; security plan; physical access control logs or records; inventory records of physical access control devices; system entry and exit points; records of key and lock combination changes; storage locations for physical access control devices; physical access control devices; list of security safeguards controlling access to designated publicly accessible areas within facility; other relevant documents or records]."
        },
        {
          "type": "Interview",
          "description": "[SELECT FROM: Personnel with physical access control responsibilities; personnel with information security responsibilities]."
        },
        {
          "type": "Test",
          "description": "[SELECT FROM: Organizational processes for physical access control; mechanisms supporting or implementing physical access control; physical access control devices]."
        }
      ]
    },
    "last_ao_sentence": "physical access devices are managed."
  },
  {
    "text": "This is a NIST 800-171 control in the Physical Protection family. It corresponds to Level 2. The control ID is PE.L2-3.10.6 with title 'ALTERNATIVE WORK SITES'. Security requirement: Enforce safeguarding measures for CUI at alternate work sites.. Assessment objective (3.10.6[a]): safeguarding measures for CUI are defined for alternate work sites.. POA&M allowed: Yes. SPRS score: 1.\nThis is a NIST 800-171 control in the Physical Protection family. It corresponds to Level 2. The control ID is PE.L2-3.10.6 with title 'ALTERNATIVE WORK SITES'. Security requirement: Enforce safeguarding measures for CUI at alternate work sites.. Assessment objective (3.10.6[b]): safeguarding measures for CUI are enforced for alternate work sites.. POA&M allowed: Yes. SPRS score: 1.",
    "metadata": {
      "framework": "NIST 800-171",
      "family": "Physical Protection",
      "control_id": "3.10.6",
      "cmmc_id": "PE.L2-3.10.6",
      "title": "ALTERNATIVE WORK SITES",
      "sprs": 1,
      "cmmc_levels": [
        "Level 2"
      ],
      "poam_allowed": "Yes",
      "ao_ids": [
        "3.10.6[a]",
        "3.10.6[b]"
      ],
      "assessment_methods": [
        {
          "type": "Examine",
          "description": "[SELECT FROM: Physical and environmental protection policy; procedures addressing alternate work sites for personnel; security plan; list of safeguards required for alternate work sites; assessments of safeguards at alternate work sites; other relevant documents or records]."
        },
        {
          "type": "Interview",
          "description": "[SELECT FROM: Personnel approving use of alternate work sites; personnel using alternate work sites; personnel assessing controls at alternate work sites; personnel with information security responsibilities]."
        },
        {
          "type": "Test",
          "description": "[SELECT FROM: Organizational processes for security at alternate work sites; mechanisms supporting alternate work sites; safeguards employed at alternate work sites; means of communications between personnel at alternate work sites and security personnel]."
        }
      ]
    },
    "last_ao_sentence": "safeguarding measures for CUI are enforced for alternate work sites."
  },
  {
    "text": "This is a NIST 800-171 control in the Risk Assessment family. It corresponds to Level 2. The control ID is RA.L2-3.11.1 with title 'RISK ASSESSMENTS'. Security requirement: Periodically assess the risk to organizational operations (including mission, functions, image, or reputation), organizational assets, and individuals, resulting from the operation of organizational systems and the associated processing, storage, or transmission of CUI. Assessment objective (3.11.1[a]): the frequency to assess risk to organizational operations, organizational assets, and individuals is defined.. POA&M allowed: No. SPRS score: 3.\nThis is a NIST 800-171 control in the Risk Assessment family. It corresponds to Level 2. The control ID is RA.L2-3.11.1 with title 'RISK ASSESSMENTS'. Security requirement: Periodically assess the risk to organizational operations (including mission, functions, image, or reputation), organizational assets, and individuals, resulting from the operation of organizational systems and the associated processing, storage, or transmission of CUI. Assessment objective (3.11.1[b]): risk to organizational operations, organizational assets, and individuals resulting from the operation of an organizational system that processes, stores, or transmits CUI is assessed with the defined frequency.. POA&M allowed: No. SPRS score: 3.",
    "metadata": {
      "framework": "NIST 800-171",
      "family": "Risk Assessment",
      "control_id": "3.11.1",
      "cmmc_id": "RA.L2-3.11.1",
      "title": "RISK ASSESSMENTS",
      "sprs": 3,
      "cmmc_levels": [
        "Level 2"
      ],
      "poam_allowed": "No",
      "ao_ids": [
        "3.11.1[a]",
        "3.11.1[b]"
      ],
      "assessment_methods": [
        {
          "type": "Examine",
          "description": "[SELECT FROM: Risk assessment policy; security planning policy and procedures; procedures addressing organizational risk assessments; security plan; risk assessment; risk assessment results; risk assessment reviews; risk assessment updates; other relevant documents or records]."
        },
        {
          "type": "Interview",
          "description": "[SELECT FROM: Personnel with risk assessment responsibilities; personnel with information security responsibilities]."
        },
        {
          "type": "Test",
          "description": "[SELECT FROM: Organizational processes for risk assessment; mechanisms supporting or for conducting, documenting, reviewing, disseminating, and updating the risk assessment]."
        }
      ]
    },
    "last_ao_sentence": "risk to organizational operations, organizational assets, and individuals resulting from the operation of an organizational system that processes, stores, or transmits CUI is assessed with the defined frequency."
  },
  {
    "text": "This is a NIST 800-171 control in the Risk Assessment family. It corresponds to Level 2. The control ID is RA.L2-3.11.2 with title 'VULNERABILITY SCAN'. Security requirement: Scan for vulnerabilities in organizational systems and applications periodically and when new vulnerabilities affecting those systems and applications are identified.. Assessment objective (3.11.2[a]): the frequency to scan for vulnerabilities in an organizational system and its applications that process, store, or transmit CUI is defined.. POA&M allowed: No. SPRS score: 5.\nThis is a NIST 800-171 control in the Risk Assessment family. It corresponds to Level 2. The control ID is RA.L2-3.11.2 with title 'VULNERABILITY SCAN'. Security requirement: Scan for vulnerabilities in organizational systems and applications periodically and when new vulnerabilities affecting those systems and applications are identified.. Assessment objective (3.11.2[b]): vulnerability scans are performed in an organizational system that processes, stores, or transmits CUI with the defined frequency.. POA&M allowed: No. SPRS score: 5.\nThis is a NIST 800-171 control in the Risk Assessment family. It corresponds to Level 2. The control ID is RA.L2-3.11.2 with title 'VULNERABILITY SCAN'. Security requirement: Scan for vulnerabilities in organizational systems and applications periodically and when new vulnerabilities affecting those systems and applications are identified.. Assessment objective (3.11.2[c]): vulnerability scans are performed in an application that contains CUI with the defined frequency.. POA&M allowed: No. SPRS score: 5.\nThis is a NIST 800-171 control in the Risk Assessment family. It corresponds to Level 2. The control ID is RA.L2-3.11.2 with title 'VULNERABILITY SCAN'. Security requirement: Scan for vulnerabilities in organizational systems and applications periodically and when new vulnerabilities affecting those systems and applications are identified.. Assessment objective (3.11.2[d]): vulnerability scans are performed in an organizational system that processes, stores, or transmits CUI when new vulnerabilities are identified.. POA&M allowed: No. SPRS score: 5.\nThis is a NIST 800-171 control in the Risk Assessment family. It corresponds to Level 2. The control ID is RA.L2-3.11.2 with title 'VULNERABILITY SCAN'. Security requirement: Scan for vulnerabilities in organizational systems and applications periodically and when new vulnerabilities affecting those systems and applications are identified.. Assessment objective (3.11.2[e]): vulnerability scans are performed in an application that contains CUI when new vulnerabilities are identified.. POA&M allowed: No. SPRS score: 5.",
    "metadata": {
      "framework": "NIST 800-171",
      "family": "Risk Assessment",
      "control_id": "3.11.2",
      "cmmc_id": "RA.L2-3.11.2",
      "title": "VULNERABILITY SCAN",
      "sprs": 5,
      "cmmc_levels": [
        "Level 2"
      ],
      "poam_allowed": "No",
      "ao_ids": [
        "3.11.2[a]",
        "3.11.2[b]",
        "3.11.2[c]",
        "3.11.2[d]",
        "3.11.2[e]"
      ],
      "assessment_methods": [
        {
          "type": "Examine",
          "description": "[SELECT FROM: Risk assessment policy; procedures addressing vulnerability scanning; risk assessment; security plan; security assessment report; vulnerability scanning tools and associated configuration documentation; vulnerability scanning results; patch and vulnerability management records; other relevant documents or records]."
        },
        {
          "type": "Interview",
          "description": "[SELECT FROM: Personnel with risk assessment, security assessment and vulnerability scanning responsibilities; personnel with vulnerability scan analysis and remediation responsibilities; personnel with information security responsibilities; system or network administrators]."
        },
        {
          "type": "Test",
          "description": "[SELECT FROM: Organizational processes for vulnerability scanning, analysis, remediation, and information sharing; mechanisms supporting or implementing vulnerability scanning, analysis, remediation, and information sharing]."
        }
      ]
    },
    "last_ao_sentence": "vulnerability scans are performed in an application that contains CUI when new vulnerabilities are identified."
  },
  {
    "text": "This is a NIST 800-171 control in the Risk Assessment family. It corresponds to Level 2. The control ID is RA.L2-3.11.3 with title 'VULNERABILITY REMEDIATION'. Security requirement: Remediate vulnerabilities in accordance with risk assessments.. Assessment objective (3.11.3[a]): vulnerabilities are identified.. POA&M allowed: No. SPRS score: 5.\nThis is a NIST 800-171 control in the Risk Assessment family. It corresponds to Level 2. The control ID is RA.L2-3.11.3 with title 'VULNERABILITY REMEDIATION'. Security requirement: Remediate vulnerabilities in accordance with risk assessments.. Assessment objective (3.11.3[b]): vulnerabilities are remediated in accordance with risk assessments.. POA&M allowed: No. SPRS score: 5.",
    "metadata": {
      "framework": "NIST 800-171",
      "family": "Risk Assessment",
      "control_id": "3.11.3",
      "cmmc_id": "RA.L2-3.11.3",
      "title": "VULNERABILITY REMEDIATION",
      "sprs": 5,
      "cmmc_levels": [
        "Level 2"
      ],
      "poam_allowed": "No",
      "ao_ids": [
        "3.11.3[a]",
        "3.11.3[b]"
      ],
      "assessment_methods": [
        {
          "type": "Examine",
          "description": "[SELECT FROM: Risk assessment policy; procedures addressing vulnerability scanning; risk assessment; security plan; security assessment report; vulnerability scanning tools and associated configuration documentation; vulnerability scanning results; patch and vulnerability management records; other relevant documents or records]."
        },
        {
          "type": "Interview",
          "description": "[SELECT FROM: Personnel with risk assessment, security assessment and vulnerability scanning responsibilities; personnel with vulnerability scan analysis responsibilities; personnel with vulnerability remediation responsibilities; personnel with information security responsibilities; system or network administrators]."
        },
        {
          "type": "Test",
          "description": "[SELECT FROM: Organizational processes for vulnerability scanning, analysis, remediation, and information sharing; mechanisms supporting or implementing vulnerability scanning, analysis, remediation, and information sharing]."
        }
      ]
    },
    "last_ao_sentence": "vulnerabilities are remediated in accordance with risk assessments."
  },
  {
    "text": "This is a NIST 800-171 control in the Security Assessment family. It corresponds to Level 2. The control ID is CA.L2-3.12.1 with title 'SECURITY CONTROL ASSESSMENT'. Security requirement: Periodically assess the security controls in organizational systems to determine if the controls are effective in their application.. Assessment objective (3.12.1[a]): the frequency of security control assessments is defined.. POA&M allowed: No. SPRS score: 3.\nThis is a NIST 800-171 control in the Security Assessment family. It corresponds to Level 2. The control ID is CA.L2-3.12.1 with title 'SECURITY CONTROL ASSESSMENT'. Security requirement: Periodically assess the security controls in organizational systems to determine if the controls are effective in their application.. Assessment objective (3.12.1[b]): security controls are assessed with the defined frequency to determine if the controls are effective in their application.. POA&M allowed: No. SPRS score: 3.",
    "metadata": {
      "framework": "NIST 800-171",
      "family": "Security Assessment",
      "control_id": "3.12.1",
      "cmmc_id": "CA.L2-3.12.1",
      "title": "SECURITY CONTROL ASSESSMENT",
      "sprs": 3,
      "cmmc_levels": [
        "Level 2"
      ],
      "poam_allowed": "No",
      "ao_ids": [
        "3.12.1[a]",
        "3.12.1[b]"
      ],
      "assessment_methods": [
        {
          "type": "Examine",
          "description": "[SELECT FROM: Security assessment and authorization policy; procedures addressing security assessment planning; procedures addressing security assessments; security assessment plan; security plan; other relevant documents or records]."
        },
        {
          "type": "Interview",
          "description": "[SELECT FROM: Personnel with security assessment responsibilities; personnel with information security responsibilities]."
        },
        {
          "type": "Test",
          "description": "[SELECT FROM: Mechanisms supporting security assessment, security assessment plan development, and security assessment reporting]."
        }
      ]
    },
    "last_ao_sentence": "security controls are assessed with the defined frequency to determine if the controls are effective in their application."
  },
  {
    "text": "This is a NIST 800-171 control in the Security Assessment family. It corresponds to Level 2. The control ID is CA.L2-3.12.2 with title 'PLAN OF ACTION'. Security requirement: Develop and implement plans of action designed to correct deficiencies and reduce or eliminate vulnerabilities in organizational systems. Assessment objective (3.12.2[a]): deficiencies and vulnerabilities to be addressed by the plan of action are identified.. POA&M allowed: No. SPRS score: 3.\nThis is a NIST 800-171 control in the Security Assessment family. It corresponds to Level 2. The control ID is CA.L2-3.12.2 with title 'PLAN OF ACTION'. Security requirement: Develop and implement plans of action designed to correct deficiencies and reduce or eliminate vulnerabilities in organizational systems. Assessment objective (3.12.2[b]): a plan of action is developed to correct identified deficiencies and reduce or eliminate identified vulnerabilities.. POA&M allowed: No. SPRS score: 3.\nThis is a NIST 800-171 control in the Security Assessment family. It corresponds to Level 2. The control ID is CA.L2-3.12.2 with title 'PLAN OF ACTION'. Security requirement: Develop and implement plans of action designed to correct deficiencies and reduce or eliminate vulnerabilities in organizational systems. Assessment objective (3.12.2[c]): the plan of action is implemented to correct identified deficiencies and reduce or eliminate identified vulnerabilities.. POA&M allowed: No. SPRS score: 3.",
    "metadata": {
      "framework": "NIST 800-171",
      "family": "Security Assessment",
      "control_id": "3.12.2",
      "cmmc_id": "CA.L2-3.12.2",
      "title": "PLAN OF ACTION",
      "sprs": 3,
      "cmmc_levels": [
        "Level 2"
      ],
      "poam_allowed": "No",
      "ao_ids": [
        "3.12.2[a]",
        "3.12.2[b]",
        "3.12.2[c]"
      ],
      "assessment_methods": [
        {
          "type": "Examine",
          "description": "[SELECT FROM: Security assessment and authorization policy; procedures addressing plan of action; security plan; security assessment plan; security assessment report; security assessment evidence; plan of action; other relevant documents or records]."
        },
        {
          "type": "Interview",
          "description": "[SELECT FROM: Personnel with plan of action development and implementation responsibilities; personnel with information security responsibilities]."
        },
        {
          "type": "Test",
          "description": "[SELECT FROM: Mechanisms for developing, implementing, and maintaining plan of action]."
        }
      ]
    },
    "last_ao_sentence": "the plan of action is implemented to correct identified deficiencies and reduce or eliminate identified vulnerabilities."
  },
  {
    "text": "This is a NIST 800-171 control in the Security Assessment family. It corresponds to Level 2. The control ID is CA.L2-3.12.3 with title 'SECURITY CONTROL MONITORING'. Security requirement: Monitor security controls on an ongoing basis to ensure the continued effectiveness of the controls.. Assessment objective (3.12.3): Determine if security controls are monitored on an ongoing basis to ensure the continued effectiveness of those controls.. POA&M allowed: No. SPRS score: 5.",
    "metadata": {
      "framework": "NIST 800-171",
      "family": "Security Assessment",
      "control_id": "3.12.3",
      "cmmc_id": "CA.L2-3.12.3",
      "title": "SECURITY CONTROL MONITORING",
      "sprs": 5,
      "cmmc_levels": [
        "Level 2"
      ],
      "poam_allowed": "No",
      "ao_ids": [
        "3.12.3"
      ],
      "assessment_methods": [
        {
          "type": "Examine",
          "description": "[SELECT FROM: Security planning policy; organizational procedures addressing security plan development and implementation; procedures addressing security plan reviews and updates; enterprise architecture documentation; security plan; records of security plan reviews and updates; other relevant documents or records]."
        },
        {
          "type": "Interview",
          "description": "[SELECT FROM: Personnel with security planning and plan implementation responsibilities; personnel with information security responsibilities]."
        },
        {
          "type": "Test",
          "description": "[SELECT FROM: Organizational processes for security plan development, review, update, and approval; mechanisms supporting the security plan]."
        }
      ]
    },
    "last_ao_sentence": "Determine if security controls are monitored on an ongoing basis to ensure the continued effectiveness of those controls."
  },
  {
    "text": "This is a NIST 800-171 control in the Security Assessment family. It corresponds to Level 2. The control ID is CA.L2-3.12.4 with title 'SYSTEM SECURITY PLAN'. Security requirement: Develop, document, and periodically update system security plans that describe system boundaries, system environments of operation, how security requirements are implemented, and the relationships with or connections to other systems.. Assessment objective (3.12.4[a]): a system security plan is developed.. POA&M allowed: No. SPRS score: 0.\nThis is a NIST 800-171 control in the Security Assessment family. It corresponds to Level 2. The control ID is CA.L2-3.12.4 with title 'SYSTEM SECURITY PLAN'. Security requirement: Develop, document, and periodically update system security plans that describe system boundaries, system environments of operation, how security requirements are implemented, and the relationships with or connections to other systems.. Assessment objective (3.12.4[b]): the system boundary is described and documented in the system security plan.. POA&M allowed: No. SPRS score: 0.\nThis is a NIST 800-171 control in the Security Assessment family. It corresponds to Level 2. The control ID is CA.L2-3.12.4 with title 'SYSTEM SECURITY PLAN'. Security requirement: Develop, document, and periodically update system security plans that describe system boundaries, system environments of operation, how security requirements are implemented, and the relationships with or connections to other systems.. Assessment objective (3.12.4[c]): the system environment of operation is described and documented in the system security plan.. POA&M allowed: No. SPRS score: 0.\nThis is a NIST 800-171 control in the Security Assessment family. It corresponds to Level 2. The control ID is CA.L2-3.12.4 with title 'SYSTEM SECURITY PLAN'. Security requirement: Develop, document, and periodically update system security plans that describe system boundaries, system environments of operation, how security requirements are implemented, and the relationships with or connections to other systems.. Assessment objective (3.12.4[d]): the security requirements identified and approved by the designated authority as non-applicable are identified.. POA&M allowed: No. SPRS score: 0.\nThis is a NIST 800-171 control in the Security Assessment family. It corresponds to Level 2. The control ID is CA.L2-3.12.4 with title 'SYSTEM SECURITY PLAN'. Security requirement: Develop, document, and periodically update system security plans that describe system boundaries, system environments of operation, how security requirements are implemented, and the relationships with or connections to other systems.. Assessment objective (3.12.4[e]): the method of security requirement implementation is described and documented in the system security plan.. POA&M allowed: No. SPRS score: 0.\nThis is a NIST 800-171 control in the Security Assessment family. It corresponds to Level 2. The control ID is CA.L2-3.12.4 with title 'SYSTEM SECURITY PLAN'. Security requirement: Develop, document, and periodically update system security plans that describe system boundaries, system environments of operation, how security requirements are implemented, and the relationships with or connections to other systems.. Assessment objective (3.12.4[f]): the relationship with or connection to other systems is described and documented in the system security plan.. POA&M allowed: No. SPRS score: 0.\nThis is a NIST 800-171 control in the Security Assessment family. It corresponds to Level 2. The control ID is CA.L2-3.12.4 with title 'SYSTEM SECURITY PLAN'. Security requirement: Develop, document, and periodically update system security plans that describe system boundaries, system environments of operation, how security requirements are implemented, and the relationships with or connections to other systems.. Assessment objective (3.12.4[g]): the frequency to update the system security plan is defined.. POA&M allowed: No. SPRS score: 0.\nThis is a NIST 800-171 control in the Security Assessment family. It corresponds to Level 2. The control ID is CA.L2-3.12.4 with title 'SYSTEM SECURITY PLAN'. Security requirement: Develop, document, and periodically update system security plans that describe system boundaries, system environments of operation, how security requirements are implemented, and the relationships with or connections to other systems.. Assessment objective (3.12.4.[h]): system security plan is updated with the defined frequency.. POA&M allowed: No. SPRS score: 0.",
    "metadata": {
      "framework": "NIST 800-171",
      "family": "Security Assessment",
      "control_id": "3.12.4",
      "cmmc_id": "CA.L2-3.12.4",
      "title": "SYSTEM SECURITY PLAN",
      "sprs": 0,
      "cmmc_levels": [
        "Level 2"
      ],
      "poam_allowed": "No",
      "ao_ids": [
        "3.12.4[a]",
        "3.12.4[b]",
        "3.12.4[c]",
        "3.12.4[d]",
        "3.12.4[e]",
        "3.12.4[f]",
        "3.12.4[g]",
        "3.12.4.[h]"
      ],
      "assessment_methods": [
        {
          "type": "Examine",
          "description": "[SELECT FROM: Security planning policy; procedures addressing security plan development and implementation; procedures addressing security plan reviews and updates; enterprise architecture documentation; security plan; records of security plan reviews and updates; other relevant documents or records]."
        },
        {
          "type": "Interview",
          "description": "[SELECT FROM: Personnel with security planning and plan implementation responsibilities; personnel with information security responsibilities]."
        },
        {
          "type": "Test",
          "description": "[SELECT FROM: Organizational processes for security plan development, review, update, and approval; mechanisms supporting the security plan]."
        }
      ]
    },
    "last_ao_sentence": "system security plan is updated with the defined frequency."
  },
  {
    "text": "This is a NIST 800-171 control in the System and Communications Protection family. It corresponds to Level 1, Level 2. The control ID is SC.L1-3.13.1 with title 'BOUNDARY PROTECTION'. Security requirement: Monitor, control, and protect communications (i.e., information transmitted or received by organizational systems) at the external boundaries and key internal boundaries of organizational systems.. Assessment objective (3.13.1[a]): the external system boundary is defined.. POA&M allowed: No. SPRS score: 5.\nThis is a NIST 800-171 control in the System and Communications Protection family. It corresponds to Level 1, Level 2. The control ID is SC.L1-3.13.1 with title 'BOUNDARY PROTECTION'. Security requirement: Monitor, control, and protect communications (i.e., information transmitted or received by organizational systems) at the external boundaries and key internal boundaries of organizational systems.. Assessment objective (3.13.1[b]): key internal system boundaries are defined.. POA&M allowed: No. SPRS score: 5.\nThis is a NIST 800-171 control in the System and Communications Protection family. It corresponds to Level 1, Level 2. The control ID is SC.L1-3.13.1 with title 'BOUNDARY PROTECTION'. Security requirement: Monitor, control, and protect communications (i.e., information transmitted or received by organizational systems) at the external boundaries and key internal boundaries of organizational systems.. Assessment objective (3.13.1[c]): communications are monitored at the external system boundary.. POA&M allowed: No. SPRS score: 5.\nThis is a NIST 800-171 control in the System and Communications Protection family. It corresponds to Level 1, Level 2. The control ID is SC.L1-3.13.1 with title 'BOUNDARY PROTECTION'. Security requirement: Monitor, control, and protect communications (i.e., information transmitted or received by organizational systems) at the external boundaries and key internal boundaries of organizational systems.. Assessment objective (3.13.1[d]): communications are monitored at key internal boundaries.. POA&M allowed: No. SPRS score: 5.\nThis is a NIST 800-171 control in the System and Communications Protection family. It corresponds to Level 1, Level 2. The control ID is SC.L1-3.13.1 with title 'BOUNDARY PROTECTION'. Security requirement: Monitor, control, and protect communications (i.e., information transmitted or received by organizational systems) at the external boundaries and key internal boundaries of organizational systems.. Assessment objective (3.13.1[e]): communications are controlled at the external system boundary.. POA&M allowed: No. SPRS score: 5.\nThis is a NIST 800-171 control in the System and Communications Protection family. It corresponds to Level 1, Level 2. The control ID is SC.L1-3.13.1 with title 'BOUNDARY PROTECTION'. Security requirement: Monitor, control, and protect communications (i.e., information transmitted or received by organizational systems) at the external boundaries and key internal boundaries of organizational systems.. Assessment objective (3.13.1[f]): communications are controlled at key internal boundaries.. POA&M allowed: No. SPRS score: 5.\nThis is a NIST 800-171 control in the System and Communications Protection family. It corresponds to Level 1, Level 2. The control ID is SC.L1-3.13.1 with title 'BOUNDARY PROTECTION'. Security requirement: Monitor, control, and protect communications (i.e., information transmitted or received by organizational systems) at the external boundaries and key internal boundaries of organizational systems.. Assessment objective (3.13.1[g]): communications are protected at the external system boundary.. POA&M allowed: No. SPRS score: 5.\nThis is a NIST 800-171 control in the System and Communications Protection family. It corresponds to Level 1, Level 2. The control ID is SC.L1-3.13.1 with title 'BOUNDARY PROTECTION'. Security requirement: Monitor, control, and protect communications (i.e., information transmitted or received by organizational systems) at the external boundaries and key internal boundaries of organizational systems.. Assessment objective (3.13.1[h]): communications are protected at key internal boundaries.. POA&M allowed: No. SPRS score: 5.",
    "metadata": {
      "framework": "NIST 800-171",
      "family": "System and Communications Protection",
      "control_id": "3.13.1",
      "cmmc_id": "SC.L1-3.13.1",
      "title": "BOUNDARY PROTECTION",
      "sprs": 5,
      "cmmc_levels": [
        "Level 1",
        "Level 2"
      ],
      "poam_allowed": "No",
      "ao_ids": [
        "3.13.1[a]",
        "3.13.1[b]",
        "3.13.1[c]",
        "3.13.1[d]",
        "3.13.1[e]",
        "3.13.1[f]",
        "3.13.1[g]",
        "3.13.1[h]"
      ],
      "assessment_methods": [
        {
          "type": "Examine",
          "description": "[SELECT FROM: System and communications protection policy; procedures addressing boundary protection; security plan; list of key internal boundaries of the system; system design documentation; boundary protection hardware and software; enterprise security architecture documentation; system audit logs and records; system configuration settings and associated documentation; other relevant documents or records]."
        },
        {
          "type": "Interview",
          "description": "[SELECT FROM: System or network administrators; personnel with information security responsibilities; system developer; personnel with boundary protection responsibilities]."
        },
        {
          "type": "Test",
          "description": "[SELECT FROM: Mechanisms implementing boundary protection capability]."
        }
      ]
    },
    "last_ao_sentence": "communications are protected at key internal boundaries."
  },
  {
    "text": "This is a NIST 800-171 control in the System and Communications Protection family. It corresponds to Level 2. The control ID is SC.L2-3.13.2 with title 'SECURITY ENGINEERING'. Security requirement: Employ architectural designs, software development techniques, and systems engineering principles that promote effective information security within organizational systems.. Assessment objective (3.13.2[a]): architectural designs that promote effective information security are identified.. POA&M allowed: No. SPRS score: 5.\nThis is a NIST 800-171 control in the System and Communications Protection family. It corresponds to Level 2. The control ID is SC.L2-3.13.2 with title 'SECURITY ENGINEERING'. Security requirement: Employ architectural designs, software development techniques, and systems engineering principles that promote effective information security within organizational systems.. Assessment objective (3.13.2[b]): software development techniques that promote effective information security are identified.. POA&M allowed: No. SPRS score: 5.\nThis is a NIST 800-171 control in the System and Communications Protection family. It corresponds to Level 2. The control ID is SC.L2-3.13.2 with title 'SECURITY ENGINEERING'. Security requirement: Employ architectural designs, software development techniques, and systems engineering principles that promote effective information security within organizational systems.. Assessment objective (3.13.2[c]): systems engineering principles that promote effective information security are identified.. POA&M allowed: No. SPRS score: 5.\nThis is a NIST 800-171 control in the System and Communications Protection family. It corresponds to Level 2. The control ID is SC.L2-3.13.2 with title 'SECURITY ENGINEERING'. Security requirement: Employ architectural designs, software development techniques, and systems engineering principles that promote effective information security within organizational systems.. Assessment objective (3.13.2[d]): identified architectural designs that promote effective information security are employed.. POA&M allowed: No. SPRS score: 5.\nThis is a NIST 800-171 control in the System and Communications Protection family. It corresponds to Level 2. The control ID is SC.L2-3.13.2 with title 'SECURITY ENGINEERING'. Security requirement: Employ architectural designs, software development techniques, and systems engineering principles that promote effective information security within organizational systems.. Assessment objective (3.13.2[e]): identified software development techniques that promote effective information security are employed.. POA&M allowed: No. SPRS score: 5.\nThis is a NIST 800-171 control in the System and Communications Protection family. It corresponds to Level 2. The control ID is SC.L2-3.13.2 with title 'SECURITY ENGINEERING'. Security requirement: Employ architectural designs, software development techniques, and systems engineering principles that promote effective information security within organizational systems.. Assessment objective (3.13.2[f]): identified systems engineering principles that promote effective information security are employed.. POA&M allowed: No. SPRS score: 5.",
    "metadata": {
      "framework": "NIST 800-171",
      "family": "System and Communications Protection",
      "control_id": "3.13.2",
      "cmmc_id": "SC.L2-3.13.2",
      "title": "SECURITY ENGINEERING",
      "sprs": 5,
      "cmmc_levels": [
        "Level 2"
      ],
      "poam_allowed": "No",
      "ao_ids": [
        "3.13.2[a]",
        "3.13.2[b]",
        "3.13.2[c]",
        "3.13.2[d]",
        "3.13.2[e]",
        "3.13.2[f]"
      ],
      "assessment_methods": [
        {
          "type": "Examine",
          "description": "[SELECT FROM: Security planning policy; procedures addressing security plan development and implementation; procedures addressing security plan reviews and updates; enterprise architecture documentation; security plan; records of security plan reviews and updates; other relevant documents or records]."
        },
        {
          "type": "Interview",
          "description": "[SELECT FROM: Personnel with security planning and plan implementation responsibilities; personnel with information security responsibilities]."
        },
        {
          "type": "Test",
          "description": "[SELECT FROM: Organizational processes for security plan development, review, update, and approval; mechanisms supporting the system security plan]."
        }
      ]
    },
    "last_ao_sentence": "identified systems engineering principles that promote effective information security are employed."
  },
  {
    "text": "This is a NIST 800-171 control in the System and Communications Protection family. It corresponds to Level 2. The control ID is SC.L2-3.13.3 with title 'ROLE SEPARATION'. Security requirement: Separate user functionality from system management functionality.. Assessment objective (3.13.3[a]): user functionality is identified.. POA&M allowed: Yes. SPRS score: 1.\nThis is a NIST 800-171 control in the System and Communications Protection family. It corresponds to Level 2. The control ID is SC.L2-3.13.3 with title 'ROLE SEPARATION'. Security requirement: Separate user functionality from system management functionality.. Assessment objective (3.13.3[b]): system management functionality is identified.. POA&M allowed: Yes. SPRS score: 1.\nThis is a NIST 800-171 control in the System and Communications Protection family. It corresponds to Level 2. The control ID is SC.L2-3.13.3 with title 'ROLE SEPARATION'. Security requirement: Separate user functionality from system management functionality.. Assessment objective (3.13.3[c]): user functionality is separated from system management functionality.. POA&M allowed: Yes. SPRS score: 1.",
    "metadata": {
      "framework": "NIST 800-171",
      "family": "System and Communications Protection",
      "control_id": "3.13.3",
      "cmmc_id": "SC.L2-3.13.3",
      "title": "ROLE SEPARATION",
      "sprs": 1,
      "cmmc_levels": [
        "Level 2"
      ],
      "poam_allowed": "Yes",
      "ao_ids": [
        "3.13.3[a]",
        "3.13.3[b]",
        "3.13.3[c]"
      ],
      "assessment_methods": [
        {
          "type": "Examine",
          "description": "[SELECT FROM: System and communications protection policy; procedures addressing application partitioning; system design documentation; system configuration settings and associated documentation; security plan; system audit logs and records; other relevant documents or records]."
        },
        {
          "type": "Interview",
          "description": "[SELECT FROM: System or network administrators; personnel with information security responsibilities; system developer]."
        },
        {
          "type": "Test",
          "description": "[SELECT FROM: Separation of user functionality from system management functionality]."
        }
      ]
    },
    "last_ao_sentence": "user functionality is separated from system management functionality."
  },
  {
    "text": "This is a NIST 800-171 control in the System and Communications Protection family. It corresponds to Level 2. The control ID is SC.L2-3.13.4 with title 'SHARED RESOURCE CONTROL'. Security requirement: Prevent unauthorized and unintended information transfer via shared system resources.. Assessment objective (3.13.4): Determine if unauthorized and unintended information transfer via shared system resources is prevented.. POA&M allowed: Yes. SPRS score: 1.",
    "metadata": {
      "framework": "NIST 800-171",
      "family": "System and Communications Protection",
      "control_id": "3.13.4",
      "cmmc_id": "SC.L2-3.13.4",
      "title": "SHARED RESOURCE CONTROL",
      "sprs": 1,
      "cmmc_levels": [
        "Level 2"
      ],
      "poam_allowed": "Yes",
      "ao_ids": [
        "3.13.4"
      ],
      "assessment_methods": [
        {
          "type": "Examine",
          "description": "[SELECT FROM: System and communications protection policy; procedures addressing application partitioning; security plan; system design documentation; system configuration settings and associated documentation; system audit logs and records; other relevant documents or records]."
        },
        {
          "type": "Interview",
          "description": "[SELECT FROM: System or network administrators; personnel with information security responsibilities; system developer]."
        },
        {
          "type": "Test",
          "description": "[SELECT FROM: Separation of user functionality from system management functionality]."
        }
      ]
    },
    "last_ao_sentence": "Determine if unauthorized and unintended information transfer via shared system resources is prevented."
  },
  {
    "text": "This is a NIST 800-171 control in the System and Communications Protection family. It corresponds to Level 1, Level 2. The control ID is SC.L1-3.13.5 with title 'PUBLIC-ACCESS SYSTEM SEPARATION'. Security requirement: Implement subnetworks for publicly accessible system components that are physically or logically separated from internal networks.. Assessment objective (3.13.5[a]): publicly accessible system components are identified.. POA&M allowed: No. SPRS score: 5.\nThis is a NIST 800-171 control in the System and Communications Protection family. It corresponds to Level 1, Level 2. The control ID is SC.L1-3.13.5 with title 'PUBLIC-ACCESS SYSTEM SEPARATION'. Security requirement: Implement subnetworks for publicly accessible system components that are physically or logically separated from internal networks.. Assessment objective (3.13.5[b]): subnetworks for publicly accessible system components are physically or logically separated from internal networks.. POA&M allowed: No. SPRS score: 5.",
    "metadata": {
      "framework": "NIST 800-171",
      "family": "System and Communications Protection",
      "control_id": "3.13.5",
      "cmmc_id": "SC.L1-3.13.5",
      "title": "PUBLIC-ACCESS SYSTEM SEPARATION",
      "sprs": 5,
      "cmmc_levels": [
        "Level 1",
        "Level 2"
      ],
      "poam_allowed": "No",
      "ao_ids": [
        "3.13.5[a]",
        "3.13.5[b]"
      ],
      "assessment_methods": [
        {
          "type": "Examine",
          "description": "[SELECT FROM: System and communications protection policy; procedures addressing boundary protection; security plan; list of key internal boundaries of the system; system design documentation; boundary protection hardware and software; system configuration settings and associated documentation; enterprise security architecture documentation; system audit logs and records; other relevant documents or records]."
        },
        {
          "type": "Interview",
          "description": "[SELECT FROM: System or network administrators; personnel with information security responsibilities; system developer; personnel with boundary protection responsibilities]."
        },
        {
          "type": "Test",
          "description": "[SELECT FROM: Mechanisms implementing boundary protection capability]."
        }
      ]
    },
    "last_ao_sentence": "subnetworks for publicly accessible system components are physically or logically separated from internal networks."
  },
  {
    "text": "This is a NIST 800-171 control in the System and Communications Protection family. It corresponds to Level 2. The control ID is SC.L2-3.13.6 with title 'NETWORK COMMUNICATION BY EXCEPTION'. Security requirement: Deny network communications traffic by default and allow network communications traffic by exception (i.e., deny all, permit by exception).. Assessment objective (3.13.6[a]): network communications traffic is denied by default.. POA&M allowed: No. SPRS score: 5.\nThis is a NIST 800-171 control in the System and Communications Protection family. It corresponds to Level 2. The control ID is SC.L2-3.13.6 with title 'NETWORK COMMUNICATION BY EXCEPTION'. Security requirement: Deny network communications traffic by default and allow network communications traffic by exception (i.e., deny all, permit by exception).. Assessment objective (3.13.6[b]): network communications traffic is allowed by exception.. POA&M allowed: No. SPRS score: 5.",
    "metadata": {
      "framework": "NIST 800-171",
      "family": "System and Communications Protection",
      "control_id": "3.13.6",
      "cmmc_id": "SC.L2-3.13.6",
      "title": "NETWORK COMMUNICATION BY EXCEPTION",
      "sprs": 5,
      "cmmc_levels": [
        "Level 2"
      ],
      "poam_allowed": "No",
      "ao_ids": [
        "3.13.6[a]",
        "3.13.6[b]"
      ],
      "assessment_methods": [
        {
          "type": "Examine",
          "description": "[SELECT FROM: System and communications protection policy; procedures addressing boundary protection; security plan; system design documentation; system configuration settings and associated documentation; system audit logs and records; other relevant documents or records]."
        },
        {
          "type": "Interview",
          "description": "[SELECT FROM: System or network administrators; personnel with information security responsibilities; system developer; personnel with boundary protection responsibilities]."
        },
        {
          "type": "Test",
          "description": "[SELECT FROM: Mechanisms implementing traffic management at managed interfaces]."
        }
      ]
    },
    "last_ao_sentence": "network communications traffic is allowed by exception."
  },
  {
    "text": "This is a NIST 800-171 control in the System and Communications Protection family. It corresponds to Level 2. The control ID is SC.L2-3.13.7 with title 'SPLIT TUNNELING'. Security requirement: Prevent remote devices from simultaneously establishing non-remote connections with organizational systems and communicating via some other connection to resources in external networks (i.e., split tunneling).. Assessment objective (3.13.7): Determine if remote devices are prevented from simultaneously establishing non-remote connections with the system and communicating via some other connection to resources in external networks (i.e., split tunneling).. POA&M allowed: Yes. SPRS score: 1.",
    "metadata": {
      "framework": "NIST 800-171",
      "family": "System and Communications Protection",
      "control_id": "3.13.7",
      "cmmc_id": "SC.L2-3.13.7",
      "title": "SPLIT TUNNELING",
      "sprs": 1,
      "cmmc_levels": [
        "Level 2"
      ],
      "poam_allowed": "Yes",
      "ao_ids": [
        "3.13.7"
      ],
      "assessment_methods": [
        {
          "type": "Examine",
          "description": "[SELECT FROM: System and communications protection policy; procedures addressing boundary protection; security plan; system design documentation; system hardware and software; system architecture; system configuration settings and associated documentation; system audit logs and records; other relevant documents or records]."
        },
        {
          "type": "Interview",
          "description": "[SELECT FROM: System or network administrators; personnel with information security responsibilities; system developer; personnel with boundary protection responsibilities]."
        },
        {
          "type": "Test",
          "description": "[SELECT FROM: Mechanisms implementing boundary protection capability; mechanisms supporting or restricting non-remote connections]."
        }
      ]
    },
    "last_ao_sentence": "Determine if remote devices are prevented from simultaneously establishing non-remote connections with the system and communicating via some other connection to resources in external networks (i.e., split tunneling)."
  },
  {
    "text": "This is a NIST 800-171 control in the System and Communications Protection family. It corresponds to Level 2. The control ID is SC.L2-3.13.8 with title 'DATA IN TRANSIT'. Security requirement: Implement cryptographic mechanisms to prevent unauthorized disclosure of CUI during transmission unless otherwise protected by alternative physical safeguards.. Assessment objective (3.13.8[a]): cryptographic mechanisms intended to prevent unauthorized disclosure of CUI are identified.. POA&M allowed: No. SPRS score: 3.\nThis is a NIST 800-171 control in the System and Communications Protection family. It corresponds to Level 2. The control ID is SC.L2-3.13.8 with title 'DATA IN TRANSIT'. Security requirement: Implement cryptographic mechanisms to prevent unauthorized disclosure of CUI during transmission unless otherwise protected by alternative physical safeguards.. Assessment objective (3.13.8[b]): alternative physical safeguards intended to prevent unauthorized disclosure of CUI are identified.. POA&M allowed: No. SPRS score: 3.\nThis is a NIST 800-171 control in the System and Communications Protection family. It corresponds to Level 2. The control ID is SC.L2-3.13.8 with title 'DATA IN TRANSIT'. Security requirement: Implement cryptographic mechanisms to prevent unauthorized disclosure of CUI during transmission unless otherwise protected by alternative physical safeguards.. Assessment objective (3.13.8[c]): either cryptographic mechanisms or alternative physical safeguards are implemented to prevent unauthorized disclosure of CUI during transmission.. POA&M allowed: No. SPRS score: 3.",
    "metadata": {
      "framework": "NIST 800-171",
      "family": "System and Communications Protection",
      "control_id": "3.13.8",
      "cmmc_id": "SC.L2-3.13.8",
      "title": "DATA IN TRANSIT",
      "sprs": 3,
      "cmmc_levels": [
        "Level 2"
      ],
      "poam_allowed": "No",
      "ao_ids": [
        "3.13.8[a]",
        "3.13.8[b]",
        "3.13.8[c]"
      ],
      "assessment_methods": [
        {
          "type": "Examine",
          "description": "[SELECT FROM: System and communications protection policy; procedures addressing transmission confidentiality and integrity; security plan; system design documentation; system configuration settings and associated documentation; system audit logs and records; other relevant documents or records]."
        },
        {
          "type": "Interview",
          "description": "[SELECT FROM: System or network administrators; personnel with information security responsibilities; system developer]."
        },
        {
          "type": "Test",
          "description": "[SELECT FROM: Cryptographic mechanisms or mechanisms supporting or implementing transmission confidentiality; organizational processes for defining and implementing alternative physical safeguards]."
        }
      ]
    },
    "last_ao_sentence": "either cryptographic mechanisms or alternative physical safeguards are implemented to prevent unauthorized disclosure of CUI during transmission."
  },
  {
    "text": "This is a NIST 800-171 control in the System and Communications Protection family. It corresponds to Level 2. The control ID is SC.L2-3.13.9 with title 'CONNECTIONS TERMINATION'. Security requirement: Terminate network connections associated with communications sessions at the end of the sessions or after a defined period of inactivity.. Assessment objective (3.13.9[a]): a period of inactivity to terminate network connections associated with communications sessions is defined.. POA&M allowed: Yes. SPRS score: 1.\nThis is a NIST 800-171 control in the System and Communications Protection family. It corresponds to Level 2. The control ID is SC.L2-3.13.9 with title 'CONNECTIONS TERMINATION'. Security requirement: Terminate network connections associated with communications sessions at the end of the sessions or after a defined period of inactivity.. Assessment objective (3.13.9[b]): network connections associated with communications sessions are terminated at the end of the sessions.. POA&M allowed: Yes. SPRS score: 1.\nThis is a NIST 800-171 control in the System and Communications Protection family. It corresponds to Level 2. The control ID is SC.L2-3.13.9 with title 'CONNECTIONS TERMINATION'. Security requirement: Terminate network connections associated with communications sessions at the end of the sessions or after a defined period of inactivity.. Assessment objective (3.13.9[c]): network connections associated with communications sessions are terminated after the defined period of inactivity.. POA&M allowed: Yes. SPRS score: 1.",
    "metadata": {
      "framework": "NIST 800-171",
      "family": "System and Communications Protection",
      "control_id": "3.13.9",
      "cmmc_id": "SC.L2-3.13.9",
      "title": "CONNECTIONS TERMINATION",
      "sprs": 1,
      "cmmc_levels": [
        "Level 2"
      ],
      "poam_allowed": "Yes",
      "ao_ids": [
        "3.13.9[a]",
        "3.13.9[b]",
        "3.13.9[c]"
      ],
      "assessment_methods": [
        {
          "type": "Examine",
          "description": "[SELECT FROM: System and communications protection policy; procedures addressing network disconnect; system design documentation; security plan; system configuration settings and associated documentation; system audit logs and records; other relevant documents or records]."
        },
        {
          "type": "Interview",
          "description": "[SELECT FROM: System or network administrators; personnel with information security responsibilities; system developer]."
        },
        {
          "type": "Test",
          "description": "[SELECT FROM: Mechanisms supporting or implementing network disconnect capability]."
        }
      ]
    },
    "last_ao_sentence": "network connections associated with communications sessions are terminated after the defined period of inactivity."
  },
  {
    "text": "This is a NIST 800-171 control in the System and Communications Protection family. It corresponds to Level 2. The control ID is SC.L2-3.13.10 with title 'KEY MANAGEMENT'. Security requirement: Establish and manage cryptographic keys for cryptography employed in organizational systems.. Assessment objective (3.13.10[a]): cryptographic keys are established whenever cryptography is employed.. POA&M allowed: Yes. SPRS score: 1.\nThis is a NIST 800-171 control in the System and Communications Protection family. It corresponds to Level 2. The control ID is SC.L2-3.13.10 with title 'KEY MANAGEMENT'. Security requirement: Establish and manage cryptographic keys for cryptography employed in organizational systems.. Assessment objective (3.13.10[b]): cryptographic keys are managed whenever cryptography is employed.. POA&M allowed: Yes. SPRS score: 1.",
    "metadata": {
      "framework": "NIST 800-171",
      "family": "System and Communications Protection",
      "control_id": "3.13.10",
      "cmmc_id": "SC.L2-3.13.10",
      "title": "KEY MANAGEMENT",
      "sprs": 1,
      "cmmc_levels": [
        "Level 2"
      ],
      "poam_allowed": "Yes",
      "ao_ids": [
        "3.13.10[a]",
        "3.13.10[b]"
      ],
      "assessment_methods": [
        {
          "type": "Examine",
          "description": "[SELECT FROM: System and communications protection policy; procedures addressing cryptographic key establishment and management; security plan; system design documentation; cryptographic mechanisms; system configuration settings and associated documentation; system audit logs and records; other relevant documents or records]."
        },
        {
          "type": "Interview",
          "description": "[SELECT FROM: System or network administrators; personnel with information security responsibilities; personnel with responsibilities for cryptographic key establishment and management]."
        },
        {
          "type": "Test",
          "description": "[SELECT FROM: Mechanisms supporting or implementing cryptographic key establishment and management]."
        }
      ]
    },
    "last_ao_sentence": "cryptographic keys are managed whenever cryptography is employed."
  },
  {
    "text": "This is a NIST 800-171 control in the System and Communications Protection family. It corresponds to Level 2. The control ID is SC.L2-3.13.11 with title 'CUI ENCRYPTION'. Security requirement: Employ FIPS-validated cryptography when used to protect the confidentiality of CUI.. Assessment objective (3.13.11): Determine if FIPS-validated cryptography is employed to protect the confidentiality of CUI.. POA&M allowed: Yes. SPRS score: 5.",
    "metadata": {
      "framework": "NIST 800-171",
      "family": "System and Communications Protection",
      "control_id": "3.13.11",
      "cmmc_id": "SC.L2-3.13.11",
      "title": "CUI ENCRYPTION",
      "sprs": 5,
      "cmmc_levels": [
        "Level 2"
      ],
      "poam_allowed": "Yes",
      "ao_ids": [
        "3.13.11"
      ],
      "assessment_methods": [
        {
          "type": "Examine",
          "description": "[SELECT FROM: System and communications protection policy; procedures addressing cryptographic protection; security plan; system design documentation; system configuration settings and associated documentation; cryptographic module validation certificates; list of FIPS-validated cryptographic modules; system audit logs and records; other relevant documents or records]."
        },
        {
          "type": "Interview",
          "description": "[SELECT FROM: System or network administrators; personnel with information security responsibilities; system developer; personnel with responsibilities for cryptographic protection]."
        },
        {
          "type": "Test",
          "description": "[SELECT FROM: Mechanisms supporting or implementing cryptographic protection]."
        }
      ]
    },
    "last_ao_sentence": "Determine if FIPS-validated cryptography is employed to protect the confidentiality of CUI."
  },
  {
    "text": "This is a NIST 800-171 control in the System and Communications Protection family. It corresponds to Level 2. The control ID is SC.L2-3.13.12 with title 'COLLABORATIVE DEVICE CONTROL'. Security requirement: Employ FIPS-validated cryptography when used to protect the confidentiality of CUI.. Assessment objective (3.13.12[a]): collaborative computing devices are identified.. POA&M allowed: Yes. SPRS score: 1.\nThis is a NIST 800-171 control in the System and Communications Protection family. It corresponds to Level 2. The control ID is SC.L2-3.13.12 with title 'COLLABORATIVE DEVICE CONTROL'. Security requirement: Employ FIPS-validated cryptography when used to protect the confidentiality of CUI.. Assessment objective (3.13.12[b]): collaborative computing devices provide indication to users of devices in use.. POA&M allowed: Yes. SPRS score: 1.\nThis is a NIST 800-171 control in the System and Communications Protection family. It corresponds to Level 2. The control ID is SC.L2-3.13.12 with title 'COLLABORATIVE DEVICE CONTROL'. Security requirement: Employ FIPS-validated cryptography when used to protect the confidentiality of CUI.. Assessment objective (3.13.12[c]): remote activation of collaborative computing devices is prohibited.. POA&M allowed: Yes. SPRS score: 1.",
    "metadata": {
      "framework": "NIST 800-171",
      "family": "System and Communications Protection",
      "control_id": "3.13.12",
      "cmmc_id": "SC.L2-3.13.12",
      "title": "COLLABORATIVE DEVICE CONTROL",
      "sprs": 1,
      "cmmc_levels": [
        "Level 2"
      ],
      "poam_allowed": "Yes",
      "ao_ids": [
        "3.13.12[a]",
        "3.13.12[b]",
        "3.13.12[c]"
      ],
      "assessment_methods": [
        {
          "type": "Examine",
          "description": "[SELECT FROM: System and communications protection policy; procedures addressing collaborative computing; access control policy and procedures; security plan; system design documentation; system configuration settings and associated documentation; system audit logs and records; other relevant documents or records]."
        },
        {
          "type": "Interview",
          "description": "[SELECT FROM: System or network administrators; personnel with information security responsibilities; system developer; personnel with responsibilities for managing collaborative computing devices]."
        },
        {
          "type": "Test",
          "description": "[SELECT FROM: Mechanisms supporting or implementing management of remote activation of collaborative computing devices; mechanisms providing an indication of use of collaborative computing devices]."
        }
      ]
    },
    "last_ao_sentence": "remote activation of collaborative computing devices is prohibited."
  },
  {
    "text": "This is a NIST 800-171 control in the System and Communications Protection family. It corresponds to Level 2. The control ID is SC.L2-3.13.13 with title 'MOBILE CODE'. Security requirement: Control and monitor the use of mobile code.. Assessment objective (3.13.13[a]): use of mobile code is controlled.. POA&M allowed: Yes. SPRS score: 1.\nThis is a NIST 800-171 control in the System and Communications Protection family. It corresponds to Level 2. The control ID is SC.L2-3.13.13 with title 'MOBILE CODE'. Security requirement: Control and monitor the use of mobile code.. Assessment objective (3.13.13[b]): use of mobile code is monitored.. POA&M allowed: Yes. SPRS score: 1.",
    "metadata": {
      "framework": "NIST 800-171",
      "family": "System and Communications Protection",
      "control_id": "3.13.13",
      "cmmc_id": "SC.L2-3.13.13",
      "title": "MOBILE CODE",
      "sprs": 1,
      "cmmc_levels": [
        "Level 2"
      ],
      "poam_allowed": "Yes",
      "ao_ids": [
        "3.13.13[a]",
        "3.13.13[b]"
      ],
      "assessment_methods": [
        {
          "type": "Examine",
          "description": "[SELECT FROM: System and communications protection policy; procedures addressing mobile code; mobile code usage restrictions, mobile code implementation policy and procedures; security plan; list of acceptable mobile code and mobile code technologies; list of unacceptable mobile code and mobile technologies; authorization records; system monitoring records; system audit logs and records; other relevant documents or records]."
        },
        {
          "type": "Interview",
          "description": "[SELECT FROM: System or network administrators; personnel with information security responsibilities; personnel with responsibilities for managing mobile code]."
        },
        {
          "type": "Test",
          "description": "[SELECT FROM: Organizational process for controlling, authorizing, monitoring, and restricting mobile code; mechanisms supporting or implementing the management of mobile code; mechanisms supporting or implementing the monitoring of mobile code]."
        }
      ]
    },
    "last_ao_sentence": "use of mobile code is monitored."
  },
  {
    "text": "This is a NIST 800-171 control in the System and Communications Protection family. It corresponds to Level 2. The control ID is SC.L2-3.13.14 with title 'VOICE OVER INTERNET PROTOCOL'. Security requirement: Control and monitor the use of Voice over Internet Protocol (VoIP) technologies. Assessment objective (3.13.14[a]): use of Voice over Internet Protocol (VoIP) technologies is controlled.. POA&M allowed: Yes. SPRS score: 1.\nThis is a NIST 800-171 control in the System and Communications Protection family. It corresponds to Level 2. The control ID is SC.L2-3.13.14 with title 'VOICE OVER INTERNET PROTOCOL'. Security requirement: Control and monitor the use of Voice over Internet Protocol (VoIP) technologies. Assessment objective (3.13.14[b]): use of Voice over Internet Protocol (VoIP) technologies is monitored.. POA&M allowed: Yes. SPRS score: 1.",
    "metadata": {
      "framework": "NIST 800-171",
      "family": "System and Communications Protection",
      "control_id": "3.13.14",
      "cmmc_id": "SC.L2-3.13.14",
      "title": "VOICE OVER INTERNET PROTOCOL",
      "sprs": 1,
      "cmmc_levels": [
        "Level 2"
      ],
      "poam_allowed": "Yes",
      "ao_ids": [
        "3.13.14[a]",
        "3.13.14[b]"
      ],
      "assessment_methods": [
        {
          "type": "Examine",
          "description": "[SELECT FROM: System and communications protection policy; procedures addressing VoIP; VoIP usage restrictions; VoIP implementation guidance; security plan; system design documentation; system configuration settings and associated documentation; system monitoring records; system audit logs and records; other relevant documents or records]."
        },
        {
          "type": "Interview",
          "description": "[SELECT FROM: System or network administrators; personnel with information security responsibilities; personnel with responsibilities for managing VoIP]."
        },
        {
          "type": "Test",
          "description": "[SELECT FROM: Organizational process for authorizing, monitoring, and controlling VoIP; mechanisms supporting or implementing authorizing, monitoring, and controlling VoIP]."
        }
      ]
    },
    "last_ao_sentence": "use of Voice over Internet Protocol (VoIP) technologies is monitored."
  },
  {
    "text": "This is a NIST 800-171 control in the System and Communications Protection family. It corresponds to Level 2. The control ID is SC.L2-3.13.15 with title 'COMMUNICATIONS AUTHENTICITY'. Security requirement: Protect the authenticity of communications sessions. Assessment objective (3.13.15): Determine if the authenticity of communications sessions is protected.. POA&M allowed: No. SPRS score: 5.",
    "metadata": {
      "framework": "NIST 800-171",
      "family": "System and Communications Protection",
      "control_id": "3.13.15",
      "cmmc_id": "SC.L2-3.13.15",
      "title": "COMMUNICATIONS AUTHENTICITY",
      "sprs": 5,
      "cmmc_levels": [
        "Level 2"
      ],
      "poam_allowed": "No",
      "ao_ids": [
        "3.13.15"
      ],
      "assessment_methods": [
        {
          "type": "Examine",
          "description": "[SELECT FROM: System and communications protection policy; procedures addressing session authenticity; security plan; system design documentation; system configuration settings and associated documentation; system audit logs and records; other relevant documents or records]."
        },
        {
          "type": "Interview",
          "description": "[SELECT FROM: System or network administrators; personnel with information security responsibilities]."
        },
        {
          "type": "Test",
          "description": "[SELECT FROM: Mechanisms supporting or implementing session authenticity]."
        }
      ]
    },
    "last_ao_sentence": "Determine if the authenticity of communications sessions is protected."
  },
  {
    "text": "This is a NIST 800-171 control in the System and Communications Protection family. It corresponds to Level 2. The control ID is SC.L2-3.13.16 with title 'DATA AT REST'. Security requirement: Protect the confidentiality of CUI at rest.. Assessment objective (3.13.16): Determine if the confidentiality of CUI at rest is protected.. POA&M allowed: Yes. SPRS score: 1.",
    "metadata": {
      "framework": "NIST 800-171",
      "family": "System and Communications Protection",
      "control_id": "3.13.16",
      "cmmc_id": "SC.L2-3.13.16",
      "title": "DATA AT REST",
      "sprs": 1,
      "cmmc_levels": [
        "Level 2"
      ],
      "poam_allowed": "Yes",
      "ao_ids": [
        "3.13.16"
      ],
      "assessment_methods": [
        {
          "type": "Examine",
          "description": "[SELECT FROM: System and communications protection policy; procedures addressing protection of information at rest; security plan; system design documentation; list of information at rest requiring confidentiality protections; system configuration settings and associated documentation; cryptographic mechanisms and associated configuration documentation; other relevant documents or records]."
        },
        {
          "type": "Interview",
          "description": "[SELECT FROM: System or network administrators; personnel with information security responsibilities; system developer]."
        },
        {
          "type": "Test",
          "description": "[SELECT FROM: Mechanisms supporting or implementing confidentiality protections for information at rest]."
        }
      ]
    },
    "last_ao_sentence": "Determine if the confidentiality of CUI at rest is protected."
  },
  {
    "text": "This is a NIST 800-171 control in the System and Information Integrity family. It corresponds to Level 1, Level 2. The control ID is SI.L1-3.14.1 with title 'FLAW REMEDIATION'. Security requirement: Identify, report, and correct system flaws in a timely manner.. Assessment objective (3.14.1[a]): the time within which to identify system flaws is specified.. POA&M allowed: No. SPRS score: 5.\nThis is a NIST 800-171 control in the System and Information Integrity family. It corresponds to Level 1, Level 2. The control ID is SI.L1-3.14.1 with title 'FLAW REMEDIATION'. Security requirement: Identify, report, and correct system flaws in a timely manner.. Assessment objective (3.14.1[b]): system flaws are identified within the specified time frame.. POA&M allowed: No. SPRS score: 5.\nThis is a NIST 800-171 control in the System and Information Integrity family. It corresponds to Level 1, Level 2. The control ID is SI.L1-3.14.1 with title 'FLAW REMEDIATION'. Security requirement: Identify, report, and correct system flaws in a timely manner.. Assessment objective (3.14.1[c]): the time within which to report system flaws is specified.. POA&M allowed: No. SPRS score: 5.\nThis is a NIST 800-171 control in the System and Information Integrity family. It corresponds to Level 1, Level 2. The control ID is SI.L1-3.14.1 with title 'FLAW REMEDIATION'. Security requirement: Identify, report, and correct system flaws in a timely manner.. Assessment objective (3.14.1[d]): system flaws are reported within the specified time frame.. POA&M allowed: No. SPRS score: 5.\nThis is a NIST 800-171 control in the System and Information Integrity family. It corresponds to Level 1, Level 2. The control ID is SI.L1-3.14.1 with title 'FLAW REMEDIATION'. Security requirement: Identify, report, and correct system flaws in a timely manner.. Assessment objective (3.14.1[e]): the time within which to correct system flaws is specified.. POA&M allowed: No. SPRS score: 5.\nThis is a NIST 800-171 control in the System and Information Integrity family. It corresponds to Level 1, Level 2. The control ID is SI.L1-3.14.1 with title 'FLAW REMEDIATION'. Security requirement: Identify, report, and correct system flaws in a timely manner.. Assessment objective (3.14.1[f]): system flaws are corrected within the specified time frame.. POA&M allowed: No. SPRS score: 5.",
    "metadata": {
      "framework": "NIST 800-171",
      "family": "System and Information Integrity",
      "control_id": "3.14.1",
      "cmmc_id": "SI.L1-3.14.1",
      "title": "FLAW REMEDIATION",
      "sprs": 5,
      "cmmc_levels": [
        "Level 1",
        "Level 2"
      ],
      "poam_allowed": "No",
      "ao_ids": [
        "3.14.1[a]",
        "3.14.1[b]",
        "3.14.1[c]",
        "3.14.1[d]",
        "3.14.1[e]",
        "3.14.1[f]"
      ],
      "assessment_methods": [
        {
          "type": "Examine",
          "description": "[SELECT FROM: System and information integrity policy; procedures addressing flaw remediation; procedures addressing configuration management; security plan; list of flaws and vulnerabilities potentially affecting the system; list of recent security flaw remediation actions performed on the system (e.g., list of installed patches, service packs, hot fixes, and other software updates to correct system flaws); test results from the installation of software and firmware updates to correct system flaws; installation/change control records for security-relevant software and firmware updates; other relevant documents or records]."
        },
        {
          "type": "Interview",
          "description": "[SELECT FROM: System or network administrators; personnel with information security responsibilities; personnel installing, configuring, and maintaining the system; personnel with responsibility for flaw remediation; personnel with configuration management responsibility]."
        },
        {
          "type": "Test",
          "description": "[SELECT FROM: Organizational processes for identifying, reporting, and correcting system flaws; organizational process for installing software and firmware updates; mechanisms supporting or implementing reporting, and correcting system flaws; mechanisms supporting or implementing testing software and firmware updates]."
        }
      ]
    },
    "last_ao_sentence": "system flaws are corrected within the specified time frame."
  },
  {
    "text": "This is a NIST 800-171 control in the System and Information Integrity family. It corresponds to Level 1, Level 2. The control ID is SI.L1-3.14.2 with title 'MALICIOUS CODE PROTECTION'. Security requirement: Provide protection from malicious code at designated locations within organizational systems.. Assessment objective (3.14.2[a]): designated locations for malicious code protection are identified.. POA&M allowed: No. SPRS score: 5.\nThis is a NIST 800-171 control in the System and Information Integrity family. It corresponds to Level 1, Level 2. The control ID is SI.L1-3.14.2 with title 'MALICIOUS CODE PROTECTION'. Security requirement: Provide protection from malicious code at designated locations within organizational systems.. Assessment objective (3.14.2[b]): protection from malicious code at designated locations is provided.. POA&M allowed: No. SPRS score: 5.",
    "metadata": {
      "framework": "NIST 800-171",
      "family": "System and Information Integrity",
      "control_id": "3.14.2",
      "cmmc_id": "SI.L1-3.14.2",
      "title": "MALICIOUS CODE PROTECTION",
      "sprs": 5,
      "cmmc_levels": [
        "Level 1",
        "Level 2"
      ],
      "poam_allowed": "No",
      "ao_ids": [
        "3.14.2[a]",
        "3.14.2[b]"
      ],
      "assessment_methods": [
        {
          "type": "Examine",
          "description": "[SELECT FROM: System and information integrity policy; configuration management policy and procedures; procedures addressing malicious code protection; records of malicious code protection updates; malicious code protection mechanisms; security plan; system design documentation; system configuration settings and associated documentation; record of actions initiated by malicious code protection mechanisms in response to malicious code detection; scan results from malicious code protection mechanisms; system audit logs and records; other relevant documents or records]."
        },
        {
          "type": "Interview",
          "description": "[SELECT FROM: System or network administrators; personnel with information security responsibilities; personnel installing, configuring, and maintaining the system; personnel with responsibility for malicious code protection; personnel with configuration management responsibility]."
        },
        {
          "type": "Test",
          "description": "[SELECT FROM: Organizational processes for employing, updating, and configuring malicious code protection mechanisms; organizational process for addressing false positives and resulting potential impact; mechanisms supporting or implementing employing, updating, and configuring malicious code protection mechanisms; mechanisms supporting or implementing malicious code scanning and subsequent actions]."
        }
      ]
    },
    "last_ao_sentence": "protection from malicious code at designated locations is provided."
  },
  {
    "text": "This is a NIST 800-171 control in the System and Information Integrity family. It corresponds to Level 2. The control ID is SI.L2-3.14.3 with title 'SECURITY ALERTS & ADVISORIES'. Security requirement: Monitor system security alerts and advisories and take action in response.. Assessment objective (3.14.3[a]): response actions to system security alerts and advisories are identified.. POA&M allowed: No. SPRS score: 5.\nThis is a NIST 800-171 control in the System and Information Integrity family. It corresponds to Level 2. The control ID is SI.L2-3.14.3 with title 'SECURITY ALERTS & ADVISORIES'. Security requirement: Monitor system security alerts and advisories and take action in response.. Assessment objective (3.14.3[b]): system security alerts and advisories are monitored.. POA&M allowed: No. SPRS score: 5.\nThis is a NIST 800-171 control in the System and Information Integrity family. It corresponds to Level 2. The control ID is SI.L2-3.14.3 with title 'SECURITY ALERTS & ADVISORIES'. Security requirement: Monitor system security alerts and advisories and take action in response.. Assessment objective (3.14.3[c]): actions in response to system security alerts and advisories are taken.. POA&M allowed: No. SPRS score: 5.",
    "metadata": {
      "framework": "NIST 800-171",
      "family": "System and Information Integrity",
      "control_id": "3.14.3",
      "cmmc_id": "SI.L2-3.14.3",
      "title": "SECURITY ALERTS & ADVISORIES",
      "sprs": 5,
      "cmmc_levels": [
        "Level 2"
      ],
      "poam_allowed": "No",
      "ao_ids": [
        "3.14.3[a]",
        "3.14.3[b]",
        "3.14.3[c]"
      ],
      "assessment_methods": [
        {
          "type": "Examine",
          "description": "[SELECT FROM: System and information integrity policy; procedures addressing security alerts, advisories, and directives; security plan; records of security alerts and advisories; other relevant documents or records]."
        },
        {
          "type": "Interview",
          "description": "[SELECT FROM: Personnel with security alert and advisory responsibilities; personnel implementing, operating, maintaining, and using the system; personnel, organizational elements, and external organizations to whom alerts, advisories, and directives are to be disseminated; system or network administrators; personnel with information security responsibilities]."
        },
        {
          "type": "Test",
          "description": "[SELECT FROM: Organizational processes for defining, receiving, generating, disseminating, and complying with security alerts, advisories, and directives; mechanisms supporting or implementing definition, receipt, generation, and dissemination of security alerts, advisories, and directives; mechanisms supporting or implementing security directives]."
        }
      ]
    },
    "last_ao_sentence": "actions in response to system security alerts and advisories are taken."
  },
  {
    "text": "This is a NIST 800-171 control in the System and Information Integrity family. It corresponds to Level 1, Level 2. The control ID is SI.L1-3.14.4 with title 'UPDATE MALICIOUS CODE PROTECTION'. Security requirement: Update malicious code protection mechanisms when new releases are available.. Assessment objective (3.14.4): Determine if malicious code protection mechanisms are updated when new releases are available.. POA&M allowed: No. SPRS score: 5.",
    "metadata": {
      "framework": "NIST 800-171",
      "family": "System and Information Integrity",
      "control_id": "3.14.4",
      "cmmc_id": "SI.L1-3.14.4",
      "title": "UPDATE MALICIOUS CODE PROTECTION",
      "sprs": 5,
      "cmmc_levels": [
        "Level 1",
        "Level 2"
      ],
      "poam_allowed": "No",
      "ao_ids": [
        "3.14.4"
      ],
      "assessment_methods": [
        {
          "type": "Examine",
          "description": "[SELECT FROM: System and information integrity policy; configuration management policy and procedures; procedures addressing malicious code protection; malicious code protection mechanisms; records of malicious code protection updates; security plan; system design documentation; system configuration settings and associated documentation; scan results from malicious code protection mechanisms; record of actions initiated by malicious code protection mechanisms in response to malicious code detection; system audit logs and records; other relevant documents or records]."
        },
        {
          "type": "Interview",
          "description": "[SELECT FROM: System or network administrators; personnel with information security responsibilities; personnel installing, configuring, and maintaining the system; personnel with responsibility for malicious code protection; personnel with configuration management responsibility]."
        },
        {
          "type": "Test",
          "description": "[SELECT FROM: Organizational processes for employing, updating, and configuring malicious code protection mechanisms; organizational process for addressing false positives and resulting potential impact; mechanisms supporting or implementing malicious code protection mechanisms (including updates and configurations); mechanisms supporting or implementing malicious code scanning and subsequent actions]."
        }
      ]
    },
    "last_ao_sentence": "Determine if malicious code protection mechanisms are updated when new releases are available."
  },
  {
    "text": "This is a NIST 800-171 control in the System and Information Integrity family. It corresponds to Level 1, Level 2. The control ID is SI.L1-3.14.5 with title 'SYSTEM & FILE SCANNING'. Security requirement: Perform periodic scans of organizational systems and real-time scans of files from external sources as files are downloaded, opened, or executed.. Assessment objective (3.14.5[a]): the frequency for malicious code scans is defined.. POA&M allowed: No. SPRS score: 5.\nThis is a NIST 800-171 control in the System and Information Integrity family. It corresponds to Level 1, Level 2. The control ID is SI.L1-3.14.5 with title 'SYSTEM & FILE SCANNING'. Security requirement: Perform periodic scans of organizational systems and real-time scans of files from external sources as files are downloaded, opened, or executed.. Assessment objective (3.14.5[b]): malicious code scans are performed with the defined frequency.. POA&M allowed: No. SPRS score: 5.\nThis is a NIST 800-171 control in the System and Information Integrity family. It corresponds to Level 1, Level 2. The control ID is SI.L1-3.14.5 with title 'SYSTEM & FILE SCANNING'. Security requirement: Perform periodic scans of organizational systems and real-time scans of files from external sources as files are downloaded, opened, or executed.. Assessment objective (3.14.5[c]): real-time malicious code scans of files from external sources as files are downloaded, opened, or executed are performed.. POA&M allowed: No. SPRS score: 5.",
    "metadata": {
      "framework": "NIST 800-171",
      "family": "System and Information Integrity",
      "control_id": "3.14.5",
      "cmmc_id": "SI.L1-3.14.5",
      "title": "SYSTEM & FILE SCANNING",
      "sprs": 5,
      "cmmc_levels": [
        "Level 1",
        "Level 2"
      ],
      "poam_allowed": "No",
      "ao_ids": [
        "3.14.5[a]",
        "3.14.5[b]",
        "3.14.5[c]"
      ],
      "assessment_methods": [
        {
          "type": "Examine",
          "description": "[SELECT FROM: System and information integrity policy; configuration management policy and procedures; procedures addressing malicious code protection; malicious code protection mechanisms; records of malicious code protection updates; security plan; system design documentation; system configuration settings and associated documentation; scan results from malicious code protection mechanisms; record of actions initiated by malicious code protection mechanisms in response to malicious code detection; system audit logs and records; other relevant documents or records]."
        },
        {
          "type": "Interview",
          "description": "[SELECT FROM: System or network administrators; personnel with information security responsibilities; personnel installing, configuring, and maintaining the system; personnel with responsibility for malicious code protection; personnel with configuration management responsibility]."
        },
        {
          "type": "Test",
          "description": "[SELECT FROM: Organizational processes for employing, updating, and configuring malicious code protection mechanisms; organizational process for addressing false positives and resulting potential impact; mechanisms supporting or implementing malicious code protection mechanisms (including updates and configurations); mechanisms supporting or implementing malicious code scanning and subsequent actions]."
        }
      ]
    },
    "last_ao_sentence": "real-time malicious code scans of files from external sources as files are downloaded, opened, or executed are performed."
  },
  {
    "text": "This is a NIST 800-171 control in the System and Information Integrity family. It corresponds to Level 2. The control ID is SI.L2-3.14.6 with title 'MONITOR COMMUNICATIONS FOR ATTACKS'. Security requirement: Monitor organizational systems, including inbound and outbound communications traffic, to detect attacks and indicators of potential attacks. Assessment objective (3.14.6[a]): the system is monitored to detect attacks and indicators of potential attacks.. POA&M allowed: No. SPRS score: 5.\nThis is a NIST 800-171 control in the System and Information Integrity family. It corresponds to Level 2. The control ID is SI.L2-3.14.6 with title 'MONITOR COMMUNICATIONS FOR ATTACKS'. Security requirement: Monitor organizational systems, including inbound and outbound communications traffic, to detect attacks and indicators of potential attacks. Assessment objective (3.14.6[b]): inbound communications traffic is monitored to detect attacks and indicators of potential attacks.. POA&M allowed: No. SPRS score: 5.\nThis is a NIST 800-171 control in the System and Information Integrity family. It corresponds to Level 2. The control ID is SI.L2-3.14.6 with title 'MONITOR COMMUNICATIONS FOR ATTACKS'. Security requirement: Monitor organizational systems, including inbound and outbound communications traffic, to detect attacks and indicators of potential attacks. Assessment objective (3.14.6[c]): outbound communications traffic is monitored to detect attacks and indicators of potential attacks.. POA&M allowed: No. SPRS score: 5.",
    "metadata": {
      "framework": "NIST 800-171",
      "family": "System and Information Integrity",
      "control_id": "3.14.6",
      "cmmc_id": "SI.L2-3.14.6",
      "title": "MONITOR COMMUNICATIONS FOR ATTACKS",
      "sprs": 5,
      "cmmc_levels": [
        "Level 2"
      ],
      "poam_allowed": "No",
      "ao_ids": [
        "3.14.6[a]",
        "3.14.6[b]",
        "3.14.6[c]"
      ],
      "assessment_methods": [
        {
          "type": "Examine",
          "description": "[SELECT FROM:  System and information integrity policy; procedures addressing system monitoring tools and techniques; continuous monitoring strategy; system and information integrity policy; procedures addressing system monitoring tools and techniques; facility diagram or layout; security plan; system design documentation; system monitoring tools and techniques documentation; locations within system where monitoring devices are deployed; system protocols; system configuration settings and associated documentation; system audit logs and records; other relevant documents or records]."
        },
        {
          "type": "Interview",
          "description": "[SELECT FROM: System or network administrators; personnel with information security responsibilities; personnel installing, configuring, and maintaining the system; personnel with responsibility monitoring the system; personnel with responsibility for the intrusion detection system]."
        },
        {
          "type": "Test",
          "description": "[SELECT FROM: Organizational processes for system monitoring; mechanisms supporting or implementing intrusion detection capability and system monitoring; mechanisms supporting or implementing system monitoring capability; organizational processes for intrusion detection and system monitoring; mechanisms supporting or implementing the monitoring of inbound and outbound communications traffic]."
        }
      ]
    },
    "last_ao_sentence": "outbound communications traffic is monitored to detect attacks and indicators of potential attacks."
  },
  {
    "text": "This is a NIST 800-171 control in the System and Information Integrity family. It corresponds to Level 2. The control ID is SI.L2-3.14.7 with title 'IDENTIFY UNAUTHORIZED USE'. Security requirement: Identify unauthorized use of organizational systems.. Assessment objective (3.14.7[a]): authorized use of the system is defined.. POA&M allowed: No. SPRS score: 3.\nThis is a NIST 800-171 control in the System and Information Integrity family. It corresponds to Level 2. The control ID is SI.L2-3.14.7 with title 'IDENTIFY UNAUTHORIZED USE'. Security requirement: Identify unauthorized use of organizational systems.. Assessment objective (3.14.7[b]): unauthorized use of the system is identified.. POA&M allowed: No. SPRS score: 3.",
    "metadata": {
      "framework": "NIST 800-171",
      "family": "System and Information Integrity",
      "control_id": "3.14.7",
      "cmmc_id": "SI.L2-3.14.7",
      "title": "IDENTIFY UNAUTHORIZED USE",
      "sprs": 3,
      "cmmc_levels": [
        "Level 2"
      ],
      "poam_allowed": "No",
      "ao_ids": [
        "3.14.7[a]",
        "3.14.7[b]"
      ],
      "assessment_methods": [
        {
          "type": "Examine",
          "description": "[SELECT FROM: Continuous monitoring strategy; system and information integrity policy; procedures addressing system monitoring tools and techniques; facility diagram/layout; security plan; system design documentation; system monitoring tools and techniques documentation; locations within system where monitoring devices are deployed; system configuration settings and associated documentation; other relevant documents or records]."
        },
        {
          "type": "Interview",
          "description": "[SELECT FROM: System or network administrators; personnel with information security responsibilities; personnel installing, configuring, and maintaining the system; personnel with responsibility for monitoring the system]."
        },
        {
          "type": "Test",
          "description": "[SELECT FROM: Organizational processes for system monitoring; mechanisms supporting or implementing system monitoring capability]."
        }
      ]
    },
    "last_ao_sentence": "unauthorized use of the system is identified."
  }
]